Workbook

Sheet Léeme
A1: Observatorios y portales de datos de Uruguay: inventario clasificado
A2: 170 recursos · taxonomía en facetas con correspondencia ODS · corte 08/10/2026
A4: Propósito | B4: Base única para el buscador temático y el análisis ecosistémico de cobertura. Cada recurso tiene un tema principal, temas secundarios, enfoques transversales explícitos, nivel de análisis y atributos de acceso.
A5: Inventario | B5: Registro completo. Las columnas con fondo crema se editan; las columnas en gris se calculan con fórmulas a partir de la taxonomía.
A6: Taxonomía temas | B6: 53 temas agrupados en 8 áreas, cada uno con ODS principal, metas de referencia, sinónimos de búsqueda y término para el Catálogo Nacional de Datos Abiertos.
A7: Enfoques | B7: Enfoques transversales y regla de asignación explícita.
A8: Niveles | B8: Escala de nivel de análisis (1 a 4).
A9: Cobertura temática | B9: Conteo por tema, estado de cobertura y alerta de concentración. Se recalcula al editar el inventario.
A10: Cobertura ODS | B10: Agregación de la cobertura por Objetivo de Desarrollo Sostenible.
A11: Cobertura enfoques | B11: Cobertura de cada enfoque transversal.
A12: Resumen | B12: Tablas de resumen: área por nivel de análisis, ámbito, tipo de recurso e instituciones con más recursos.
A13: Por confirmar | B13: Iniciativas sin portal público confirmado; no suman al inventario.
A14: Metodología | B14: Criterios del relevamiento original y criterios nuevos de clasificación y cobertura.
A15: Cómo agregar un recurso | B15: Copiar la última fila del inventario, completar las columnas crema y elegir tema principal, nivel y atributos en las listas desplegables. Los temas secundarios y enfoques se escriben como códigos separados por punto y coma (por ejemplo: T14; T25 / E01; E09).

Sheet Inventario
A1: ID | B1: Portal o recurso | C1: Institución responsable | D1: Ámbito | E1: Naturaleza institucional | F1: Tipo de recurso | G1: Alcance territorial | H1: Descripción breve | I1: Enlace | J1: Tema principal | K1: Código tema | L1: Temas secundarios (códigos) | M1: Todos los temas | N1: Área | O1: ODS principal | P1: Enfoques transversales | Q1: Nivel de análisis | R1: Descarga de datos | S1: API | T1: Desagregación territorial | U1: Desagregación por sexo | V1: Período de datos comprobado | W1: Vigencia comprobada | X1: Publicación / actualización comprobada | Y1: Portal o sistema relacionado | Z1: Notas de verificación | AA1: Fuentes de verificación | AB1: Fecha de relevamiento | AC1: Categoría original | AD1: Etiquetas originales | AE1: Incorporación
A2: UY-001 | B2: Análisis y estadísticas agropecuarias — OPYPA | C2: MGAP / OPYPA | D2: Nacional | E2: Público nacional | F2: Repositorio estadístico | G2: Nacional | H2: Análisis anual de cadenas agropecuarias, coyuntura y políticas sectoriales. | I2: https://www.gub.uy/ministerio-ganaderia-agricultura-pesca/opypa | J2: T04 · Agro y cadenas agroindustriales | K2: =LEFT(J2,3) -> T04 | L2: T01 | M2: =IF(L2="",K2,K2&"; "&L2) -> T04; T01 | N2: =INDEX('Taxonomía temas'!$D$2:$D$54,MATCH(K2,'Taxonomía temas'!$A$2:$A$54,0)) -> Economía y producción | O2: =INDEX('Taxonomía temas'!$F$2:$F$54,MATCH(K2,'Taxonomía temas'!$A$2:$A$54,0)) -> 2 | Q2: 4 · Análisis e informes | R2: Por verificar | S2: Por verificar | T2: Por verificar | U2: Por verificar | V2: 2025: anuario | W2: =IF(V2="","No","Sí") -> Sí | Z2: Repositorio de estudios; no equivale a un tablero en tiempo real. | AA2: https://www.gub.uy/ministerio-ganaderia-agricultura-pesca/opypa | AB2: 2026-10-02 | AC2: Productivo y económico | AD2: agro; economía; políticas; sectores | AE2: Relevamiento 02/10/2026
A3: UY-002 | B3: Centro de Información | C3: Uruguay XXI | D3: Nacional | E3: Público no estatal | F3: Portal estadístico | G3: Nacional | H3: Reúne informes comerciales, sectoriales, de inversión y herramientas estadísticas. | I3: https://www.uruguayxxi.gub.uy/es/centro-informacion/ | J3: T03 · Comercio exterior e inversión | K3: =LEFT(J3,3) -> T03 | L3: T07 | M3: =IF(L3="",K3,K3&"; "&L3) -> T03; T07 | N3: =INDEX('Taxonomía temas'!$D$2:$D$54,MATCH(K3,'Taxonomía temas'!$A$2:$A$54,0)) -> Economía y producción | O3: =INDEX('Taxonomía temas'!$F$2:$F$54,MATCH(K3,'Taxonomía temas'!$A$2:$A$54,0)) -> 17 | Q3: 4 · Análisis e informes | R3: Por verificar | S3: Por verificar | T3: Por verificar | U3: Por verificar | V3: Septiembre 2026: exportaciones | W3: =IF(V3="","No","Sí") -> Sí | Z3: Combina informes recurrentes y aplicaciones interactivas. | AA3: https://www.uruguayxxi.gub.uy/es/centro-informacion/ | AB3: 2026-10-02 | AC3: Productivo y económico | AD3: exportaciones; inversión; sectores; comercio-exterior | AE3: Relevamiento 02/10/2026
A4: UY-003 | B4: Centro de Información Logística | C4: INALOG | D4: Nacional | E4: Público no estatal | F4: Portal estadístico | G4: Nacional | H4: Informes sectoriales, análisis y estadísticas de operaciones logísticas del país. | I4: https://www.inalog.org.uy/centro-de-informacion/ | J4: T08 · Logística, transporte de cargas e infraestructura | K4: =LEFT(J4,3) -> T08 | L4: T03 | M4: =IF(L4="",K4,K4&"; "&L4) -> T08; T03 | N4: =INDEX('Taxonomía temas'!$D$2:$D$54,MATCH(K4,'Taxonomía temas'!$A$2:$A$54,0)) -> Economía y producción | O4: =INDEX('Taxonomía temas'!$F$2:$F$54,MATCH(K4,'Taxonomía temas'!$A$2:$A$54,0)) -> 9 | Q4: 2 · Indicadores y series | R4: Por verificar | S4: Por verificar | T4: Por verificar | U4: Por verificar | W4: =IF(V4="","No","Sí") -> No | Z4: El Sistema de Información Logística alimenta estudios; no se confirmó acceso público integral a su base. | AA4: https://www.inalog.org.uy/centro-de-informacion/ | AB4: 2026-10-02 | AC4: Productivo y económico | AD4: logística; puertos; cargas; comercio-exterior | AE4: Relevamiento 02/10/2026
A5: UY-004 | B5: Datos y estadísticas económicas | C5: MEF | D5: Nacional | E5: Público nacional | F5: Portal estadístico | G5: Nacional | H5: Información fiscal, deuda y otras series económicas del Ministerio de Economía y Finanzas. | I5: https://www.gub.uy/ministerio-economia-finanzas/datos-y-estadisticas/datos | J5: T02 · Finanzas públicas, tributación y presupuesto | K5: =LEFT(J5,3) -> T02 | L5: T01 | M5: =IF(L5="",K5,K5&"; "&L5) -> T02; T01 | N5: =INDEX('Taxonomía temas'!$D$2:$D$54,MATCH(K5,'Taxonomía temas'!$A$2:$A$54,0)) -> Economía y producción | O5: =INDEX('Taxonomía temas'!$F$2:$F$54,MATCH(K5,'Taxonomía temas'!$A$2:$A$54,0)) -> 17 | Q5: 2 · Indicadores y series | R5: Por verificar | S5: Por verificar | T5: Por verificar | U5: Por verificar | V5: Agosto 2026: resultado fiscal | W5: =IF(V5="","No","Sí") -> Sí | Z5: Las series tienen calendarios propios. | AA5: https://www.gub.uy/ministerio-economia-finanzas/datos-y-estadisticas/datos https://www.gub.uy/ministerio-economia-finanzas/ | AB5: 2026-10-02 | AC5: Productivo y económico | AD5: finanzas-públicas; macroeconomía; deuda | AE5: Relevamiento 02/10/2026
A6: UY-005 | B6: Estadísticas agropecuarias — DIEA | C6: MGAP / DIEA | D6: Nacional | E6: Público nacional | F6: Portal estadístico | G6: Nacional y departamental | H6: Censos, encuestas, anuarios y estadísticas de producción y mercado de tierras. | I6: https://www.gub.uy/ministerio-ganaderia-agricultura-pesca/diea | J6: T04 · Agro y cadenas agroindustriales | K6: =LEFT(J6,3) -> T04 | M6: =IF(L6="",K6,K6&"; "&L6) -> T04 | N6: =INDEX('Taxonomía temas'!$D$2:$D$54,MATCH(K6,'Taxonomía temas'!$A$2:$A$54,0)) -> Economía y producción | O6: =INDEX('Taxonomía temas'!$F$2:$F$54,MATCH(K6,'Taxonomía temas'!$A$2:$A$54,0)) -> 2 | Q6: 2 · Indicadores y series | R6: Por verificar | S6: Por verificar | T6: Por verificar | U6: Por verificar | V6: 2025: arrendamientos; 2024: censo | W6: =IF(V6="","No","Sí") -> Sí | X6: 2026-09-09 | Z6: Fecha indicada: publicación sobre arrendamientos 2025. | AA6: https://www.gub.uy/ministerio-ganaderia-agricultura-pesca/diea | AB6: 2026-10-02 | AC6: Productivo y económico | AD6: agro; tierras; censo-agropecuario; producción | AE6: Relevamiento 02/10/2026
A7: UY-006 | B7: Estadísticas de comercio y operaciones aduaneras | C7: Dirección Nacional de Aduanas | D7: Nacional | E7: Público nacional | F7: Portal estadístico | G7: Nacional | H7: Estadísticas de declaraciones aduaneras, movimientos comerciales y otros procedimientos. | I7: https://www.aduanas.gub.uy/innovaportal/v/4239/4/innova.front/estadisticas.html | J7: T03 · Comercio exterior e inversión | K7: =LEFT(J7,3) -> T03 | M7: =IF(L7="",K7,K7&"; "&L7) -> T03 | N7: =INDEX('Taxonomía temas'!$D$2:$D$54,MATCH(K7,'Taxonomía temas'!$A$2:$A$54,0)) -> Economía y producción | O7: =INDEX('Taxonomía temas'!$F$2:$F$54,MATCH(K7,'Taxonomía temas'!$A$2:$A$54,0)) -> 17 | Q7: 2 · Indicadores y series | R7: Por verificar | S7: Por verificar | T7: Por verificar | U7: Por verificar | W7: =IF(V7="","No","Sí") -> No | Z7: Conjuntos y períodos heterogéneos. | AA7: https://www.aduanas.gub.uy/innovaportal/v/4239/4/innova.front/estadisticas.html | AB7: 2026-10-02 | AC7: Productivo y económico | AD7: aduanas; comercio-exterior; encomiendas; incautaciones | AE7: Relevamiento 02/10/2026
A8: UY-007 | B8: Estadísticas de telecomunicaciones | C8: URSEC | D8: Nacional | E8: Público nacional | F8: Portal estadístico | G8: Nacional | H8: Informes e indicadores del mercado de telecomunicaciones. | I8: https://www.gub.uy/unidad-reguladora-servicios-comunicaciones/tematica/servicios-telecomunicaciones | J8: T10 · Telecomunicaciones y sociedad digital | K8: =LEFT(J8,3) -> T10 | M8: =IF(L8="",K8,K8&"; "&L8) -> T10 | N8: =INDEX('Taxonomía temas'!$D$2:$D$54,MATCH(K8,'Taxonomía temas'!$A$2:$A$54,0)) -> Ciencia, tecnología e innovación | O8: =INDEX('Taxonomía temas'!$F$2:$F$54,MATCH(K8,'Taxonomía temas'!$A$2:$A$54,0)) -> 9 | Q8: 2 · Indicadores y series | R8: Por verificar | S8: Por verificar | T8: Por verificar | U8: Por verificar | V8: Diciembre 2025 | W8: =IF(V8="","No","Sí") -> Sí | X8: 2026-07-10 | Z8: Fecha de publicación del informe con datos a diciembre de 2025. | AA8: https://www.gub.uy/unidad-reguladora-servicios-comunicaciones/tematica/servicios-telecomunicaciones | AB8: 2026-10-02 | AC8: Productivo y económico | AD8: telecomunicaciones; conectividad; mercados; digital | AE8: Relevamiento 02/10/2026
A9: UY-008 | B9: Estadísticas e indicadores económicos | C9: BCU | D9: Nacional | E9: Público nacional | F9: Portal estadístico | G9: Nacional | H9: Series monetarias, financieras, cambiarias, de actividad y de relaciones económicas con el exterior. | I9: https://www.bcu.gub.uy/Estadisticas-e-Indicadores/Paginas/default.aspx | J9: T01 · Macroeconomía y cuentas nacionales | K9: =LEFT(J9,3) -> T01 | L9: T03 | M9: =IF(L9="",K9,K9&"; "&L9) -> T01; T03 | N9: =INDEX('Taxonomía temas'!$D$2:$D$54,MATCH(K9,'Taxonomía temas'!$A$2:$A$54,0)) -> Economía y producción | O9: =INDEX('Taxonomía temas'!$F$2:$F$54,MATCH(K9,'Taxonomía temas'!$A$2:$A$54,0)) -> 8 | Q9: 2 · Indicadores y series | R9: Por verificar | S9: Por verificar | T9: Por verificar | U9: Por verificar | V9: Junio 2026: IMAE | W9: =IF(V9="","No","Sí") -> Sí | Z9: El período indicado corresponde a una serie, no a todas. | AA9: https://www.bcu.gub.uy/Estadisticas-e-Indicadores/Paginas/default.aspx | AB9: 2026-10-02 | AC9: Productivo y económico | AD9: macroeconomía; cuentas-nacionales; finanzas; sector-externo | AE9: Relevamiento 02/10/2026
A10: UY-009 | B10: Estadísticas portuarias de Montevideo | C10: Administración Nacional de Puertos | D10: Nacional | E10: Público nacional | F10: Repositorio estadístico | G10: Puerto de Montevideo | H10: Series mensuales de operaciones y tráfico portuario. | I10: https://anp.com.uy/index.php/es/inicio/puertos/comerciales/montevideo/estadisticas/estadistica-por-mes-unidad-gestion-de-trafico | J10: T08 · Logística, transporte de cargas e infraestructura | K10: =LEFT(J10,3) -> T08 | L10: T03 | M10: =IF(L10="",K10,K10&"; "&L10) -> T08; T03 | N10: =INDEX('Taxonomía temas'!$D$2:$D$54,MATCH(K10,'Taxonomía temas'!$A$2:$A$54,0)) -> Economía y producción | O10: =INDEX('Taxonomía temas'!$F$2:$F$54,MATCH(K10,'Taxonomía temas'!$A$2:$A$54,0)) -> 9 | Q10: 2 · Indicadores y series | R10: Por verificar | S10: Por verificar | T10: Por verificar | U10: Por verificar | V10: Junio 2026 | W10: =IF(V10="","No","Sí") -> Sí | Z10: Alcance del enlace: Unidad de Gestión de Tráfico de Montevideo. | AA10: https://anp.com.uy/index.php/es/inicio/puertos/comerciales/montevideo/estadisticas/estadistica-por-mes-unidad-gestion-de-trafico | AB10: 2026-10-02 | AC10: Productivo y económico | AD10: puertos; logística; cargas; transporte | AE10: Relevamiento 02/10/2026
A11: UY-010 | B11: Estadísticas vitivinícolas | C11: INAVI | D11: Nacional | E11: Público no estatal | F11: Portal estadístico | G11: Nacional | H11: Información estadística de viñedos, elaboración, existencias, comercialización y comercio exterior. | I11: https://inavi.com.uy/estadisticas/ | J11: T04 · Agro y cadenas agroindustriales | K11: =LEFT(J11,3) -> T04 | L11: T03 | M11: =IF(L11="",K11,K11&"; "&L11) -> T04; T03 | N11: =INDEX('Taxonomía temas'!$D$2:$D$54,MATCH(K11,'Taxonomía temas'!$A$2:$A$54,0)) -> Economía y producción | O11: =INDEX('Taxonomía temas'!$F$2:$F$54,MATCH(K11,'Taxonomía temas'!$A$2:$A$54,0)) -> 2 | Q11: 2 · Indicadores y series | R11: Por verificar | S11: Por verificar | T11: Por verificar | U11: Por verificar | W11: =IF(V11="","No","Sí") -> No | Z11: Años disponibles mediante selección; último año no comprobado. | AA11: https://inavi.com.uy/estadisticas/ | AB11: 2026-10-02 | AC11: Productivo y económico | AD11: vitivinicultura; producción; ventas; exportaciones | AE11: Relevamiento 02/10/2026
A12: UY-011 | B12: Estudios económicos de la construcción | C12: Cámara de la Construcción del Uruguay | D12: Nacional | E12: Sector empresarial | F12: Repositorio estadístico | G12: Nacional | H12: Informes de actividad, empleo, precios, mercado inmobiliario y accidentes del sector. | I12: https://sitio.ccu.com.uy/estudios-economicos/ | J12: T09 · Precios, consumo y construcción | K12: =LEFT(J12,3) -> T09 | L12: T14 | M12: =IF(L12="",K12,K12&"; "&L12) -> T09; T14 | N12: =INDEX('Taxonomía temas'!$D$2:$D$54,MATCH(K12,'Taxonomía temas'!$A$2:$A$54,0)) -> Economía y producción | O12: =INDEX('Taxonomía temas'!$F$2:$F$54,MATCH(K12,'Taxonomía temas'!$A$2:$A$54,0)) -> 12 | Q12: 4 · Análisis e informes | R12: Por verificar | S12: Por verificar | T12: Por verificar | U12: Por verificar | V12: Abril 2025: índices de precios | W12: =IF(V12="","No","Sí") -> Sí | Z12: Período confirmado solo para los índices encontrados. | AA12: https://sitio.ccu.com.uy/estudios-economicos/ https://sitio.ccu.com.uy/estudios-economicos/precios-indicadores-financieros-y-de-interes/indicadores-de-precios/ | AB12: 2026-10-02 | AC12: Productivo y económico | AD12: construcción; empleo; precios; inmuebles | AE12: Relevamiento 02/10/2026
A13: UY-012 | B13: Explorador de datos forestales | C13: MGAP / Dirección General Forestal | D13: Nacional | E13: Público nacional | F13: Visualizador | G13: Nacional y departamental | H13: Consulta visual de superficie forestal, producción y comercio de productos forestales. | I13: https://www.gub.uy/ministerio-ganaderia-agricultura-pesca/pagina-embebida/datos-forestales | J13: T04 · Agro y cadenas agroindustriales | K13: =LEFT(J13,3) -> T04 | L13: T03 | M13: =IF(L13="",K13,K13&"; "&L13) -> T04; T03 | N13: =INDEX('Taxonomía temas'!$D$2:$D$54,MATCH(K13,'Taxonomía temas'!$A$2:$A$54,0)) -> Economía y producción | O13: =INDEX('Taxonomía temas'!$F$2:$F$54,MATCH(K13,'Taxonomía temas'!$A$2:$A$54,0)) -> 2 | Q13: 3 · Visualización interactiva | R13: Por verificar | S13: Por verificar | T13: Por verificar | U13: Por verificar | V13: 2025; cartografía 2024 | W13: =IF(V13="","No","Sí") -> Sí | X13: 2026-08-11 | Z13: Lanzamiento del explorador en agosto de 2026; incluye series desde 1975. | AA13: https://www.gub.uy/ministerio-ganaderia-agricultura-pesca/pagina-embebida/datos-forestales https://www.gub.uy/ministerio-ganaderia-agricultura-pesca/noticias/explorador-interactivo-forestal | AB13: 2026-10-02 | AC13: Productivo y económico | AD13: forestación; superficie; producción; exportaciones | AE13: Relevamiento 02/10/2026
A14: UY-013 | B14: Indicadores del sector lácteo | C14: INALE | D14: Nacional | E14: Público no estatal | F14: Portal estadístico | G14: Nacional | H14: Indicadores sobre producción, remisión, precios y comercio de productos lácteos. | I14: https://www.inale.org/ | J14: T04 · Agro y cadenas agroindustriales | K14: =LEFT(J14,3) -> T04 | L14: T03 | M14: =IF(L14="",K14,K14&"; "&L14) -> T04; T03 | N14: =INDEX('Taxonomía temas'!$D$2:$D$54,MATCH(K14,'Taxonomía temas'!$A$2:$A$54,0)) -> Economía y producción | O14: =INDEX('Taxonomía temas'!$F$2:$F$54,MATCH(K14,'Taxonomía temas'!$A$2:$A$54,0)) -> 2 | Q14: 2 · Indicadores y series | R14: Por verificar | S14: Por verificar | T14: Por verificar | U14: Por verificar | V14: Septiembre 2026: indicadores mensuales | W14: =IF(V14="","No","Sí") -> Sí | X14: 2026-10-01 | Z14: Acceso desde la portada institucional; cada serie tiene su propio corte. | AA14: https://www.inale.org/ | AB14: 2026-10-02 | AC14: Productivo y económico | AD14: lechería; precios; remisión; exportaciones | AE14: Relevamiento 02/10/2026
A15: UY-014 | B15: Monitor de Coyuntura Económica | C15: Universidad Católica del Uruguay | D15: Nacional | E15: Académico | F15: Monitor | G15: Nacional | H15: Seguimiento periódico de indicadores económicos y análisis de coyuntura. | I15: https://www.ucu.edu.uy/Institucionales/MONITOR-DE-COYUNTURA-uc1457 | J15: T01 · Macroeconomía y cuentas nacionales | K15: =LEFT(J15,3) -> T01 | L15: T14; T09 | M15: =IF(L15="",K15,K15&"; "&L15) -> T01; T14; T09 | N15: =INDEX('Taxonomía temas'!$D$2:$D$54,MATCH(K15,'Taxonomía temas'!$A$2:$A$54,0)) -> Economía y producción | O15: =INDEX('Taxonomía temas'!$F$2:$F$54,MATCH(K15,'Taxonomía temas'!$A$2:$A$54,0)) -> 8 | Q15: 4 · Análisis e informes | R15: Por verificar | S15: Por verificar | T15: Por verificar | U15: Por verificar | W15: =IF(V15="","No","Sí") -> No | X15: 2026-09-29 | Z15: Fecha de publicación del monitor; último período de cada serie no auditado. | AA15: https://www.ucu.edu.uy/Institucionales/MONITOR-DE-COYUNTURA-uc1457 | AB15: 2026-10-02 | AC15: Productivo y económico | AD15: macroeconomía; actividad; empleo; precios | AE15: Relevamiento 02/10/2026
A16: UY-015 | B16: Monitor de Inversión Extranjera Directa | C16: Uruguay XXI | D16: Nacional | E16: Público no estatal | F16: Repositorio estadístico | G16: Nacional | H16: Informes periódicos sobre inversión extranjera y empresas internacionales en Uruguay. | I16: https://www.uruguayxxi.gub.uy/es/centro-informacion/inversor/informes/informes-de-mensual/ | J16: T03 · Comercio exterior e inversión | K16: =LEFT(J16,3) -> T03 | L16: T07 | M16: =IF(L16="",K16,K16&"; "&L16) -> T03; T07 | N16: =INDEX('Taxonomía temas'!$D$2:$D$54,MATCH(K16,'Taxonomía temas'!$A$2:$A$54,0)) -> Economía y producción | O16: =INDEX('Taxonomía temas'!$F$2:$F$54,MATCH(K16,'Taxonomía temas'!$A$2:$A$54,0)) -> 17 | Q16: 4 · Análisis e informes | R16: Por verificar | S16: Por verificar | T16: Por verificar | U16: Por verificar | W16: =IF(V16="","No","Sí") -> No | Y16: Centro de Información — Uruguay XXI | Z16: Se localizó edición de abril de 2026; no se trasladó esa fecha al período de todos los datos. | AA16: https://www.uruguayxxi.gub.uy/es/centro-informacion/inversor/informes/informes-de-mensual/ | AB16: 2026-10-02 | AC16: Productivo y económico | AD16: inversión-extranjera; empresas; sector-externo | AE16: Relevamiento 02/10/2026
A17: UY-016 | B17: Monitor Macroeconómico | C17: Uruguay XXI | D17: Nacional | E17: Público no estatal | F17: Módulo | G17: Nacional | H17: Indicadores seleccionados para seguir el contexto económico uruguayo. | I17: https://www.uruguayxxi.gub.uy/es/centro-informacion/monitor-macroeconomico/ | J17: T01 · Macroeconomía y cuentas nacionales | K17: =LEFT(J17,3) -> T01 | L17: T14; T09 | M17: =IF(L17="",K17,K17&"; "&L17) -> T01; T14; T09 | N17: =INDEX('Taxonomía temas'!$D$2:$D$54,MATCH(K17,'Taxonomía temas'!$A$2:$A$54,0)) -> Economía y producción | O17: =INDEX('Taxonomía temas'!$F$2:$F$54,MATCH(K17,'Taxonomía temas'!$A$2:$A$54,0)) -> 8 | Q17: 3 · Visualización interactiva | R17: Por verificar | S17: Por verificar | T17: Por verificar | U17: Por verificar | W17: =IF(V17="","No","Sí") -> No | Y17: Centro de Información — Uruguay XXI | Z17: Consultar fecha de cada indicador. | AA17: https://www.uruguayxxi.gub.uy/es/centro-informacion/monitor-macroeconomico/ | AB17: 2026-10-02 | AC17: Productivo y económico | AD17: macroeconomía; actividad; precios; empleo | AE17: Relevamiento 02/10/2026
A18: UY-017 | B18: Monitor Mipymes | C18: ANDE | D18: Nacional | E18: Público no estatal | F18: Monitor | G18: Nacional | H18: Empresas, empleo, ventas, emprendimientos y financiamiento de las mipymes. | I18: https://monitor.ande.org.uy/home.aspx | J18: T07 · Empresas, mipymes y emprendimiento | K18: =LEFT(J18,3) -> T07 | L18: T14 | M18: =IF(L18="",K18,K18&"; "&L18) -> T07; T14 | N18: =INDEX('Taxonomía temas'!$D$2:$D$54,MATCH(K18,'Taxonomía temas'!$A$2:$A$54,0)) -> Economía y producción | O18: =INDEX('Taxonomía temas'!$F$2:$F$54,MATCH(K18,'Taxonomía temas'!$A$2:$A$54,0)) -> 8 | P18: E01 · Género | Q18: 3 · Visualización interactiva | R18: Por verificar | S18: Por verificar | T18: Por verificar | U18: Sí | V18: 2.º trimestre 2026; mayo 2026 en series mensuales | W18: =IF(V18="","No","Sí") -> Sí | Z18: Las series anuales tienen distintos rezagos: empresas y ventas 2024; empleo 2025. | AA18: https://monitor.ande.org.uy/home.aspx | AB18: 2026-10-02 | AC18: Productivo y económico | AD18: mipymes; empresas; empleo; género; microfinanzas | AE18: Relevamiento 02/10/2026
A19: UY-018 | B19: Monitoreo Industrial | C19: Cámara de Industrias del Uruguay | D19: Nacional | E19: Sector empresarial | F19: Monitor | G19: Nacional | H19: Series, encuestas e informes recurrentes sobre desempeño de la industria. | I19: https://www.ciu.com.uy/monitoreo-industrial/ | J19: T05 · Industria y manufactura | K19: =LEFT(J19,3) -> T05 | L19: T14; T03 | M19: =IF(L19="",K19,K19&"; "&L19) -> T05; T14; T03 | N19: =INDEX('Taxonomía temas'!$D$2:$D$54,MATCH(K19,'Taxonomía temas'!$A$2:$A$54,0)) -> Economía y producción | O19: =INDEX('Taxonomía temas'!$F$2:$F$54,MATCH(K19,'Taxonomía temas'!$A$2:$A$54,0)) -> 9 | Q19: 3 · Visualización interactiva | R19: Por verificar | S19: Por verificar | T19: Por verificar | U19: Por verificar | V19: Agosto 2026: comercio exterior | W19: =IF(V19="","No","Sí") -> Sí | X19: 2026-09-17 | Z19: Incluye distintas frecuencias según producto. | AA19: https://www.ciu.com.uy/monitoreo-industrial/ | AB19: 2026-10-02 | AC19: Productivo y económico | AD19: industria; precios; empleo; expectativas; comercio-exterior | AE19: Relevamiento 02/10/2026
A20: UY-019 | B20: Observatorio de Oleaginosos | C20: Mesa Tecnológica de Oleaginosos | D20: Nacional | E20: Sector empresarial | F20: Observatorio | G20: Nacional | H20: Informes e indicadores de desempeño de cultivos y cadenas de oleaginosos. | I20: https://oleaginosos.org.uy/observatorio | J20: T04 · Agro y cadenas agroindustriales | K20: =LEFT(J20,3) -> T04 | M20: =IF(L20="",K20,K20&"; "&L20) -> T04 | N20: =INDEX('Taxonomía temas'!$D$2:$D$54,MATCH(K20,'Taxonomía temas'!$A$2:$A$54,0)) -> Economía y producción | O20: =INDEX('Taxonomía temas'!$F$2:$F$54,MATCH(K20,'Taxonomía temas'!$A$2:$A$54,0)) -> 2 | Q20: 4 · Análisis e informes | R20: Por verificar | S20: Por verificar | T20: Por verificar | U20: Por verificar | V20: Zafra 2024/2025 | W20: =IF(V20="","No","Sí") -> Sí | Z20: Fuente sectorial e interinstitucional. | AA20: https://oleaginosos.org.uy/observatorio | AB20: 2026-10-02 | AC20: Productivo y económico | AD20: agricultura; oleaginosos; soja; zafras | AE20: Relevamiento 02/10/2026
A21: UY-020 | B21: Observatorio Económico de Salto | C21: Universidad Católica del Uruguay | D21: Nacional | E21: Académico | F21: Observatorio | G21: Salto y frontera | H21: Estudios e indicadores sobre economía regional y diferencias de precios en la frontera. | I21: https://www.ucu.edu.uy/Institucionales/OBSERVATORIO-ECONOMICO-DE-SALTO-uc2511 | J21: T09 · Precios, consumo y construcción | K21: =LEFT(J21,3) -> T09 | L21: T01 | M21: =IF(L21="",K21,K21&"; "&L21) -> T09; T01 | N21: =INDEX('Taxonomía temas'!$D$2:$D$54,MATCH(K21,'Taxonomía temas'!$A$2:$A$54,0)) -> Economía y producción | O21: =INDEX('Taxonomía temas'!$F$2:$F$54,MATCH(K21,'Taxonomía temas'!$A$2:$A$54,0)) -> 12 | P21: E09 · Territorial y subnacional | Q21: 4 · Análisis e informes | R21: Por verificar | S21: Por verificar | T21: Sí | U21: Por verificar | W21: =IF(V21="","No","Sí") -> No | Z21: Última edición no comprobada. | AA21: https://www.ucu.edu.uy/Institucionales/OBSERVATORIO-ECONOMICO-DE-SALTO-uc2511 | AB21: 2026-10-02 | AC21: Productivo y económico | AD21: frontera; precios; comercio; economía-regional | AE21: Relevamiento 02/10/2026
A22: UY-021 | B22: Observatorio Granjero | C22: UAM / MGAP | D22: Nacional | E22: Interinstitucional / mixto | F22: Observatorio | G22: Nacional | H22: Boletines de precios mayoristas, oferta y análisis de productos hortifrutícolas. | I22: https://uam.com.uy/boletin-de-precios-mayoristas/ | J22: T04 · Agro y cadenas agroindustriales | K22: =LEFT(J22,3) -> T04 | L22: T09 | M22: =IF(L22="",K22,K22&"; "&L22) -> T04; T09 | N22: =INDEX('Taxonomía temas'!$D$2:$D$54,MATCH(K22,'Taxonomía temas'!$A$2:$A$54,0)) -> Economía y producción | O22: =INDEX('Taxonomía temas'!$F$2:$F$54,MATCH(K22,'Taxonomía temas'!$A$2:$A$54,0)) -> 2 | Q22: 4 · Análisis e informes | R22: Por verificar | S22: Por verificar | T22: Por verificar | U22: Por verificar | W22: =IF(V22="","No","Sí") -> No | Z22: Entrada por boletines de UAM; fecha del último boletín no comprobada. | AA22: https://uam.com.uy/boletin-de-precios-mayoristas/ | AB22: 2026-10-02 | AC22: Productivo y económico | AD22: horticultura; fruticultura; precios; mercados | AE22: Relevamiento 02/10/2026
A23: UY-022 | B23: Observatorio Industrial | C23: MIEM | D23: Nacional | E23: Público nacional | F23: Observatorio | G23: Nacional | H23: Indicadores y análisis sobre actividad manufacturera, estructura industrial y desempeño sectorial. | I23: https://observatorio.miem.gub.uy/obs/ | J23: T05 · Industria y manufactura | K23: =LEFT(J23,3) -> T05 | L23: T14 | M23: =IF(L23="",K23,K23&"; "&L23) -> T05; T14 | N23: =INDEX('Taxonomía temas'!$D$2:$D$54,MATCH(K23,'Taxonomía temas'!$A$2:$A$54,0)) -> Economía y producción | O23: =INDEX('Taxonomía temas'!$F$2:$F$54,MATCH(K23,'Taxonomía temas'!$A$2:$A$54,0)) -> 9 | Q23: 4 · Análisis e informes | R23: Por verificar | S23: Por verificar | T23: Por verificar | U23: Por verificar | V23: Julio 2026: IVF | W23: =IF(V23="","No","Sí") -> Sí | Z23: Contenido indexado; el tablero dinámico no pudo auditarse íntegramente. | AA23: https://observatorio.miem.gub.uy/obs/ | AB23: 2026-10-02 | AC23: Productivo y económico | AD23: industria; producción; empleo; inversión | AE23: Relevamiento 02/10/2026
A24: UY-023 | B24: Observatorio TI | C24: CUTI | D24: Nacional | E24: Sector empresarial | F24: Observatorio | G24: Nacional | H24: Indicadores de empresas tecnológicas, talento, empleo y exportaciones del sector. | I24: https://observatorioti.cuti.org.uy/ | J24: T13 · Sector tecnológico y software | K24: =LEFT(J24,3) -> T13 | L24: T14; T03; T11 | M24: =IF(L24="",K24,K24&"; "&L24) -> T13; T14; T03; T11 | N24: =INDEX('Taxonomía temas'!$D$2:$D$54,MATCH(K24,'Taxonomía temas'!$A$2:$A$54,0)) -> Ciencia, tecnología e innovación | O24: =INDEX('Taxonomía temas'!$F$2:$F$54,MATCH(K24,'Taxonomía temas'!$A$2:$A$54,0)) -> 9 | Q24: 4 · Análisis e informes | R24: Por verificar | S24: Por verificar | T24: Por verificar | U24: Por verificar | V24: 2024: encuesta sectorial | W24: =IF(V24="","No","Sí") -> Sí | Z24: No confundir el año de publicación con el período de la encuesta. | AA24: https://observatorioti.cuti.org.uy/ | AB24: 2026-10-02 | AC24: Productivo y económico | AD24: tecnologías-digitales; software; empleo; exportaciones | AE24: Relevamiento 02/10/2026
A25: UY-024 | B25: Observatorio Turístico de Montevideo | C25: Intendencia de Montevideo | D25: Departamental | E25: Gobierno departamental | F25: Módulo | G25: Montevideo | H25: Información e indicadores para analizar el turismo del departamento. | I25: https://www.descubrimontevideo.uy/macrodatos/ | J25: T06 · Turismo | K25: =LEFT(J25,3) -> T06 | M25: =IF(L25="",K25,K25&"; "&L25) -> T06 | N25: =INDEX('Taxonomía temas'!$D$2:$D$54,MATCH(K25,'Taxonomía temas'!$A$2:$A$54,0)) -> Economía y producción | O25: =INDEX('Taxonomía temas'!$F$2:$F$54,MATCH(K25,'Taxonomía temas'!$A$2:$A$54,0)) -> 8 | P25: E09 · Territorial y subnacional | Q25: 3 · Visualización interactiva | R25: Por verificar | S25: Por verificar | T25: Sí | U25: Por verificar | W25: =IF(V25="","No","Sí") -> No | Y25: Montevidata | Z25: Se accede desde Montevidata al sitio Descubrí Montevideo. | AA25: https://www.descubrimontevideo.uy/macrodatos/ | AB25: 2026-10-02 | AC25: Productivo y económico | AD25: montevideo; turismo; visitantes; gasto | AE25: Relevamiento 02/10/2026
A26: UY-025 | B26: Observatorio Turístico Inteligente | C26: Ministerio de Turismo | D26: Nacional | E26: Público nacional | F26: Observatorio | G26: Nacional | H26: Herramientas para analizar turismo receptivo, emisivo, interno y de cruceros. | I26: https://turismo.gub.uy/observatorio/index.html | J26: T06 · Turismo | K26: =LEFT(J26,3) -> T06 | M26: =IF(L26="",K26,K26&"; "&L26) -> T06 | N26: =INDEX('Taxonomía temas'!$D$2:$D$54,MATCH(K26,'Taxonomía temas'!$A$2:$A$54,0)) -> Economía y producción | O26: =INDEX('Taxonomía temas'!$F$2:$F$54,MATCH(K26,'Taxonomía temas'!$A$2:$A$54,0)) -> 8 | Q26: 4 · Análisis e informes | R26: Por verificar | S26: Por verificar | T26: Por verificar | U26: Por verificar | V26: 1.er trimestre 2026: informe receptivo | W26: =IF(V26="","No","Sí") -> Sí | Z26: El período corresponde al informe localizado; otros paneles pueden tener distinto corte. | AA26: https://turismo.gub.uy/observatorio/index.html https://www.gub.uy/ministerio-turismo/tematica/observatorios-turisticos | AB26: 2026-10-02 | AC26: Productivo y económico | AD26: turismo; visitantes; gasto; cruceros | AE26: Relevamiento 02/10/2026
A27: UY-026 | B27: Publicaciones, informes y series de la cadena cárnica | C27: INAC | D27: Nacional | E27: Público no estatal | F27: Portal estadístico | G27: Nacional | H27: Series e informes sobre faena, precios, exportaciones y desempeño de la cadena cárnica. | I27: https://www.inac.uy/innovaportal/v/26276/37/innova.bs/publicaciones-informes-y-series | J27: T04 · Agro y cadenas agroindustriales | K27: =LEFT(J27,3) -> T04 | L27: T03; T09 | M27: =IF(L27="",K27,K27&"; "&L27) -> T04; T03; T09 | N27: =INDEX('Taxonomía temas'!$D$2:$D$54,MATCH(K27,'Taxonomía temas'!$A$2:$A$54,0)) -> Economía y producción | O27: =INDEX('Taxonomía temas'!$F$2:$F$54,MATCH(K27,'Taxonomía temas'!$A$2:$A$54,0)) -> 2 | Q27: 2 · Indicadores y series | R27: Por verificar | S27: Por verificar | T27: Por verificar | U27: Por verificar | V27: 2025: anuario | W27: =IF(V27="","No","Sí") -> Sí | Z27: Los indicadores semanales pueden ser más recientes que el anuario. | AA27: https://www.inac.uy/innovaportal/v/26276/37/innova.bs/publicaciones-informes-y-series | AB27: 2026-10-02 | AC27: Productivo y económico | AD27: ganadería; carne; faena; exportaciones; precios | AE27: Relevamiento 02/10/2026
A28: UY-027 | B28: Recaudación anual y mensual por impuesto | C28: DGI | D28: Nacional | E28: Público nacional | F28: Repositorio estadístico | G28: Nacional | H28: Series de ingresos tributarios desagregadas por impuesto y período. | I28: https://www.gub.uy/direccion-general-impositiva/datos-y-estadisticas/estadisticas/recaudacion-anual-mensual-impuesto | J28: T02 · Finanzas públicas, tributación y presupuesto | K28: =LEFT(J28,3) -> T02 | M28: =IF(L28="",K28,K28&"; "&L28) -> T02 | N28: =INDEX('Taxonomía temas'!$D$2:$D$54,MATCH(K28,'Taxonomía temas'!$A$2:$A$54,0)) -> Economía y producción | O28: =INDEX('Taxonomía temas'!$F$2:$F$54,MATCH(K28,'Taxonomía temas'!$A$2:$A$54,0)) -> 17 | Q28: 2 · Indicadores y series | R28: Por verificar | S28: Por verificar | T28: Por verificar | U28: Por verificar | V28: Julio 2026 | W28: =IF(V28="","No","Sí") -> Sí | X28: 2026-10-01 | Z28: Fecha de actualización de la página consultada. | AA28: https://www.gub.uy/direccion-general-impositiva/datos-y-estadisticas/estadisticas/recaudacion-anual-mensual-impuesto | AB28: 2026-10-02 | AC28: Productivo y económico | AD28: tributación; recaudación; finanzas-públicas | AE28: Relevamiento 02/10/2026
A29: UY-028 | B29: Series históricas agropecuarias | C29: MGAP | D29: Nacional | E29: Público nacional | F29: Base de datos | G29: Nacional | H29: Consulta de series históricas de indicadores agropecuarios. | I29: https://www.mgap.gub.uy/SeriesHistoricas/hshistoricas.aspx | J29: T04 · Agro y cadenas agroindustriales | K29: =LEFT(J29,3) -> T04 | M29: =IF(L29="",K29,K29&"; "&L29) -> T04 | N29: =INDEX('Taxonomía temas'!$D$2:$D$54,MATCH(K29,'Taxonomía temas'!$A$2:$A$54,0)) -> Economía y producción | O29: =INDEX('Taxonomía temas'!$F$2:$F$54,MATCH(K29,'Taxonomía temas'!$A$2:$A$54,0)) -> 2 | Q29: 1 · Datos | R29: Por verificar | S29: Por verificar | T29: Por verificar | U29: Por verificar | W29: =IF(V29="","No","Sí") -> No | Z29: El acceso observado solicita registro. | AA29: https://www.mgap.gub.uy/SeriesHistoricas/hshistoricas.aspx | AB29: 2026-10-02 | AC29: Productivo y económico | AD29: agro; series-históricas; producción | AE29: Relevamiento 02/10/2026
A30: UY-029 | B30: Sistema de estadísticas de comercio exterior | C30: Uruguay XXI | D30: Nacional | E30: Público no estatal | F30: Módulo | G30: Nacional | H30: Consulta de flujos comerciales por producto, mercado y período. | I30: https://herramientas.uruguayxxi.gub.uy/sistema_de_estadistica/ | J30: T03 · Comercio exterior e inversión | K30: =LEFT(J30,3) -> T03 | M30: =IF(L30="",K30,K30&"; "&L30) -> T03 | N30: =INDEX('Taxonomía temas'!$D$2:$D$54,MATCH(K30,'Taxonomía temas'!$A$2:$A$54,0)) -> Economía y producción | O30: =INDEX('Taxonomía temas'!$F$2:$F$54,MATCH(K30,'Taxonomía temas'!$A$2:$A$54,0)) -> 17 | Q30: 3 · Visualización interactiva | R30: Por verificar | S30: Por verificar | T30: Por verificar | U30: Por verificar | W30: =IF(V30="","No","Sí") -> No | Y30: Centro de Información — Uruguay XXI | Z30: Último período disponible no comprobado. | AA30: https://herramientas.uruguayxxi.gub.uy/sistema_de_estadistica/ | AB30: 2026-10-02 | AC30: Productivo y económico | AD30: exportaciones; importaciones; productos; destinos | AE30: Relevamiento 02/10/2026
A31: UY-030 | B31: Sistema de Información de Precios al Consumidor | C31: MEF / Defensa del Consumidor | D31: Nacional | E31: Público nacional | F31: Monitor | G31: Nacional | H31: Comparación de precios de productos y establecimientos para consumidores. | I31: https://www.precios.uy/ | J31: T09 · Precios, consumo y construcción | K31: =LEFT(J31,3) -> T09 | M31: =IF(L31="",K31,K31&"; "&L31) -> T09 | N31: =INDEX('Taxonomía temas'!$D$2:$D$54,MATCH(K31,'Taxonomía temas'!$A$2:$A$54,0)) -> Economía y producción | O31: =INDEX('Taxonomía temas'!$F$2:$F$54,MATCH(K31,'Taxonomía temas'!$A$2:$A$54,0)) -> 12 | Q31: 3 · Visualización interactiva | R31: Por verificar | S31: Por verificar | T31: Por verificar | U31: Por verificar | W31: =IF(V31="","No","Sí") -> No | Z31: Actualización por producto y establecimiento; último corte no comprobado. | AA31: https://www.precios.uy/ | AB31: 2026-10-02 | AC31: Productivo y económico | AD31: precios; consumo; comercio | AE31: Relevamiento 02/10/2026
A32: UY-031 | B32: Sistema Nacional de Información Agropecuaria — SNIA | C32: MGAP | D32: Nacional | E32: Público nacional | F32: Geoportal | G32: Nacional | H32: Integración de información agropecuaria y acceso a visores temáticos. | I32: https://www.snia.gub.uy/dibujos/arbol-de-visores | J32: T04 · Agro y cadenas agroindustriales | K32: =LEFT(J32,3) -> T04 | L32: T35; T37; T41 | M32: =IF(L32="",K32,K32&"; "&L32) -> T04; T35; T37; T41 | N32: =INDEX('Taxonomía temas'!$D$2:$D$54,MATCH(K32,'Taxonomía temas'!$A$2:$A$54,0)) -> Economía y producción | O32: =INDEX('Taxonomía temas'!$F$2:$F$54,MATCH(K32,'Taxonomía temas'!$A$2:$A$54,0)) -> 2 | Q32: 3 · Visualización interactiva | R32: Por verificar | S32: Por verificar | T32: Sí | U32: Por verificar | W32: =IF(V32="","No","Sí") -> No | Z32: Enlace del directorio oficial IDE; carga del destino no confirmada. | AA32: https://www.gub.uy/infraestructura-datos-espaciales/nodos-ideuy | AB32: 2026-10-02 | AC32: Productivo y económico | AD32: agro; geodatos; clima; suelos | AE32: Relevamiento 02/10/2026
A33: UY-032 | B33: Visor CONEAT, suelos y campo natural | C33: MGAP / DGRN | D33: Nacional | E33: Público nacional | F33: Geoportal | G33: Nacional | H33: Cartografía de grupos de suelos, productividad y recursos naturales de uso agropecuario. | I33: https://dgrn.mgap.gub.uy/js/visores/dgrn/ | J33: T37 · Suelos, geología y recursos naturales | K33: =LEFT(J33,3) -> T37 | L33: T04; T41 | M33: =IF(L33="",K33,K33&"; "&L33) -> T37; T04; T41 | N33: =INDEX('Taxonomía temas'!$D$2:$D$54,MATCH(K33,'Taxonomía temas'!$A$2:$A$54,0)) -> Ambiente, energía y clima | O33: =INDEX('Taxonomía temas'!$F$2:$F$54,MATCH(K33,'Taxonomía temas'!$A$2:$A$54,0)) -> 15 | Q33: 3 · Visualización interactiva | R33: Por verificar | S33: Por verificar | T33: Sí | U33: Por verificar | W33: =IF(V33="","No","Sí") -> No | Z33: La vigencia varía por capa cartográfica. | AA33: https://dgrn.mgap.gub.uy/js/visores/dgrn/ | AB33: 2026-10-02 | AC33: Productivo y económico | AD33: suelos; coneat; agro; geodatos | AE33: Relevamiento 02/10/2026
A34: UY-033 | B34: A Tu Servicio | C34: MSP / DATA Uruguay | D34: Nacional | E34: Interinstitucional / mixto | F34: Visualizador | G34: Nacional | H34: Comparación de prestadores de salud mediante indicadores de servicios, desempeño y atención. | I34: https://atuservicio.uy/ | J34: T22 · Salud y sistema sanitario | K34: =LEFT(J34,3) -> T22 | M34: =IF(L34="",K34,K34&"; "&L34) -> T22 | N34: =INDEX('Taxonomía temas'!$D$2:$D$54,MATCH(K34,'Taxonomía temas'!$A$2:$A$54,0)) -> Salud y población | O34: =INDEX('Taxonomía temas'!$F$2:$F$54,MATCH(K34,'Taxonomía temas'!$A$2:$A$54,0)) -> 3 | Q34: 3 · Visualización interactiva | R34: Por verificar | S34: Por verificar | T34: Por verificar | U34: Por verificar | W34: =IF(V34="","No","Sí") -> No | Z34: Catálogo fuente actualizado en abril de 2025; esa fecha no acredita el corte actual del sitio. | AA34: https://github.com/datauy/atuservicio https://catalogodatos.gub.uy/dataset/msp-a-tu-servicio | AB34: 2026-10-02 | AC34: Social y salud | AD34: salud; prestadores; calidad; usuarios | AE34: Relevamiento 02/10/2026
A35: UY-034 | B35: Datos abiertos de INEFOP | C35: INEFOP | D35: Nacional | E35: Público no estatal | F35: Catálogo institucional | G35: Nacional | H35: Conjuntos de datos institucionales sobre gestión y transparencia del instituto. | I35: https://catalogodatos.gub.uy/organization/instituto-nacional-de-empleo-y-formacion-profesional | J35: T21 · Formación profesional y capacitación | K35: =LEFT(J35,3) -> T21 | L35: T14; T44 | M35: =IF(L35="",K35,K35&"; "&L35) -> T21; T14; T44 | N35: =INDEX('Taxonomía temas'!$D$2:$D$54,MATCH(K35,'Taxonomía temas'!$A$2:$A$54,0)) -> Trabajo y protección social | O35: =INDEX('Taxonomía temas'!$F$2:$F$54,MATCH(K35,'Taxonomía temas'!$A$2:$A$54,0)) -> 4 | Q35: 1 · Datos | R35: Sí | S35: Por verificar | T35: Por verificar | U35: Por verificar | W35: =IF(V35="","No","Sí") -> No | Y35: Catálogo Nacional de Datos Abiertos | Z35: Se confirmó la incorporación al catálogo nacional y once conjuntos publicados; fecha por conjunto. | AA35: https://www.inefop.uy/post/inefop-se-integra-al-cat%C3%A1logo-nacional-de-datos-abiertos-y-avanza-en-apertura-de-datos | AB35: 2026-10-02 | AC35: Social y salud | AD35: formación-profesional; empleo; gestión; datos-abiertos | AE35: Relevamiento 02/10/2026
A36: UY-035 | B36: Estadísticas del mercado de trabajo | C36: MTSS / Unidad Estadística | D36: Nacional | E36: Público nacional | F36: Portal estadístico | G36: Nacional y departamental | H36: Informes y estadísticas sobre empleo, condiciones laborales y otros temas del trabajo. | I36: https://www.gub.uy/ministerio-trabajo-seguridad-social/unidad-estadistica-mtss | J36: T14 · Empleo y mercado de trabajo | K36: =LEFT(J36,3) -> T14 | L36: T15 | M36: =IF(L36="",K36,K36&"; "&L36) -> T14; T15 | N36: =INDEX('Taxonomía temas'!$D$2:$D$54,MATCH(K36,'Taxonomía temas'!$A$2:$A$54,0)) -> Trabajo y protección social | O36: =INDEX('Taxonomía temas'!$F$2:$F$54,MATCH(K36,'Taxonomía temas'!$A$2:$A$54,0)) -> 8 | Q36: 2 · Indicadores y series | R36: Por verificar | S36: Por verificar | T36: Por verificar | U36: Por verificar | V36: 2025: empleo cooperativo; 2024: accidentes | W36: =IF(V36="","No","Sí") -> Sí | Z36: Períodos diferentes según informe. | AA36: https://www.gub.uy/ministerio-trabajo-seguridad-social/unidad-estadistica-mtss https://www.gub.uy/ministerio-trabajo-seguridad-social/datos-y-estadisticas/estadisticas | AB36: 2026-10-02 | AC36: Social y salud | AD36: empleo; salarios; relaciones-laborales; accidentes | AE36: Relevamiento 02/10/2026
A37: UY-036 | B37: Estadísticas vitales | C37: Ministerio de Salud Pública | D37: Nacional | E37: Público nacional | F37: Repositorio estadístico | G37: Nacional y departamental | H37: Series y publicaciones sobre nacimientos, defunciones y otros hechos vitales. | I37: https://www.gub.uy/ministerio-salud-publica/datos-y-estadisticas/estadisticas/estadisticas-vitales | J37: T25 · Población, demografía y estadísticas vitales | K37: =LEFT(J37,3) -> T25 | L37: T22 | M37: =IF(L37="",K37,K37&"; "&L37) -> T25; T22 | N37: =INDEX('Taxonomía temas'!$D$2:$D$54,MATCH(K37,'Taxonomía temas'!$A$2:$A$54,0)) -> Salud y población | O37: =INDEX('Taxonomía temas'!$F$2:$F$54,MATCH(K37,'Taxonomía temas'!$A$2:$A$54,0)) -> 17 | Q37: 2 · Indicadores y series | R37: Por verificar | S37: Por verificar | T37: Por verificar | U37: Por verificar | W37: =IF(V37="","No","Sí") -> No | Z37: Último período disponible no comprobado en este relevamiento. | AA37: https://www.gub.uy/ministerio-salud-publica/datos-y-estadisticas/estadisticas/estadisticas-vitales | AB37: 2026-10-02 | AC37: Social y salud | AD37: salud; natalidad; mortalidad; demografía | AE37: Relevamiento 02/10/2026
A38: UY-037 | B38: Infancia en Datos | C38: UNICEF Uruguay | D38: Nacional | E38: Internacional, sección Uruguay | F38: Portal de indicadores | G38: Uruguay | H38: Presentaciones y análisis de evidencia sobre infancia, adolescencia y acceso a derechos. | I38: https://www.unicef.org/uruguay/infancia-en-datos | J38: T17 · Pobreza, desigualdad y condiciones de vida | K38: =LEFT(J38,3) -> T17 | L38: T22; T27 | M38: =IF(L38="",K38,K38&"; "&L38) -> T17; T22; T27 | N38: =INDEX('Taxonomía temas'!$D$2:$D$54,MATCH(K38,'Taxonomía temas'!$A$2:$A$54,0)) -> Trabajo y protección social | O38: =INDEX('Taxonomía temas'!$F$2:$F$54,MATCH(K38,'Taxonomía temas'!$A$2:$A$54,0)) -> 1 | P38: E02 · Infancia y adolescencia; E08 · Enfoque de derechos | Q38: 4 · Análisis e informes | R38: Por verificar | S38: Por verificar | T38: Por verificar | U38: Por verificar | V38: 2025: censo de adolescentes privados de libertad | W38: =IF(V38="","No","Sí") -> Sí | Z38: Período indicado para un estudio; otras publicaciones usan Censo 2023 y encuestas distintas. | AA38: https://www.unicef.org/uruguay/infancia-en-datos | AB38: 2026-10-02 | AC38: Social y salud | AD38: infancia; adolescencia; pobreza; salud; educación | AE38: Relevamiento 02/10/2026
A39: UY-038 | B39: Información y observación del personal de salud | C39: Ministerio de Salud Pública | D39: Nacional | E39: Público nacional | F39: Portal temático | G39: Nacional | H39: Estadísticas y estudios relativos a disponibilidad y características del personal sanitario. | I39: https://www.gub.uy/ministerio-salud-publica/personal-salud | J39: T22 · Salud y sistema sanitario | K39: =LEFT(J39,3) -> T22 | L39: T14 | M39: =IF(L39="",K39,K39&"; "&L39) -> T22; T14 | N39: =INDEX('Taxonomía temas'!$D$2:$D$54,MATCH(K39,'Taxonomía temas'!$A$2:$A$54,0)) -> Salud y población | O39: =INDEX('Taxonomía temas'!$F$2:$F$54,MATCH(K39,'Taxonomía temas'!$A$2:$A$54,0)) -> 3 | Q39: 2 · Indicadores y series | R39: Por verificar | S39: Por verificar | T39: Por verificar | U39: Por verificar | W39: =IF(V39="","No","Sí") -> No | Z39: Acceso institucional a recursos e información del área. | AA39: https://www.gub.uy/ministerio-salud-publica/personal-salud | AB39: 2026-10-02 | AC39: Social y salud | AD39: salud; recursos-humanos; empleo; profesionales | AE39: Relevamiento 02/10/2026
A40: UY-039 | B40: Informes de población y proyectos atendidos | C40: INAU | D40: Nacional | E40: Público nacional | F40: Repositorio estadístico | G40: Nacional | H40: Informes de atención y cobertura de proyectos dirigidos a niños, niñas y adolescentes. | I40: https://www.inau.gub.uy/documentos/ano-2025 | J40: T18 · Protección social y servicios sociales | K40: =LEFT(J40,3) -> T18 | M40: =IF(L40="",K40,K40&"; "&L40) -> T18 | N40: =INDEX('Taxonomía temas'!$D$2:$D$54,MATCH(K40,'Taxonomía temas'!$A$2:$A$54,0)) -> Trabajo y protección social | O40: =INDEX('Taxonomía temas'!$F$2:$F$54,MATCH(K40,'Taxonomía temas'!$A$2:$A$54,0)) -> 1 | P40: E02 · Infancia y adolescencia | Q40: 2 · Indicadores y series | R40: Por verificar | S40: Por verificar | T40: Por verificar | U40: Por verificar | V40: 2025 | W40: =IF(V40="","No","Sí") -> Sí | Z40: Enlace a la colección anual 2025. | AA40: https://www.inau.gub.uy/documentos/ano-2025 | AB40: 2026-10-02 | AC40: Social y salud | AD40: infancia; adolescencia; protección; servicios | AE40: Relevamiento 02/10/2026
A41: UY-040 | B41: Mirador DESCA | C41: INDDHH y Defensoría del Pueblo | D41: Nacional | E41: Público nacional | F41: Observatorio | G41: Nacional | H41: Indicadores y análisis de derechos económicos, sociales, culturales y ambientales. | I41: https://www.miradordesca.uy/ | J41: T48 · Derechos humanos | K41: =LEFT(J41,3) -> T48 | L41: T40; T22; T27; T32 | M41: =IF(L41="",K41,K41&"; "&L41) -> T48; T40; T22; T27; T32 | N41: =INDEX('Taxonomía temas'!$D$2:$D$54,MATCH(K41,'Taxonomía temas'!$A$2:$A$54,0)) -> Estado, gobierno y derechos | O41: =INDEX('Taxonomía temas'!$F$2:$F$54,MATCH(K41,'Taxonomía temas'!$A$2:$A$54,0)) -> 16 | P41: E08 · Enfoque de derechos | Q41: 4 · Análisis e informes | R41: Por verificar | S41: Por verificar | T41: Por verificar | U41: Por verificar | W41: =IF(V41="","No","Sí") -> No | Z41: Fechas y cobertura varían por dimensión. | AA41: https://www.gub.uy/institucion-nacional-derechos-humanos-uruguay/tematica/estudios?page=0 | AB41: 2026-10-02 | AC41: Social y salud | AD41: derechos-humanos; ambiente; vivienda; salud; educación | AE41: Relevamiento 02/10/2026
A42: UY-041 | B42: Monitor de accidentes de trabajo | C42: Banco de Seguros del Estado | D42: Nacional | E42: Público nacional | F42: Monitor | G42: Nacional | H42: Consulta de información estadística y bases de accidentes laborales atendidos por el BSE. | I42: https://hospital.bse.com.uy/portal-hospital/monitor-de-accidentes-de-trabajo | J42: T15 · Salud y seguridad laboral | K42: =LEFT(J42,3) -> T15 | M42: =IF(L42="",K42,K42&"; "&L42) -> T15 | N42: =INDEX('Taxonomía temas'!$D$2:$D$54,MATCH(K42,'Taxonomía temas'!$A$2:$A$54,0)) -> Trabajo y protección social | O42: =INDEX('Taxonomía temas'!$F$2:$F$54,MATCH(K42,'Taxonomía temas'!$A$2:$A$54,0)) -> 8 | Q42: 3 · Visualización interactiva | R42: Por verificar | S42: Por verificar | T42: Por verificar | U42: Por verificar | W42: =IF(V42="","No","Sí") -> No | Z42: Último período del monitor no comprobado; no extrapolar fechas de otras estadísticas del hospital. | AA42: https://hospital.bse.com.uy/portal-hospital/monitor-de-accidentes-de-trabajo | AB42: 2026-10-02 | AC42: Social y salud | AD42: salud-laboral; accidentes; empleo; prevención | AE42: Relevamiento 02/10/2026
A43: UY-042 | B43: Monitoreo del mercado regulado del cannabis | C43: IRCCA | D43: Nacional | E43: Público no estatal | F43: Repositorio estadístico | G43: Nacional | H43: Informes sobre usuarios, vías de acceso, producción y distribución del cannabis regulado. | I43: https://ircca.gub.uy/recursos-de-informacion/informes-del-mercado-regulado/ | J43: T24 · Drogas y consumos | K43: =LEFT(J43,3) -> T24 | M43: =IF(L43="",K43,K43&"; "&L43) -> T24 | N43: =INDEX('Taxonomía temas'!$D$2:$D$54,MATCH(K43,'Taxonomía temas'!$A$2:$A$54,0)) -> Salud y población | O43: =INDEX('Taxonomía temas'!$F$2:$F$54,MATCH(K43,'Taxonomía temas'!$A$2:$A$54,0)) -> 3 | Q43: 2 · Indicadores y series | R43: Por verificar | S43: Por verificar | T43: Por verificar | U43: Por verificar | V43: Enero–abril 2026 | W43: =IF(V43="","No","Sí") -> Sí | X43: 2026-05-11 | Z43: El informe 2026 se encuentra también en noticias; la colección principal destaca el cierre 2025. | AA43: https://ircca.gub.uy/recursos-de-informacion/informes-del-mercado-regulado/ https://ircca.gub.uy/informe-del-mercado-de-cannabis-de-uso-adulto-en-uruguay-datos-actualizados-al-primer-cuatrimestre-de-2026-enero-a-abril/ | AB43: 2026-10-02 | AC43: Social y salud | AD43: cannabis; mercado-regulado; salud; producción | AE43: Relevamiento 02/10/2026
A44: UY-043 | B44: Observatorio / BPS en cifras | C44: Banco de Previsión Social | D44: Nacional | E44: Público nacional | F44: Observatorio | G44: Nacional | H44: Indicadores y series administrativas de prestaciones, beneficiarios y cotizantes. | I44: https://observatorio.bps.gub.uy/#/ | J44: T16 · Seguridad social y pensiones | K44: =LEFT(J44,3) -> T16 | M44: =IF(L44="",K44,K44&"; "&L44) -> T16 | N44: =INDEX('Taxonomía temas'!$D$2:$D$54,MATCH(K44,'Taxonomía temas'!$A$2:$A$54,0)) -> Trabajo y protección social | O44: =INDEX('Taxonomía temas'!$F$2:$F$54,MATCH(K44,'Taxonomía temas'!$A$2:$A$54,0)) -> 1 | Q44: 4 · Análisis e informes | R44: Por verificar | S44: Por verificar | T44: Por verificar | U44: Por verificar | V44: 2026: principales indicadores | W44: =IF(V44="","No","Sí") -> Sí | X44: 2026-07-02 | Z44: Fecha tomada de la entrada estadística oficial; aplicación dinámica no auditada íntegramente. | AA44: https://www.bps.gub.uy/bps/observatorio/estadisticas.jsp | AB44: 2026-10-02 | AC44: Social y salud | AD44: seguridad-social; jubilaciones; cotizantes; prestaciones | AE44: Relevamiento 02/10/2026
A45: UY-044 | B45: Observatorio de Cultura de Montevideo | C45: Intendencia de Montevideo | D45: Departamental | E45: Gobierno departamental | F45: Módulo | G45: Montevideo | H45: Información de actividades, infraestructura y políticas culturales municipales. | I45: https://montevidata.montevideo.gub.uy/cultura | J45: T30 · Cultura | K45: =LEFT(J45,3) -> T30 | M45: =IF(L45="",K45,K45&"; "&L45) -> T30 | N45: =INDEX('Taxonomía temas'!$D$2:$D$54,MATCH(K45,'Taxonomía temas'!$A$2:$A$54,0)) -> Educación, cultura y deporte | O45: =INDEX('Taxonomía temas'!$F$2:$F$54,MATCH(K45,'Taxonomía temas'!$A$2:$A$54,0)) -> 11 | P45: E09 · Territorial y subnacional | Q45: 3 · Visualización interactiva | R45: Por verificar | S45: Por verificar | T45: Sí | U45: Por verificar | W45: =IF(V45="","No","Sí") -> No | Y45: Montevidata | Z45: Fecha variable por tablero. | AA45: https://montevidata.montevideo.gub.uy/cultura | AB45: 2026-10-02 | AC45: Social y salud | AD45: montevideo; cultura; participación; equipamientos | AE45: Relevamiento 02/10/2026
A46: UY-045 | B46: Observatorio de Género de la Udelar | C46: Universidad de la República | D46: Nacional | E46: Académico | F46: Observatorio | G46: Udelar | H46: Análisis y seguimiento de desigualdades de género en el ámbito universitario. | I46: https://udelar.edu.uy/observatorio-genero | J46: T29 · Educación superior y universidad | K46: =LEFT(J46,3) -> T29 | M46: =IF(L46="",K46,K46&"; "&L46) -> T29 | N46: =INDEX('Taxonomía temas'!$D$2:$D$54,MATCH(K46,'Taxonomía temas'!$A$2:$A$54,0)) -> Educación, cultura y deporte | O46: =INDEX('Taxonomía temas'!$F$2:$F$54,MATCH(K46,'Taxonomía temas'!$A$2:$A$54,0)) -> 4 | P46: E01 · Género | Q46: 4 · Análisis e informes | R46: Por verificar | S46: Por verificar | T46: Por verificar | U46: Sí | W46: =IF(V46="","No","Sí") -> No | Z46: Incluye estudios y memoria institucional; fecha de datos variable. | AA46: https://udelar.edu.uy/observatorio-genero https://udelar.edu.uy/observatorio-genero | AB46: 2026-10-02 | AC46: Social y salud | AD46: género; universidad; igualdad; instituciones | AE46: Relevamiento 02/10/2026
A47: UY-046 | B47: Observatorio de Igualdad de Género de Montevideo | C47: Intendencia de Montevideo | D47: Departamental | E47: Gobierno departamental | F47: Módulo | G47: Montevideo | H47: Indicadores de políticas y servicios municipales vinculados a la igualdad de género. | I47: https://montevidata.montevideo.gub.uy/igualdad-de-genero | J47: T17 · Pobreza, desigualdad y condiciones de vida | K47: =LEFT(J47,3) -> T17 | L47: T46 | M47: =IF(L47="",K47,K47&"; "&L47) -> T17; T46 | N47: =INDEX('Taxonomía temas'!$D$2:$D$54,MATCH(K47,'Taxonomía temas'!$A$2:$A$54,0)) -> Trabajo y protección social | O47: =INDEX('Taxonomía temas'!$F$2:$F$54,MATCH(K47,'Taxonomía temas'!$A$2:$A$54,0)) -> 1 | P47: E01 · Género; E09 · Territorial y subnacional | Q47: 3 · Visualización interactiva | R47: Por verificar | S47: Por verificar | T47: Sí | U47: Sí | W47: =IF(V47="","No","Sí") -> No | Y47: Montevidata | Z47: Fecha variable por programa. | AA47: https://montevidata.montevideo.gub.uy/igualdad-de-genero | AB47: 2026-10-02 | AC47: Social y salud | AD47: montevideo; género; violencia; autonomía | AE47: Relevamiento 02/10/2026
A48: UY-047 | B48: Observatorio de Infancia y Adolescencia | C48: OIA | D48: Nacional | E48: Naturaleza no corroborada | F48: Observatorio | G48: Nacional | H48: Seguimiento y análisis de la situación de niños, niñas y adolescentes. | I48: https://oia.org.uy/ | J48: T17 · Pobreza, desigualdad y condiciones de vida | K48: =LEFT(J48,3) -> T17 | L48: T18; T27 | M48: =IF(L48="",K48,K48&"; "&L48) -> T17; T18; T27 | N48: =INDEX('Taxonomía temas'!$D$2:$D$54,MATCH(K48,'Taxonomía temas'!$A$2:$A$54,0)) -> Trabajo y protección social | O48: =INDEX('Taxonomía temas'!$F$2:$F$54,MATCH(K48,'Taxonomía temas'!$A$2:$A$54,0)) -> 1 | P48: E02 · Infancia y adolescencia; E08 · Enfoque de derechos | Q48: 4 · Análisis e informes | R48: Por verificar | S48: Por verificar | T48: Por verificar | U48: Por verificar | W48: =IF(V48="","No","Sí") -> No | Z48: Datos e indicadores localizados; la página Nosotros no identifica instituciones responsables. Se requiere corroborar su adscripción. | AA48: https://oia.org.uy/ | AB48: 2026-10-02 | AC48: Social y salud | AD48: infancia; adolescencia; derechos; políticas-sociales | AE48: Relevamiento 02/10/2026
A49: UY-048 | B49: Observatorio de Migraciones de Rivera | C49: Intendencia de Rivera | D49: Departamental | E49: Gobierno departamental | F49: Observatorio | G49: Rivera | H49: Información y estudios sobre población migrante y procesos de integración local. | I49: https://www.rivera.gub.uy/social/observatorio/ | J49: T26 · Migración y movilidad humana | K49: =LEFT(J49,3) -> T26 | M49: =IF(L49="",K49,K49&"; "&L49) -> T26 | N49: =INDEX('Taxonomía temas'!$D$2:$D$54,MATCH(K49,'Taxonomía temas'!$A$2:$A$54,0)) -> Salud y población | O49: =INDEX('Taxonomía temas'!$F$2:$F$54,MATCH(K49,'Taxonomía temas'!$A$2:$A$54,0)) -> 10 | P49: E06 · Migración; E09 · Territorial y subnacional | Q49: 4 · Análisis e informes | R49: Por verificar | S49: Por verificar | T49: Sí | U49: Por verificar | W49: =IF(V49="","No","Sí") -> No | Z49: No se comprobó un último corte estadístico. | AA49: https://www.rivera.gub.uy/social/observatorio/ | AB49: 2026-10-02 | AC49: Social y salud | AD49: migración; frontera; integración; derechos | AE49: Relevamiento 02/10/2026
A50: UY-049 | B50: Observatorio de Movilidad, Infancia y Familia — OMIF | C50: Universidad de la República | D50: Nacional | E50: Académico | F50: Observatorio | G50: Nacional | H50: Recopilación de registros y estudios sobre migración, movilidad y familias. | I50: https://omif.cienciassociales.edu.uy/registros-administrativos/ | J50: T26 · Migración y movilidad humana | K50: =LEFT(J50,3) -> T26 | L50: T25 | M50: =IF(L50="",K50,K50&"; "&L50) -> T26; T25 | N50: =INDEX('Taxonomía temas'!$D$2:$D$54,MATCH(K50,'Taxonomía temas'!$A$2:$A$54,0)) -> Salud y población | O50: =INDEX('Taxonomía temas'!$F$2:$F$54,MATCH(K50,'Taxonomía temas'!$A$2:$A$54,0)) -> 10 | P50: E02 · Infancia y adolescencia; E06 · Migración | Q50: 4 · Análisis e informes | R50: Por verificar | S50: Por verificar | T50: Por verificar | U50: Por verificar | W50: =IF(V50="","No","Sí") -> No | Z50: Acceso directo a registros administrativos. | AA50: https://omif.cienciassociales.edu.uy/registros-administrativos/ | AB50: 2026-10-02 | AC50: Social y salud | AD50: migración; familias; infancia; demografía | AE50: Relevamiento 02/10/2026
A51: UY-050 | B51: Observatorio de Salud de Montevideo | C51: Intendencia de Montevideo | D51: Departamental | E51: Gobierno departamental | F51: Módulo | G51: Montevideo | H51: Indicadores sobre cobertura y atención de los servicios municipales de salud. | I51: https://montevidata.montevideo.gub.uy/salud | J51: T22 · Salud y sistema sanitario | K51: =LEFT(J51,3) -> T22 | M51: =IF(L51="",K51,K51&"; "&L51) -> T22 | N51: =INDEX('Taxonomía temas'!$D$2:$D$54,MATCH(K51,'Taxonomía temas'!$A$2:$A$54,0)) -> Salud y población | O51: =INDEX('Taxonomía temas'!$F$2:$F$54,MATCH(K51,'Taxonomía temas'!$A$2:$A$54,0)) -> 3 | P51: E09 · Territorial y subnacional | Q51: 3 · Visualización interactiva | R51: Por verificar | S51: Por verificar | T51: Sí | U51: Por verificar | W51: =IF(V51="","No","Sí") -> No | Y51: Montevidata | Z51: Fecha variable por indicador. | AA51: https://montevidata.montevideo.gub.uy/salud | AB51: 2026-10-02 | AC51: Social y salud | AD51: montevideo; salud; policlínicas; cobertura | AE51: Relevamiento 02/10/2026
A52: UY-051 | B52: Observatorio de Seguridad Alimentaria y Nutricional — OBSAN | C52: MIDES / INDA | D52: Nacional | E52: Público nacional | F52: Observatorio | G52: Nacional | H52: Información y análisis sobre acceso a alimentos y situación alimentaria y nutricional. | I52: https://www.gub.uy/ministerio-desarrollo-social/obsan | J52: T20 · Alimentación y nutrición | K52: =LEFT(J52,3) -> T20 | L52: T17 | M52: =IF(L52="",K52,K52&"; "&L52) -> T20; T17 | N52: =INDEX('Taxonomía temas'!$D$2:$D$54,MATCH(K52,'Taxonomía temas'!$A$2:$A$54,0)) -> Trabajo y protección social | O52: =INDEX('Taxonomía temas'!$F$2:$F$54,MATCH(K52,'Taxonomía temas'!$A$2:$A$54,0)) -> 2 | Q52: 4 · Análisis e informes | R52: Por verificar | S52: Por verificar | T52: Por verificar | U52: Por verificar | V52: 2025: inseguridad alimentaria | W52: =IF(V52="","No","Sí") -> Sí | Z52: Período del cuarto informe localizado. | AA52: https://www.gub.uy/ministerio-desarrollo-social/obsan | AB52: 2026-10-02 | AC52: Social y salud | AD52: alimentación; nutrición; pobreza; seguridad-alimentaria | AE52: Relevamiento 02/10/2026
A53: UY-052 | B53: Observatorio de Seguridad Social | C53: CINVE | D53: Nacional | E53: Sociedad civil / investigación | F53: Observatorio | G53: Nacional | H53: Análisis, indicadores y seguimiento del sistema de seguridad social. | I53: https://www.observatorioseguridadsocial.org.uy/ | J53: T16 · Seguridad social y pensiones | K53: =LEFT(J53,3) -> T16 | L53: T14 | M53: =IF(L53="",K53,K53&"; "&L53) -> T16; T14 | N53: =INDEX('Taxonomía temas'!$D$2:$D$54,MATCH(K53,'Taxonomía temas'!$A$2:$A$54,0)) -> Trabajo y protección social | O53: =INDEX('Taxonomía temas'!$F$2:$F$54,MATCH(K53,'Taxonomía temas'!$A$2:$A$54,0)) -> 1 | Q53: 4 · Análisis e informes | R53: Por verificar | S53: Por verificar | T53: Por verificar | U53: Por verificar | V53: Julio 2026: mercado laboral | W53: =IF(V53="","No","Sí") -> Sí | Z53: Monitor publicado en septiembre de 2026; comprobar el corte de cada serie. | AA53: https://www.observatorioseguridadsocial.org.uy/?b=0290270917702 https://www.observatorioseguridadsocial.org.uy/index.php/institucional | AB53: 2026-10-02 | AC53: Social y salud | AD53: seguridad-social; jubilaciones; mercado-laboral | AE53: Relevamiento 02/10/2026
A54: UY-053 | B54: Observatorio de Trabajo de Montevideo | C54: Intendencia de Montevideo | D54: Departamental | E54: Gobierno departamental | F54: Módulo | G54: Montevideo | H54: Seguimiento de formación, empleo protegido e iniciativas de inclusión laboral. | I54: https://montevidata.montevideo.gub.uy/trabajo | J54: T14 · Empleo y mercado de trabajo | K54: =LEFT(J54,3) -> T14 | L54: T21 | M54: =IF(L54="",K54,K54&"; "&L54) -> T14; T21 | N54: =INDEX('Taxonomía temas'!$D$2:$D$54,MATCH(K54,'Taxonomía temas'!$A$2:$A$54,0)) -> Trabajo y protección social | O54: =INDEX('Taxonomía temas'!$F$2:$F$54,MATCH(K54,'Taxonomía temas'!$A$2:$A$54,0)) -> 8 | P54: E09 · Territorial y subnacional | Q54: 3 · Visualización interactiva | R54: Por verificar | S54: Por verificar | T54: Sí | U54: Por verificar | W54: =IF(V54="","No","Sí") -> No | Y54: Montevidata | Z54: Fecha variable por programa. | AA54: https://montevidata.montevideo.gub.uy/trabajo | AB54: 2026-10-02 | AC54: Social y salud | AD54: montevideo; empleo; capacitación; inclusión | AE54: Relevamiento 02/10/2026
A55: UY-054 | B55: Observatorio de Vejez, Envejecimiento y Seguridad Social — OVESS | C55: BPS | D55: Nacional | E55: Público nacional | F55: Observatorio | G55: Nacional | H55: Indicadores para analizar vejez, estructura poblacional y protección social. | I55: https://observatorio.bps.gub.uy/ovess/ | J55: T16 · Seguridad social y pensiones | K55: =LEFT(J55,3) -> T16 | L55: T25 | M55: =IF(L55="",K55,K55&"; "&L55) -> T16; T25 | N55: =INDEX('Taxonomía temas'!$D$2:$D$54,MATCH(K55,'Taxonomía temas'!$A$2:$A$54,0)) -> Trabajo y protección social | O55: =INDEX('Taxonomía temas'!$F$2:$F$54,MATCH(K55,'Taxonomía temas'!$A$2:$A$54,0)) -> 1 | P55: E04 · Personas mayores y envejecimiento | Q55: 4 · Análisis e informes | R55: Por verificar | S55: Por verificar | T55: Por verificar | U55: Por verificar | W55: =IF(V55="","No","Sí") -> No | Y55: BPS | Z55: Incluye proyecciones hasta 2070: ese horizonte no es un dato observado reciente. | AA55: https://observatorio.bps.gub.uy/ovess/ | AB55: 2026-10-02 | AC55: Social y salud | AD55: envejecimiento; demografía; personas-mayores; seguridad-social | AE55: Relevamiento 02/10/2026
A56: UY-055 | B56: Observatorio de Violencia Basada en Género hacia las Mujeres | C56: MIDES / Inmujeres | D56: Nacional | E56: Público nacional | F56: Observatorio | G56: Nacional | H56: Estadísticas y documentos sobre violencia contra las mujeres y respuestas institucionales. | I56: https://www.gub.uy/ministerio-desarrollo-social/observatorio/violencia-genero | J56: T46 · Seguridad y delito | K56: =LEFT(J56,3) -> T46 | L56: T47 | M56: =IF(L56="",K56,K56&"; "&L56) -> T46; T47 | N56: =INDEX('Taxonomía temas'!$D$2:$D$54,MATCH(K56,'Taxonomía temas'!$A$2:$A$54,0)) -> Estado, gobierno y derechos | O56: =INDEX('Taxonomía temas'!$F$2:$F$54,MATCH(K56,'Taxonomía temas'!$A$2:$A$54,0)) -> 16 | P56: E01 · Género | Q56: 4 · Análisis e informes | R56: Por verificar | S56: Por verificar | T56: Por verificar | U56: Sí | W56: =IF(V56="","No","Sí") -> No | Z56: Se localizó una publicación de abril de 2026; no se asigna ese año a todos los datos. | AA56: https://www.gub.uy/ministerio-desarrollo-social/observatorio/violencia-genero https://www.gub.uy/ministerio-desarrollo-social/sites/ministerio-desarrollo-social/files/documentos/publicaciones/Indicadores%20femicidios%20_%20OVBG%20abril%202026.pdf | AB56: 2026-10-02 | AC56: Social y salud | AD56: género; violencia; derechos; seguridad | AE56: Relevamiento 02/10/2026
A57: UY-056 | B57: Observatorio del Derecho a la Alimentación — Derecho | C57: Udelar / Facultad de Derecho | D57: Nacional | E57: Académico | F57: Observatorio de estudios | G57: Nacional | H57: Investigación y seguimiento del derecho a la alimentación y sus marcos institucionales. | I57: https://www.fder.edu.uy/oda | J57: T20 · Alimentación y nutrición | K57: =LEFT(J57,3) -> T20 | L57: T48 | M57: =IF(L57="",K57,K57&"; "&L57) -> T20; T48 | N57: =INDEX('Taxonomía temas'!$D$2:$D$54,MATCH(K57,'Taxonomía temas'!$A$2:$A$54,0)) -> Trabajo y protección social | O57: =INDEX('Taxonomía temas'!$F$2:$F$54,MATCH(K57,'Taxonomía temas'!$A$2:$A$54,0)) -> 2 | P57: E08 · Enfoque de derechos | Q57: 4 · Análisis e informes | R57: Por verificar | S57: Por verificar | T57: Por verificar | U57: Por verificar | W57: =IF(V57="","No","Sí") -> No | Z57: Predominan estudios y documentos, no un tablero estadístico permanente. | AA57: https://www.fder.edu.uy/oda | AB57: 2026-10-02 | AC57: Social y salud | AD57: alimentación; derechos; políticas; investigación | AE57: Relevamiento 02/10/2026
A58: UY-057 | B58: Observatorio del Derecho a la Alimentación — Nutrición | C58: Udelar / Escuela de Nutrición | D58: Nacional | E58: Académico | F58: Observatorio de estudios | G58: Nacional | H58: Estudios sobre alimentación adecuada y políticas alimentarias desde la perspectiva nutricional. | I58: https://www.nutricion.edu.uy/?page_id=6614 | J58: T20 · Alimentación y nutrición | K58: =LEFT(J58,3) -> T20 | M58: =IF(L58="",K58,K58&"; "&L58) -> T20 | N58: =INDEX('Taxonomía temas'!$D$2:$D$54,MATCH(K58,'Taxonomía temas'!$A$2:$A$54,0)) -> Trabajo y protección social | O58: =INDEX('Taxonomía temas'!$F$2:$F$54,MATCH(K58,'Taxonomía temas'!$A$2:$A$54,0)) -> 2 | P58: E08 · Enfoque de derechos | Q58: 4 · Análisis e informes | R58: Por verificar | S58: Por verificar | T58: Por verificar | U58: Por verificar | W58: =IF(V58="","No","Sí") -> No | Z58: Nodo académico diferenciado del de Facultad de Derecho. | AA58: https://www.nutricion.edu.uy/?page_id=6614 | AB58: 2026-10-02 | AC58: Social y salud | AD58: alimentación; nutrición; derechos; investigación | AE58: Relevamiento 02/10/2026
A59: UY-058 | B59: Observatorio del Sistema de Salud — datos | C59: Observatorio del Sistema de Salud | D59: Nacional | E59: Naturaleza no corroborada | F59: Observatorio | G59: Nacional | H59: Recopilación y análisis de indicadores del sistema de salud. | I59: https://observatoriosalud.org.uy/seccion/datos | J59: T22 · Salud y sistema sanitario | K59: =LEFT(J59,3) -> T22 | M59: =IF(L59="",K59,K59&"; "&L59) -> T22 | N59: =INDEX('Taxonomía temas'!$D$2:$D$54,MATCH(K59,'Taxonomía temas'!$A$2:$A$54,0)) -> Salud y población | O59: =INDEX('Taxonomía temas'!$F$2:$F$54,MATCH(K59,'Taxonomía temas'!$A$2:$A$54,0)) -> 3 | Q59: 4 · Análisis e informes | R59: Por verificar | S59: Por verificar | T59: Por verificar | U59: Por verificar | V59: Marzo 2026: afiliación; 2025: asistencia | W59: =IF(V59="","No","Sí") -> Sí | X59: 2026-06-09 | Z59: Fuente no estatal; responsable institucional específico pendiente de corroboración. | AA59: https://observatoriosalud.org.uy/seccion/datos | AB59: 2026-10-02 | AC59: Social y salud | AD59: salud; financiamiento; prestadores; afiliación | AE59: Relevamiento 02/10/2026
A60: UY-059 | B60: Observatorio Nacional en Género y Salud Sexual y Reproductiva | C60: MYSU | D60: Nacional | E60: Sociedad civil / investigación | F60: Observatorio | G60: Nacional | H60: Investigaciones y monitoreo de servicios, derechos y políticas de salud sexual y reproductiva. | I60: https://www.mysu.org.uy/que-hacemos/observatorio/ | J60: T23 · Salud sexual y reproductiva | K60: =LEFT(J60,3) -> T23 | L60: T22 | M60: =IF(L60="",K60,K60&"; "&L60) -> T23; T22 | N60: =INDEX('Taxonomía temas'!$D$2:$D$54,MATCH(K60,'Taxonomía temas'!$A$2:$A$54,0)) -> Salud y población | O60: =INDEX('Taxonomía temas'!$F$2:$F$54,MATCH(K60,'Taxonomía temas'!$A$2:$A$54,0)) -> 3 | P60: E01 · Género; E08 · Enfoque de derechos | Q60: 4 · Análisis e informes | R60: Por verificar | S60: Por verificar | T60: Por verificar | U60: Sí | W60: =IF(V60="","No","Sí") -> No | Z60: Predominan estudios e informes; no todas las salidas son datos descargables. | AA60: https://www.mysu.org.uy/que-hacemos/observatorio/ | AB60: 2026-10-02 | AC60: Social y salud | AD60: género; salud-sexual; derechos; salud-reproductiva | AE60: Relevamiento 02/10/2026
A61: UY-060 | B61: Observatorio Social | C61: MIDES | D61: Nacional | E61: Público nacional | F61: Observatorio | G61: Nacional y departamental | H61: Información sobre condiciones de vida, desigualdades y políticas sociales. | I61: https://www.gub.uy/ministerio-desarrollo-social/observatorio | J61: T17 · Pobreza, desigualdad y condiciones de vida | K61: =LEFT(J61,3) -> T17 | L61: T18 | M61: =IF(L61="",K61,K61&"; "&L61) -> T17; T18 | N61: =INDEX('Taxonomía temas'!$D$2:$D$54,MATCH(K61,'Taxonomía temas'!$A$2:$A$54,0)) -> Trabajo y protección social | O61: =INDEX('Taxonomía temas'!$F$2:$F$54,MATCH(K61,'Taxonomía temas'!$A$2:$A$54,0)) -> 1 | Q61: 4 · Análisis e informes | R61: Por verificar | S61: Por verificar | T61: Por verificar | U61: Por verificar | V61: 2023 en indicadores localizados | W61: =IF(V61="","No","Sí") -> Sí | Z61: 2023 es un corte comprobado en indicadores, no una fecha global del portal. | AA61: https://www.gub.uy/ministerio-desarrollo-social/observatorio | AB61: 2026-10-02 | AC61: Social y salud | AD61: pobreza; desigualdad; hogares; políticas-sociales | AE61: Relevamiento 02/10/2026
A62: UY-061 | B62: Observatorio Uruguayo de Drogas | C62: Junta Nacional de Drogas | D62: Nacional | E62: Público nacional | F62: Observatorio | G62: Nacional | H62: Encuestas, investigaciones y estadísticas sobre usos de drogas y sus consecuencias. | I62: https://www.gub.uy/junta-nacional-drogas/observatorio-uruguayo-de-drogas | J62: T24 · Drogas y consumos | K62: =LEFT(J62,3) -> T24 | L62: T22 | M62: =IF(L62="",K62,K62&"; "&L62) -> T24; T22 | N62: =INDEX('Taxonomía temas'!$D$2:$D$54,MATCH(K62,'Taxonomía temas'!$A$2:$A$54,0)) -> Salud y población | O62: =INDEX('Taxonomía temas'!$F$2:$F$54,MATCH(K62,'Taxonomía temas'!$A$2:$A$54,0)) -> 3 | Q62: 4 · Análisis e informes | R62: Por verificar | S62: Por verificar | T62: Por verificar | U62: Por verificar | W62: =IF(V62="","No","Sí") -> No | Z62: Períodos distintos por estudio. | AA62: https://www.gub.uy/junta-nacional-drogas/observatorio-uruguayo-de-drogas | AB62: 2026-10-02 | AC62: Social y salud | AD62: drogas; consumos; salud; políticas | AE62: Relevamiento 02/10/2026
A63: UY-062 | B63: OBSERVEN — Observatorio sobre Vejez y Envejecimiento | C63: Udelar / Centro Interdisciplinario de Envejecimiento | D63: Nacional | E63: Académico | F63: Observatorio | G63: Nacional | H63: Información estadística, publicaciones e investigaciones sobre vejez y envejecimiento. | I63: https://observatorioenvejecimiento.psico.edu.uy/ | J63: T25 · Población, demografía y estadísticas vitales | K63: =LEFT(J63,3) -> T25 | L63: T16 | M63: =IF(L63="",K63,K63&"; "&L63) -> T25; T16 | N63: =INDEX('Taxonomía temas'!$D$2:$D$54,MATCH(K63,'Taxonomía temas'!$A$2:$A$54,0)) -> Salud y población | O63: =INDEX('Taxonomía temas'!$F$2:$F$54,MATCH(K63,'Taxonomía temas'!$A$2:$A$54,0)) -> 17 | P63: E04 · Personas mayores y envejecimiento; E08 · Enfoque de derechos | Q63: 4 · Análisis e informes | R63: Por verificar | S63: Por verificar | T63: Por verificar | U63: Por verificar | W63: =IF(V63="","No","Sí") -> No | Z63: Parte del contenido corresponde a estudios históricos; último corte estadístico no comprobado. | AA63: https://observatorioenvejecimiento.psico.edu.uy/ | AB63: 2026-10-02 | AC63: Social y salud | AD63: envejecimiento; personas-mayores; demografía; derechos | AE63: Relevamiento 02/10/2026
A64: UY-063 | B64: ODISMET Uruguay — banco de datos | C64: ODISMET | D64: Nacional | E64: Internacional, sección Uruguay | F64: Observatorio | G64: Uruguay | H64: Indicadores sociodemográficos y laborales vinculados a discapacidad en Uruguay. | I64: https://www.odismet.org/uruguay/banco-de-datos/datos-sociodemograficos | J64: T14 · Empleo y mercado de trabajo | K64: =LEFT(J64,3) -> T14 | L64: T25 | M64: =IF(L64="",K64,K64&"; "&L64) -> T14; T25 | N64: =INDEX('Taxonomía temas'!$D$2:$D$54,MATCH(K64,'Taxonomía temas'!$A$2:$A$54,0)) -> Trabajo y protección social | O64: =INDEX('Taxonomía temas'!$F$2:$F$54,MATCH(K64,'Taxonomía temas'!$A$2:$A$54,0)) -> 8 | P64: E05 · Discapacidad | Q64: 4 · Análisis e informes | R64: Por verificar | S64: Por verificar | T64: Por verificar | U64: Por verificar | V64: 2023: censo | W64: =IF(V64="","No","Sí") -> Sí | Z64: Portal internacional con sección Uruguay; las definiciones de discapacidad requieren atención al comparar fuentes. | AA64: https://www.odismet.org/uruguay/banco-de-datos/datos-sociodemograficos | AB64: 2026-10-02 | AC64: Social y salud | AD64: discapacidad; empleo; inclusión; demografía | AE64: Relevamiento 02/10/2026
A65: UY-064 | B65: SINADI — indicadores de desempeño asistencial | C65: Ministerio de Salud Pública | D65: Nacional | E65: Público nacional | F65: Portal estadístico | G65: Nacional | H65: Indicadores de actividad y desempeño de instituciones del sistema de salud. | I65: https://www.gub.uy/ministerio-salud-publica/tematica/indicadores-desempeno-asistencial | J65: T22 · Salud y sistema sanitario | K65: =LEFT(J65,3) -> T22 | M65: =IF(L65="",K65,K65&"; "&L65) -> T22 | N65: =INDEX('Taxonomía temas'!$D$2:$D$54,MATCH(K65,'Taxonomía temas'!$A$2:$A$54,0)) -> Salud y población | O65: =INDEX('Taxonomía temas'!$F$2:$F$54,MATCH(K65,'Taxonomía temas'!$A$2:$A$54,0)) -> 3 | Q65: 2 · Indicadores y series | R65: Por verificar | S65: Por verificar | T65: Por verificar | U65: Por verificar | V65: 2025 | W65: =IF(V65="","No","Sí") -> Sí | Z65: Informes publicados en 2026 con datos de 2025. | AA65: https://www.gub.uy/ministerio-salud-publica/tematica/indicadores-desempeno-asistencial | AB65: 2026-10-02 | AC65: Social y salud | AD65: salud; prestadores; asistencia; gestión | AE65: Relevamiento 02/10/2026
A66: UY-065 | B66: Sistema de Información de Género — SIG | C66: MIDES / Inmujeres | D66: Nacional | E66: Público nacional | F66: Portal estadístico | G66: Nacional | H66: Indicadores y publicaciones para estudiar brechas y desigualdades entre mujeres y varones. | I66: https://www.gub.uy/ministerio-desarrollo-social/sig | J66: T17 · Pobreza, desigualdad y condiciones de vida | K66: =LEFT(J66,3) -> T17 | L66: T14; T19 | M66: =IF(L66="",K66,K66&"; "&L66) -> T17; T14; T19 | N66: =INDEX('Taxonomía temas'!$D$2:$D$54,MATCH(K66,'Taxonomía temas'!$A$2:$A$54,0)) -> Trabajo y protección social | O66: =INDEX('Taxonomía temas'!$F$2:$F$54,MATCH(K66,'Taxonomía temas'!$A$2:$A$54,0)) -> 1 | P66: E01 · Género | Q66: 2 · Indicadores y series | R66: Por verificar | S66: Por verificar | T66: Por verificar | U66: Sí | W66: =IF(V66="","No","Sí") -> No | Z66: Último período no comprobado. | AA66: https://www.gub.uy/ministerio-desarrollo-social/sig | AB66: 2026-10-02 | AC66: Social y salud | AD66: género; autonomía; trabajo; desigualdad | AE66: Relevamiento 02/10/2026
A67: UY-066 | B67: Balance Energético Nacional — BEN | C67: MIEM / Dirección Nacional de Energía | D67: Nacional | E67: Público nacional | F67: Portal estadístico | G67: Nacional | H67: Balance de oferta, transformación y consumo energético por fuentes y sectores. | I67: https://www.gub.uy/ministerio-industria-energia-mineria/ben | J67: T34 · Energía | K67: =LEFT(J67,3) -> T34 | L67: T35 | M67: =IF(L67="",K67,K67&"; "&L67) -> T34; T35 | N67: =INDEX('Taxonomía temas'!$D$2:$D$54,MATCH(K67,'Taxonomía temas'!$A$2:$A$54,0)) -> Ambiente, energía y clima | O67: =INDEX('Taxonomía temas'!$F$2:$F$54,MATCH(K67,'Taxonomía temas'!$A$2:$A$54,0)) -> 7 | Q67: 2 · Indicadores y series | R67: Por verificar | S67: Por verificar | T67: Por verificar | U67: Por verificar | V67: 2025 | W67: =IF(V67="","No","Sí") -> Sí | X67: 2026-07-31 | Z67: Fecha de la noticia oficial sobre el BEN 2025, presentado el 30/07/2026. | AA67: https://www.gub.uy/ministerio-industria-energia-mineria/ben https://www.gub.uy/ministerio-industria-energia-mineria/comunicacion/noticias/consumo-electricidad-transporte-supero-primera-vez-del-conjunto-industrias | AB67: 2026-10-02 | AC67: Ambiental y energía | AD67: energía; consumo; oferta; renovables; emisiones | AE67: Relevamiento 02/10/2026
A68: UY-067 | B68: Datos abiertos de energía y agua | C68: URSEA | D68: Nacional | E68: Público nacional | F68: Repositorio de datos | G68: Nacional | H68: Conjuntos de datos sobre servicios regulados y precios de referencia de combustibles. | I68: https://www.gub.uy/unidad-reguladora-servicios-energia-agua/datos-y-estadisticas/datos-abiertos | J68: T34 · Energía | K68: =LEFT(J68,3) -> T34 | L68: T33 | M68: =IF(L68="",K68,K68&"; "&L68) -> T34; T33 | N68: =INDEX('Taxonomía temas'!$D$2:$D$54,MATCH(K68,'Taxonomía temas'!$A$2:$A$54,0)) -> Ambiente, energía y clima | O68: =INDEX('Taxonomía temas'!$F$2:$F$54,MATCH(K68,'Taxonomía temas'!$A$2:$A$54,0)) -> 7 | Q68: 1 · Datos | R68: Sí | S68: Por verificar | T68: Por verificar | U68: Por verificar | W68: =IF(V68="","No","Sí") -> No | Z68: Actualización independiente por conjunto. | AA68: https://www.gub.uy/unidad-reguladora-servicios-energia-agua/datos-y-estadisticas/datos-abiertos | AB68: 2026-10-02 | AC68: Ambiental y energía | AD68: energía; agua; combustibles; tarifas; regulación | AE68: Relevamiento 02/10/2026
A69: UY-068 | B69: Datos abiertos hidrológicos | C69: Ministerio de Ambiente / DINAGUA | D69: Nacional | E69: Público nacional | F69: Repositorio de datos | G69: Nacional y cuencas | H69: Descarga de series y publicaciones hidrológicas para reutilización. | I69: https://www.ambiente.gub.uy/informacion_hidrica/datos_abiertos.php | J69: T33 · Agua y recursos hídricos | K69: =LEFT(J69,3) -> T33 | M69: =IF(L69="",K69,K69&"; "&L69) -> T33 | N69: =INDEX('Taxonomía temas'!$D$2:$D$54,MATCH(K69,'Taxonomía temas'!$A$2:$A$54,0)) -> Ambiente, energía y clima | O69: =INDEX('Taxonomía temas'!$F$2:$F$54,MATCH(K69,'Taxonomía temas'!$A$2:$A$54,0)) -> 6 | Q69: 1 · Datos | R69: Sí | S69: Por verificar | T69: Por verificar | U69: Por verificar | V69: 2020–2021 en anuario localizado | W69: =IF(V69="","No","Sí") -> Sí | Y69: DINAGUA | Z69: No se verificó que ese anuario represente el último dato de todas las series. | AA69: https://www.ambiente.gub.uy/informacion_hidrica/datos_abiertos.php | AB69: 2026-10-02 | AC69: Ambiental y energía | AD69: agua; estaciones; series-históricas; datos-abiertos | AE69: Relevamiento 02/10/2026
A70: UY-069 | B70: Geoportal OAN | C70: Ministerio de Ambiente | D70: Nacional | E70: Público nacional | F70: Módulo | G70: Nacional | H70: Cartografía y capas de información ambiental para visualización territorial. | I70: https://www.ambiente.gub.uy/oan/geoportal/ | J70: T32 · Ambiente y biodiversidad | K70: =LEFT(J70,3) -> T32 | L70: T41 | M70: =IF(L70="",K70,K70&"; "&L70) -> T32; T41 | N70: =INDEX('Taxonomía temas'!$D$2:$D$54,MATCH(K70,'Taxonomía temas'!$A$2:$A$54,0)) -> Ambiente, energía y clima | O70: =INDEX('Taxonomía temas'!$F$2:$F$54,MATCH(K70,'Taxonomía temas'!$A$2:$A$54,0)) -> 15 | Q70: 3 · Visualización interactiva | R70: Por verificar | S70: Por verificar | T70: Sí | U70: Por verificar | W70: =IF(V70="","No","Sí") -> No | Y70: Observatorio Ambiental Nacional — OAN | Z70: Vigencia según capa. | AA70: https://www.ambiente.gub.uy/oan/geoportal/ | AB70: 2026-10-02 | AC70: Ambiental y energía | AD70: ambiente; geodatos; territorio; ecosistemas | AE70: Relevamiento 02/10/2026
A71: UY-070 | B71: GRAS — clima y estaciones | C71: INIA | D71: Nacional | E71: Público no estatal | F71: Portal de datos | G71: Nacional | H71: Información meteorológica y agroclimática de estaciones y otros productos de apoyo al agro. | I71: https://www.inia.uy/gras/Clima | J71: T35 · Clima, meteorología y cambio climático | K71: =LEFT(J71,3) -> T35 | L71: T04 | M71: =IF(L71="",K71,K71&"; "&L71) -> T35; T04 | N71: =INDEX('Taxonomía temas'!$D$2:$D$54,MATCH(K71,'Taxonomía temas'!$A$2:$A$54,0)) -> Ambiente, energía y clima | O71: =INDEX('Taxonomía temas'!$F$2:$F$54,MATCH(K71,'Taxonomía temas'!$A$2:$A$54,0)) -> 13 | Q71: 1 · Datos | R71: Por verificar | S71: Por verificar | T71: Por verificar | U71: Por verificar | W71: =IF(V71="","No","Sí") -> No | Z71: Frecuencia distinta según producto. | AA71: https://www.inia.uy/gras/Clima https://inia.uy/gras/Clima/Estaciones-on-line | AB71: 2026-10-02 | AC71: Ambiental y energía | AD71: clima; agro; estaciones; precipitación | AE71: Relevamiento 02/10/2026
A72: UY-071 | B72: GRAS — monitoreo ambiental | C72: INIA | D72: Nacional | E72: Público no estatal | F72: Monitor | G72: Nacional | H72: Seguimiento de vegetación, balance hídrico y condiciones ambientales relevantes para la producción. | I72: https://www.inia.uy/gras/Monitoreo-Ambiental | J72: T35 · Clima, meteorología y cambio climático | K72: =LEFT(J72,3) -> T35 | L72: T04; T33 | M72: =IF(L72="",K72,K72&"; "&L72) -> T35; T04; T33 | N72: =INDEX('Taxonomía temas'!$D$2:$D$54,MATCH(K72,'Taxonomía temas'!$A$2:$A$54,0)) -> Ambiente, energía y clima | O72: =INDEX('Taxonomía temas'!$F$2:$F$54,MATCH(K72,'Taxonomía temas'!$A$2:$A$54,0)) -> 13 | Q72: 3 · Visualización interactiva | R72: Por verificar | S72: Por verificar | T72: Por verificar | U72: Por verificar | W72: =IF(V72="","No","Sí") -> No | Z72: Último corte no comprobado. | AA72: https://www.inia.uy/gras/Monitoreo-Ambiental | AB72: 2026-10-02 | AC72: Ambiental y energía | AD72: agro; sequía; vegetación; balance-hídrico | AE72: Relevamiento 02/10/2026
A73: UY-072 | B73: Indicadores ambientales OAN | C73: Ministerio de Ambiente | D73: Nacional | E73: Público nacional | F73: Módulo | G73: Nacional | H73: Indicadores temáticos del estado del ambiente y de las presiones sobre los ecosistemas. | I73: https://www.ambiente.gub.uy/oan/indicadores/ | J73: T32 · Ambiente y biodiversidad | K73: =LEFT(J73,3) -> T32 | M73: =IF(L73="",K73,K73&"; "&L73) -> T32 | N73: =INDEX('Taxonomía temas'!$D$2:$D$54,MATCH(K73,'Taxonomía temas'!$A$2:$A$54,0)) -> Ambiente, energía y clima | O73: =INDEX('Taxonomía temas'!$F$2:$F$54,MATCH(K73,'Taxonomía temas'!$A$2:$A$54,0)) -> 15 | Q73: 3 · Visualización interactiva | R73: Por verificar | S73: Por verificar | T73: Por verificar | U73: Por verificar | W73: =IF(V73="","No","Sí") -> No | Y73: Observatorio Ambiental Nacional — OAN | Z73: El año depende de cada indicador. | AA73: https://www.ambiente.gub.uy/oan/indicadores/ | AB73: 2026-10-02 | AC73: Ambiental y energía | AD73: ambiente; indicadores; ecosistemas; presiones | AE73: Relevamiento 02/10/2026
A74: UY-073 | B74: Información meteorológica y climática | C74: INUMET | D74: Nacional | E74: Público nacional | F74: Portal de datos | G74: Nacional | H74: Observaciones, boletines y productos meteorológicos y climáticos del territorio nacional. | I74: https://www.inumet.gub.uy/ | J74: T35 · Clima, meteorología y cambio climático | K74: =LEFT(J74,3) -> T35 | M74: =IF(L74="",K74,K74&"; "&L74) -> T35 | N74: =INDEX('Taxonomía temas'!$D$2:$D$54,MATCH(K74,'Taxonomía temas'!$A$2:$A$54,0)) -> Ambiente, energía y clima | O74: =INDEX('Taxonomía temas'!$F$2:$F$54,MATCH(K74,'Taxonomía temas'!$A$2:$A$54,0)) -> 13 | Q74: 1 · Datos | R74: Por verificar | S74: Por verificar | T74: Por verificar | U74: Por verificar | V74: 2 de octubre de 2026: observaciones | W74: =IF(V74="","No","Sí") -> Sí | Z74: La fecha de observación no se aplica a todas las series históricas. | AA74: https://www.inumet.gub.uy/ | AB74: 2026-10-02 | AC74: Ambiental y energía | AD74: meteorología; clima; precipitación; temperatura | AE74: Relevamiento 02/10/2026
A75: UY-074 | B75: Información operativa del mercado eléctrico | C75: ADME | D75: Nacional | E75: Público no estatal | F75: Monitor | G75: Nacional | H75: Indicadores operativos, generación por fuente, demanda y datos del mercado eléctrico. | I75: https://adme.uy/controlpanel.php | J75: T34 · Energía | K75: =LEFT(J75,3) -> T34 | M75: =IF(L75="",K75,K75&"; "&L75) -> T34 | N75: =INDEX('Taxonomía temas'!$D$2:$D$54,MATCH(K75,'Taxonomía temas'!$A$2:$A$54,0)) -> Ambiente, energía y clima | O75: =INDEX('Taxonomía temas'!$F$2:$F$54,MATCH(K75,'Taxonomía temas'!$A$2:$A$54,0)) -> 7 | Q75: 3 · Visualización interactiva | R75: Por verificar | S75: Por verificar | T75: Por verificar | U75: Por verificar | W75: =IF(V75="","No","Sí") -> No | Z75: Panel con actualización operativa; último sello temporal no comprobado. | AA75: https://adme.uy/controlpanel.php https://www.adme.com.uy/datosabiertos.html | AB75: 2026-10-02 | AC75: Ambiental y energía | AD75: electricidad; generación; demanda; mercado-eléctrico | AE75: Relevamiento 02/10/2026
A76: UY-075 | B76: MapBiomas Uruguay | C76: Red MapBiomas Uruguay | D76: Nacional | E76: Interinstitucional / mixto | F76: Monitor | G76: Nacional | H76: Series cartográficas anuales de cobertura y uso del suelo con consulta y descarga. | I76: https://uruguay.mapbiomas.org/ | J76: T32 · Ambiente y biodiversidad | K76: =LEFT(J76,3) -> T32 | L76: T04; T41 | M76: =IF(L76="",K76,K76&"; "&L76) -> T32; T04; T41 | N76: =INDEX('Taxonomía temas'!$D$2:$D$54,MATCH(K76,'Taxonomía temas'!$A$2:$A$54,0)) -> Ambiente, energía y clima | O76: =INDEX('Taxonomía temas'!$F$2:$F$54,MATCH(K76,'Taxonomía temas'!$A$2:$A$54,0)) -> 15 | Q76: 3 · Visualización interactiva | R76: Sí | S76: Por verificar | T76: Sí | U76: Por verificar | V76: 1985–2024 | W76: =IF(V76="","No","Sí") -> Sí | Z76: Colección verificada hasta 2024; colaboración académica y de sociedad civil. | AA76: https://uruguay.mapbiomas.org/ https://uruguay.mapbiomas.org/colecciones-mapbiomas/ | AB76: 2026-10-02 | AC76: Ambiental y energía | AD76: cobertura-suelo; uso-suelo; ecosistemas; teledetección | AE76: Relevamiento 02/10/2026
A77: UY-076 | B77: Monitor Integral de Riesgos y Afectaciones — MIRA | C77: Sistema Nacional de Emergencias | D77: Nacional | E77: Público nacional | F77: Monitor | G77: Nacional | H77: Sistema de información para registrar y analizar eventos adversos y sus impactos. | I77: https://www.gub.uy/sistema-nacional-emergencias/politicas-y-gestion/monitor-integral-riesgos-afectaciones | J77: T38 · Riesgos y emergencias | K77: =LEFT(J77,3) -> T38 | M77: =IF(L77="",K77,K77&"; "&L77) -> T38 | N77: =INDEX('Taxonomía temas'!$D$2:$D$54,MATCH(K77,'Taxonomía temas'!$A$2:$A$54,0)) -> Ambiente, energía y clima | O77: =INDEX('Taxonomía temas'!$F$2:$F$54,MATCH(K77,'Taxonomía temas'!$A$2:$A$54,0)) -> 11 | Q77: 3 · Visualización interactiva | R77: Por verificar | S77: Por verificar | T77: Sí | U77: Por verificar | W77: =IF(V77="","No","Sí") -> No | X77: 2026-07-09 | Z77: Ficha pública; acceso a todos los componentes y bases no confirmado. | AA77: https://www.gub.uy/sistema-nacional-emergencias/politicas-y-gestion/monitor-integral-riesgos-afectaciones | AB77: 2026-10-02 | AC77: Ambiental y energía | AD77: riesgos; emergencias; afectaciones; territorio | AE77: Relevamiento 02/10/2026
A78: UY-077 | B78: Observatorio Ambiental de Montevideo | C78: Intendencia de Montevideo | D78: Departamental | E78: Gobierno departamental | F78: Módulo | G78: Montevideo | H78: Información sobre calidad ambiental, residuos, saneamiento y gestión de ecosistemas urbanos. | I78: https://montevidata.montevideo.gub.uy/ambiental | J78: T32 · Ambiente y biodiversidad | K78: =LEFT(J78,3) -> T32 | L78: T33; T36 | M78: =IF(L78="",K78,K78&"; "&L78) -> T32; T33; T36 | N78: =INDEX('Taxonomía temas'!$D$2:$D$54,MATCH(K78,'Taxonomía temas'!$A$2:$A$54,0)) -> Ambiente, energía y clima | O78: =INDEX('Taxonomía temas'!$F$2:$F$54,MATCH(K78,'Taxonomía temas'!$A$2:$A$54,0)) -> 15 | P78: E09 · Territorial y subnacional | Q78: 3 · Visualización interactiva | R78: Por verificar | S78: Por verificar | T78: Sí | U78: Por verificar | W78: =IF(V78="","No","Sí") -> No | Y78: Montevidata | Z78: Fecha variable por tablero. | AA78: https://montevidata.montevideo.gub.uy/ambiental | AB78: 2026-10-02 | AC78: Ambiental y energía | AD78: montevideo; ambiente; agua; aire; residuos | AE78: Relevamiento 02/10/2026
A79: UY-078 | B79: Observatorio Ambiental Nacional — OAN | C79: Ministerio de Ambiente | D79: Nacional | E79: Público nacional | F79: Observatorio | G79: Nacional | H79: Información pública ambiental, reportes, indicadores y recursos geográficos. | I79: https://www.ambiente.gub.uy/oan/ | J79: T32 · Ambiente y biodiversidad | K79: =LEFT(J79,3) -> T32 | L79: T33; T36; T35 | M79: =IF(L79="",K79,K79&"; "&L79) -> T32; T33; T36; T35 | N79: =INDEX('Taxonomía temas'!$D$2:$D$54,MATCH(K79,'Taxonomía temas'!$A$2:$A$54,0)) -> Ambiente, energía y clima | O79: =INDEX('Taxonomía temas'!$F$2:$F$54,MATCH(K79,'Taxonomía temas'!$A$2:$A$54,0)) -> 15 | Q79: 4 · Análisis e informes | R79: Por verificar | S79: Por verificar | T79: Por verificar | U79: Por verificar | W79: =IF(V79="","No","Sí") -> No | Z79: Acceso confirmado por ficha oficial; no se auditó cada tablero dinámico. | AA79: https://www.gub.uy/ministerio-ambiente/tramites-y-servicios/servicios/observatorio-ambiental-nacional | AB79: 2026-10-02 | AC79: Ambiental y energía | AD79: ambiente; agua; aire; biodiversidad; residuos | AE79: Relevamiento 02/10/2026
A80: UY-079 | B80: Observatorio de Energía y Desarrollo Sustentable | C80: Universidad Católica del Uruguay | D80: Nacional | E80: Académico | F80: Observatorio de estudios | G80: Nacional | H80: Estudios y análisis sobre energía, transición y desarrollo sustentable. | I80: https://www.ucu.edu.uy/Institucionales/Observatorio-de-Energia-y-Desarrollo-Sustentable-uc839 | J80: T34 · Energía | K80: =LEFT(J80,3) -> T34 | L80: T35 | M80: =IF(L80="",K80,K80&"; "&L80) -> T34; T35 | N80: =INDEX('Taxonomía temas'!$D$2:$D$54,MATCH(K80,'Taxonomía temas'!$A$2:$A$54,0)) -> Ambiente, energía y clima | O80: =INDEX('Taxonomía temas'!$F$2:$F$54,MATCH(K80,'Taxonomía temas'!$A$2:$A$54,0)) -> 7 | Q80: 4 · Análisis e informes | R80: Por verificar | S80: Por verificar | T80: Por verificar | U80: Por verificar | W80: =IF(V80="","No","Sí") -> No | Z80: Se incluye como observatorio académico; disponibilidad de una base numérica permanente no confirmada. | AA80: https://www.ucu.edu.uy/Institucionales/Observatorio-de-Energia-y-Desarrollo-Sustentable-uc839 | AB80: 2026-10-02 | AC80: Ambiental y energía | AD80: energía; sostenibilidad; transición; investigación | AE80: Relevamiento 02/10/2026
A81: UY-080 | B81: Observatorio de Reciclaje del Uruguay | C81: CEMPRE Uruguay | D81: Nacional | E81: Sociedad civil / investigación | F81: Observatorio | G81: Nacional | H81: Datos y análisis sobre reciclaje, materiales y gestión de residuos. | I81: https://cempre.org.uy/observatorio-de-reciclaje-del-uruguay-cempre/ | J81: T36 · Residuos y economía circular | K81: =LEFT(J81,3) -> T36 | M81: =IF(L81="",K81,K81&"; "&L81) -> T36 | N81: =INDEX('Taxonomía temas'!$D$2:$D$54,MATCH(K81,'Taxonomía temas'!$A$2:$A$54,0)) -> Ambiente, energía y clima | O81: =INDEX('Taxonomía temas'!$F$2:$F$54,MATCH(K81,'Taxonomía temas'!$A$2:$A$54,0)) -> 12 | Q81: 4 · Análisis e informes | R81: Por verificar | S81: Por verificar | T81: Por verificar | U81: Por verificar | W81: =IF(V81="","No","Sí") -> No | Z81: Último año de datos no comprobado. | AA81: https://cempre.org.uy/observatorio-de-reciclaje-del-uruguay-cempre/ | AB81: 2026-10-02 | AC81: Ambiental y energía | AD81: reciclaje; residuos; economía-circular | AE81: Relevamiento 02/10/2026
A82: UY-081 | B82: Observatorio Hidrológico Nacional | C82: Ministerio de Ambiente / DINAGUA | D82: Nacional | E82: Público nacional | F82: Observatorio | G82: Nacional y cuencas | H82: Seguimiento de situación hidrológica, estaciones, niveles y recursos hídricos. | I82: https://www.gub.uy/ministerio-ambiente/tramites-y-servicios/servicios/observatorio-hidrologico-nacional | J82: T33 · Agua y recursos hídricos | K82: =LEFT(J82,3) -> T33 | L82: T38 | M82: =IF(L82="",K82,K82&"; "&L82) -> T33; T38 | N82: =INDEX('Taxonomía temas'!$D$2:$D$54,MATCH(K82,'Taxonomía temas'!$A$2:$A$54,0)) -> Ambiente, energía y clima | O82: =INDEX('Taxonomía temas'!$F$2:$F$54,MATCH(K82,'Taxonomía temas'!$A$2:$A$54,0)) -> 6 | Q82: 4 · Análisis e informes | R82: Por verificar | S82: Por verificar | T82: Por verificar | U82: Por verificar | W82: =IF(V82="","No","Sí") -> No | Z82: Enlace a la ficha oficial con acceso al observatorio. | AA82: https://www.gub.uy/ministerio-ambiente/tramites-y-servicios/servicios/observatorio-hidrologico-nacional | AB82: 2026-10-02 | AC82: Ambiental y energía | AD82: agua; hidrología; sequía; inundaciones | AE82: Relevamiento 02/10/2026
A83: UY-082 | B83: SIGRAS | C83: INIA | D83: Nacional | E83: Público no estatal | F83: Geoportal | G83: Nacional | H83: Visualización y consulta geográfica de información agroambiental. | I83: https://inia.uy/gras-sigras-web | J83: T04 · Agro y cadenas agroindustriales | K83: =LEFT(J83,3) -> T04 | L83: T35; T37; T41 | M83: =IF(L83="",K83,K83&"; "&L83) -> T04; T35; T37; T41 | N83: =INDEX('Taxonomía temas'!$D$2:$D$54,MATCH(K83,'Taxonomía temas'!$A$2:$A$54,0)) -> Economía y producción | O83: =INDEX('Taxonomía temas'!$F$2:$F$54,MATCH(K83,'Taxonomía temas'!$A$2:$A$54,0)) -> 2 | Q83: 3 · Visualización interactiva | R83: Por verificar | S83: Por verificar | T83: Sí | U83: Por verificar | W83: =IF(V83="","No","Sí") -> No | Z83: Complementa los productos de GRAS; fechas por capa. | AA83: https://inia.uy/gras-sigras-web | AB83: 2026-10-02 | AC83: Ambiental y energía | AD83: agro; geodatos; suelos; clima | AE83: Relevamiento 02/10/2026
A84: UY-083 | B84: Visualizador de avances de la contribución climática nacional | C84: Ministerio de Ambiente / SNRCC | D84: Nacional | E84: Interinstitucional / mixto | F84: Visualizador | G84: Nacional | H84: Seguimiento de medidas y objetivos de la contribución nacional al Acuerdo de París. | I84: https://catalogodatos.gub.uy/showcase/visualizador-de-objetivos-y-medidas-de-mitigacion-y-adaptacion-ante-el-cambio-climatico | J84: T35 · Clima, meteorología y cambio climático | K84: =LEFT(J84,3) -> T35 | M84: =IF(L84="",K84,K84&"; "&L84) -> T35 | N84: =INDEX('Taxonomía temas'!$D$2:$D$54,MATCH(K84,'Taxonomía temas'!$A$2:$A$54,0)) -> Ambiente, energía y clima | O84: =INDEX('Taxonomía temas'!$F$2:$F$54,MATCH(K84,'Taxonomía temas'!$A$2:$A$54,0)) -> 13 | Q84: 3 · Visualización interactiva | R84: Por verificar | S84: Por verificar | T84: Por verificar | U84: Por verificar | W84: =IF(V84="","No","Sí") -> No | Z84: Entrada mediante ficha del Catálogo Nacional de Datos Abiertos. | AA84: https://catalogodatos.gub.uy/showcase/visualizador-de-objetivos-y-medidas-de-mitigacion-y-adaptacion-ante-el-cambio-climatico | AB84: 2026-10-02 | AC84: Ambiental y energía | AD84: cambio-climático; emisiones; ndc; compromisos | AE84: Relevamiento 02/10/2026
A85: UY-084 | B85: Visualizador de cambio climático | C85: Ministerio de Ambiente | D85: Nacional | E85: Público nacional | F85: Geoportal | G85: Nacional | H85: Capas espaciales vinculadas a impactos, vulnerabilidad y respuesta frente al cambio climático. | I85: https://www.ambiente.gub.uy/visualizador/index.php?vis=cambio-climatico | J85: T35 · Clima, meteorología y cambio climático | K85: =LEFT(J85,3) -> T35 | L85: T38; T41 | M85: =IF(L85="",K85,K85&"; "&L85) -> T35; T38; T41 | N85: =INDEX('Taxonomía temas'!$D$2:$D$54,MATCH(K85,'Taxonomía temas'!$A$2:$A$54,0)) -> Ambiente, energía y clima | O85: =INDEX('Taxonomía temas'!$F$2:$F$54,MATCH(K85,'Taxonomía temas'!$A$2:$A$54,0)) -> 13 | Q85: 3 · Visualización interactiva | R85: Por verificar | S85: Por verificar | T85: Sí | U85: Por verificar | W85: =IF(V85="","No","Sí") -> No | Z85: Período variable según capa. | AA85: https://www.ambiente.gub.uy/visualizador/index.php?vis=cambio-climatico | AB85: 2026-10-02 | AC85: Ambiental y energía | AD85: cambio-climático; adaptación; riesgo; geodatos | AE85: Relevamiento 02/10/2026
A86: UY-085 | B86: Visualizador de gráficos y series BEN | C86: MIEM / DNE | D86: Nacional | E86: Público nacional | F86: Módulo | G86: Nacional | H86: Consulta y exportación de gráficos y series históricas del balance energético. | I86: https://visualizadorben.miem.gub.uy/visualizador/api/repos/%3Apublic%3Aorganismos%3Amiem%3Amiem_ben.wcdf/generatedContent | J86: T34 · Energía | K86: =LEFT(J86,3) -> T34 | M86: =IF(L86="",K86,K86&"; "&L86) -> T34 | N86: =INDEX('Taxonomía temas'!$D$2:$D$54,MATCH(K86,'Taxonomía temas'!$A$2:$A$54,0)) -> Ambiente, energía y clima | O86: =INDEX('Taxonomía temas'!$F$2:$F$54,MATCH(K86,'Taxonomía temas'!$A$2:$A$54,0)) -> 7 | Q86: 3 · Visualización interactiva | R86: Sí | S86: Por verificar | T86: Por verificar | U86: Por verificar | W86: =IF(V86="","No","Sí") -> No | Y86: Balance Energético Nacional — BEN | Z86: Verificar el año seleccionado; no se auditó la actualización de cada gráfico. | AA86: https://visualizadorben.miem.gub.uy/visualizador/api/repos/%3Apublic%3Aorganismos%3Amiem%3Amiem_ben.wcdf/generatedContent | AB86: 2026-10-02 | AC86: Ambiental y energía | AD86: energía; series-históricas; consumo; oferta | AE86: Relevamiento 02/10/2026
A87: UY-086 | B87: Visualizador Estratégico de Residuos — VER | C87: CEMPRE Uruguay | D87: Nacional | E87: Sociedad civil / investigación | F87: Visualizador | G87: Nacional | H87: Herramienta territorial para analizar información y oportunidades de gestión de residuos. | I87: https://cempre.org.uy/v-e-r-visualizador-estrategico-de-residuos-3/ | J87: T36 · Residuos y economía circular | K87: =LEFT(J87,3) -> T36 | L87: T41 | M87: =IF(L87="",K87,K87&"; "&L87) -> T36; T41 | N87: =INDEX('Taxonomía temas'!$D$2:$D$54,MATCH(K87,'Taxonomía temas'!$A$2:$A$54,0)) -> Ambiente, energía y clima | O87: =INDEX('Taxonomía temas'!$F$2:$F$54,MATCH(K87,'Taxonomía temas'!$A$2:$A$54,0)) -> 12 | Q87: 3 · Visualización interactiva | R87: Por verificar | S87: Por verificar | T87: Sí | U87: Por verificar | W87: =IF(V87="","No","Sí") -> No | Y87: CEMPRE | Z87: Acceso mediante página institucional de presentación. | AA87: https://cempre.org.uy/v-e-r-visualizador-estrategico-de-residuos-3/ | AB87: 2026-10-02 | AC87: Ambiental y energía | AD87: residuos; geodatos; reciclaje; economía-circular | AE87: Relevamiento 02/10/2026
A88: UY-087 | B88: Visualizadores de información hídrica | C88: Ministerio de Ambiente / DINAGUA | D88: Nacional | E88: Público nacional | F88: Geoportal | G88: Nacional y cuencas | H88: Mapas y consultas de información hídrica, aprovechamientos y áreas expuestas a inundaciones. | I88: https://www.ambiente.gub.uy/informacion_hidrica/ | J88: T33 · Agua y recursos hídricos | K88: =LEFT(J88,3) -> T33 | L88: T38; T41 | M88: =IF(L88="",K88,K88&"; "&L88) -> T33; T38; T41 | N88: =INDEX('Taxonomía temas'!$D$2:$D$54,MATCH(K88,'Taxonomía temas'!$A$2:$A$54,0)) -> Ambiente, energía y clima | O88: =INDEX('Taxonomía temas'!$F$2:$F$54,MATCH(K88,'Taxonomía temas'!$A$2:$A$54,0)) -> 6 | Q88: 3 · Visualización interactiva | R88: Por verificar | S88: Por verificar | T88: Sí | U88: Por verificar | W88: =IF(V88="","No","Sí") -> No | Z88: Herramientas de DINAGUA; pueden compartir datos con el observatorio. | AA88: https://www.ambiente.gub.uy/informacion_hidrica/ | AB88: 2026-10-02 | AC88: Ambiental y energía | AD88: agua; usos; inundaciones; geodatos | AE88: Relevamiento 02/10/2026
A89: UY-088 | B89: VisualPEB — matriz energética | C89: MIEM / DNE | D89: Nacional | E89: Público nacional | F89: Módulo | G89: Nacional | H89: Representación y consulta de las relaciones entre fuentes y usos de energía. | I89: https://visualpeb.miem.gub.uy/visualPEB/ben | J89: T34 · Energía | K89: =LEFT(J89,3) -> T34 | M89: =IF(L89="",K89,K89&"; "&L89) -> T34 | N89: =INDEX('Taxonomía temas'!$D$2:$D$54,MATCH(K89,'Taxonomía temas'!$A$2:$A$54,0)) -> Ambiente, energía y clima | O89: =INDEX('Taxonomía temas'!$F$2:$F$54,MATCH(K89,'Taxonomía temas'!$A$2:$A$54,0)) -> 7 | Q89: 3 · Visualización interactiva | R89: Por verificar | S89: Por verificar | T89: Por verificar | U89: Por verificar | W89: =IF(V89="","No","Sí") -> No | Y89: Balance Energético Nacional — BEN | Z89: Comparte el sistema de información del BEN. | AA89: https://visualpeb.miem.gub.uy/visualPEB/ben | AB89: 2026-10-02 | AC89: Ambiental y energía | AD89: energía; balance; flujos; matriz | AE89: Relevamiento 02/10/2026
A90: UY-089 | B90: Buscador de indicadores OTU | C90: OPP | D90: Nacional | E90: Público nacional | F90: Módulo | G90: Nacional y subnacional | H90: Búsqueda de indicadores para comparar condiciones de los territorios. | I90: https://otu.opp.gub.uy/filtros/buscar_indicadores | J90: T39 · Territorio, ordenamiento y desarrollo local | K90: =LEFT(J90,3) -> T39 | M90: =IF(L90="",K90,K90&"; "&L90) -> T39 | N90: =INDEX('Taxonomía temas'!$D$2:$D$54,MATCH(K90,'Taxonomía temas'!$A$2:$A$54,0)) -> Territorio, vivienda y movilidad | O90: =INDEX('Taxonomía temas'!$F$2:$F$54,MATCH(K90,'Taxonomía temas'!$A$2:$A$54,0)) -> 11 | P90: E09 · Territorial y subnacional | Q90: 3 · Visualización interactiva | R90: Por verificar | S90: Por verificar | T90: Sí | U90: Por verificar | W90: =IF(V90="","No","Sí") -> No | Y90: Observatorio Territorio Uruguay — OTU | Z90: Vigencia por indicador; no se verificó un último corte global. | AA90: https://otu.opp.gub.uy/ | AB90: 2026-10-02 | AC90: Territorial | AD90: territorio; indicadores; departamentos; municipios | AE90: Relevamiento 02/10/2026
A91: UY-090 | B91: Geoportal MTOP | C91: Ministerio de Transporte y Obras Públicas | D91: Nacional | E91: Público nacional | F91: Geoportal | G91: Nacional | H91: Información geográfica sobre infraestructura y redes de transporte. | I91: https://geoportal.mtop.gub.uy/ | J91: T08 · Logística, transporte de cargas e infraestructura | K91: =LEFT(J91,3) -> T08 | L91: T41 | M91: =IF(L91="",K91,K91&"; "&L91) -> T08; T41 | N91: =INDEX('Taxonomía temas'!$D$2:$D$54,MATCH(K91,'Taxonomía temas'!$A$2:$A$54,0)) -> Economía y producción | O91: =INDEX('Taxonomía temas'!$F$2:$F$54,MATCH(K91,'Taxonomía temas'!$A$2:$A$54,0)) -> 9 | Q91: 3 · Visualización interactiva | R91: Por verificar | S91: Por verificar | T91: Sí | U91: Por verificar | W91: =IF(V91="","No","Sí") -> No | Z91: Vigencia por capa. | AA91: https://geoportal.mtop.gub.uy/ | AB91: 2026-10-02 | AC91: Territorial | AD91: infraestructura; transporte; rutas; geodatos | AE91: Relevamiento 02/10/2026
A92: UY-091 | B92: Geoportal y servicios cartográficos IGM | C92: Instituto Geográfico Militar | D92: Nacional | E92: Público nacional | F92: Geoportal | G92: Nacional | H92: Servicios cartográficos y recursos para consultar información geográfica de base. | I92: https://igm.gub.uy/geoportal/listado-servicios/ | J92: T41 · Información geográfica, cartografía y catastro | K92: =LEFT(J92,3) -> T41 | M92: =IF(L92="",K92,K92&"; "&L92) -> T41 | N92: =INDEX('Taxonomía temas'!$D$2:$D$54,MATCH(K92,'Taxonomía temas'!$A$2:$A$54,0)) -> Territorio, vivienda y movilidad | O92: =INDEX('Taxonomía temas'!$F$2:$F$54,MATCH(K92,'Taxonomía temas'!$A$2:$A$54,0)) -> 17 | Q92: 3 · Visualización interactiva | R92: Por verificar | S92: Por verificar | T92: Sí | U92: Por verificar | W92: =IF(V92="","No","Sí") -> No | Z92: Vigencia y escala dependen del producto. | AA92: https://igm.gub.uy/geoportal/listado-servicios/ | AB92: 2026-10-02 | AC92: Territorial | AD92: cartografía; geodesia; geodatos; topografía | AE92: Relevamiento 02/10/2026
A93: UY-092 | B93: GIS Rivera | C93: Intendencia de Rivera | D93: Departamental | E93: Gobierno departamental | F93: Geoportal | G93: Rivera | H93: Visor de información geográfica y capas territoriales del departamento. | I93: https://gis.rivera.gub.uy/ | J93: T41 · Información geográfica, cartografía y catastro | K93: =LEFT(J93,3) -> T41 | L93: T39 | M93: =IF(L93="",K93,K93&"; "&L93) -> T41; T39 | N93: =INDEX('Taxonomía temas'!$D$2:$D$54,MATCH(K93,'Taxonomía temas'!$A$2:$A$54,0)) -> Territorio, vivienda y movilidad | O93: =INDEX('Taxonomía temas'!$F$2:$F$54,MATCH(K93,'Taxonomía temas'!$A$2:$A$54,0)) -> 17 | P93: E09 · Territorial y subnacional | Q93: 3 · Visualización interactiva | R93: Por verificar | S93: Por verificar | T93: Sí | U93: Por verificar | W93: =IF(V93="","No","Sí") -> No | Z93: Vigencia por capa. | AA93: https://gis.rivera.gub.uy/ | AB93: 2026-10-02 | AC93: Territorial | AD93: rivera; geodatos; territorio; infraestructura | AE93: Relevamiento 02/10/2026
A94: UY-093 | B94: Inventario Nacional de Ordenamiento Territorial — INOT | C94: MVOT / DINOT | D94: Nacional | E94: Público nacional | F94: Geoportal | G94: Nacional | H94: Consulta territorial de instrumentos y normativa de ordenamiento. | I94: https://geoportal.mvot.gub.uy/sitio/portal/inot | J94: T39 · Territorio, ordenamiento y desarrollo local | K94: =LEFT(J94,3) -> T39 | M94: =IF(L94="",K94,K94&"; "&L94) -> T39 | N94: =INDEX('Taxonomía temas'!$D$2:$D$54,MATCH(K94,'Taxonomía temas'!$A$2:$A$54,0)) -> Territorio, vivienda y movilidad | O94: =INDEX('Taxonomía temas'!$F$2:$F$54,MATCH(K94,'Taxonomía temas'!$A$2:$A$54,0)) -> 11 | Q94: 3 · Visualización interactiva | R94: Por verificar | S94: Por verificar | T94: Sí | U94: Por verificar | W94: =IF(V94="","No","Sí") -> No | Z94: La vigencia corresponde a cada instrumento. | AA94: https://geoportal.mvot.gub.uy/sitio/portal/inot | AB94: 2026-10-02 | AC94: Territorial | AD94: ordenamiento-territorial; normativa; instrumentos | AE94: Relevamiento 02/10/2026
A95: UY-094 | B95: Mirador OTU | C95: OPP | D95: Nacional | E95: Público nacional | F95: Módulo | G95: Nacional y subnacional | H95: Herramienta del OTU para explorar información y actuaciones en el territorio. | I95: https://otu.opp.gub.uy/mirador | J95: T39 · Territorio, ordenamiento y desarrollo local | K95: =LEFT(J95,3) -> T39 | L95: T02 | M95: =IF(L95="",K95,K95&"; "&L95) -> T39; T02 | N95: =INDEX('Taxonomía temas'!$D$2:$D$54,MATCH(K95,'Taxonomía temas'!$A$2:$A$54,0)) -> Territorio, vivienda y movilidad | O95: =INDEX('Taxonomía temas'!$F$2:$F$54,MATCH(K95,'Taxonomía temas'!$A$2:$A$54,0)) -> 11 | P95: E09 · Territorial y subnacional | Q95: 3 · Visualización interactiva | R95: Por verificar | S95: Por verificar | T95: Sí | U95: Por verificar | W95: =IF(V95="","No","Sí") -> No | Y95: Observatorio Territorio Uruguay — OTU | Z95: URL aportada y contrastada con la estructura institucional; carga no confirmada. | AA95: https://opp.gub.uy/es/observatorio-territorio-uruguay | AB95: 2026-10-02 | AC95: Territorial | AD95: territorio; inversión; proyectos; desarrollo-local | AE95: Relevamiento 02/10/2026
A96: UY-095 | B96: Montevidata | C96: Intendencia de Montevideo | D96: Departamental | E96: Gobierno departamental | F96: Portal de datos | G96: Montevideo | H96: Portal integrador de observatorios y visualizaciones municipales de distintas áreas. | I96: https://montevidata.montevideo.gub.uy/ | J96: T44 · Gobierno abierto y datos abiertos | K96: =LEFT(J96,3) -> T44 | L96: T39 | M96: =IF(L96="",K96,K96&"; "&L96) -> T44; T39 | N96: =INDEX('Taxonomía temas'!$D$2:$D$54,MATCH(K96,'Taxonomía temas'!$A$2:$A$54,0)) -> Estado, gobierno y derechos | O96: =INDEX('Taxonomía temas'!$F$2:$F$54,MATCH(K96,'Taxonomía temas'!$A$2:$A$54,0)) -> 16 | P96: E09 · Territorial y subnacional | Q96: 1 · Datos | R96: Por verificar | S96: Por verificar | T96: Sí | U96: Por verificar | W96: =IF(V96="","No","Sí") -> No | Z96: Los módulos temáticos siguientes se identifican por separado, sin contarlos como nuevos portales matriz. | AA96: https://montevidata.montevideo.gub.uy/ | AB96: 2026-10-02 | AC96: Territorial | AD96: montevideo; indicadores; gestión; datos-abiertos | AE96: Relevamiento 02/10/2026
A97: UY-096 | B97: Observatorio de Asentamientos de Montevideo | C97: Intendencia de Montevideo | D97: Departamental | E97: Gobierno departamental | F97: Módulo | G97: Montevideo | H97: Seguimiento territorial de asentamientos e intervenciones municipales. | I97: https://montevidata.montevideo.gub.uy/territorial/asentamientos | J97: T40 · Vivienda, hábitat y asentamientos | K97: =LEFT(J97,3) -> T40 | M97: =IF(L97="",K97,K97&"; "&L97) -> T40 | N97: =INDEX('Taxonomía temas'!$D$2:$D$54,MATCH(K97,'Taxonomía temas'!$A$2:$A$54,0)) -> Territorio, vivienda y movilidad | O97: =INDEX('Taxonomía temas'!$F$2:$F$54,MATCH(K97,'Taxonomía temas'!$A$2:$A$54,0)) -> 11 | P97: E09 · Territorial y subnacional | Q97: 3 · Visualización interactiva | R97: Por verificar | S97: Por verificar | T97: Sí | U97: Por verificar | W97: =IF(V97="","No","Sí") -> No | X97: 2026-06-26 | Y97: Montevidata | Z97: Fecha de actualización del conjunto de intervenciones; no necesariamente de todas las capas. | AA97: https://ckan.montevideo.gub.uy/dataset/asentamientos-en-montevideo https://catalogodatos.gub.uy/dataset/principales-intervenciones-en-asentamientos-en-montevideo | AB97: 2026-10-02 | AC97: Territorial | AD97: montevideo; asentamientos; vivienda; hábitat | AE97: Relevamiento 02/10/2026
A98: UY-097 | B98: Observatorio de Movilidad de Montevideo | C98: Intendencia de Montevideo | D98: Departamental | E98: Gobierno departamental | F98: Módulo | G98: Montevideo | H98: Datos de transporte público, movilidad activa, tránsito e infraestructura. | I98: https://montevidata.montevideo.gub.uy/movilidad | J98: T42 · Movilidad urbana y seguridad vial | K98: =LEFT(J98,3) -> T42 | M98: =IF(L98="",K98,K98&"; "&L98) -> T42 | N98: =INDEX('Taxonomía temas'!$D$2:$D$54,MATCH(K98,'Taxonomía temas'!$A$2:$A$54,0)) -> Territorio, vivienda y movilidad | O98: =INDEX('Taxonomía temas'!$F$2:$F$54,MATCH(K98,'Taxonomía temas'!$A$2:$A$54,0)) -> 11 | P98: E09 · Territorial y subnacional | Q98: 3 · Visualización interactiva | R98: Por verificar | S98: Por verificar | T98: Sí | U98: Por verificar | W98: =IF(V98="","No","Sí") -> No | Y98: Montevidata | Z98: Fecha variable por tablero. | AA98: https://montevidata.montevideo.gub.uy/movilidad | AB98: 2026-10-02 | AC98: Territorial | AD98: montevideo; movilidad; transporte; tránsito | AE98: Relevamiento 02/10/2026
A99: UY-098 | B99: Observatorio ODS de Montevideo | C99: Intendencia de Montevideo | D99: Departamental | E99: Gobierno departamental | F99: Módulo | G99: Montevideo | H99: Indicadores departamentales para seguir objetivos y metas de desarrollo sostenible. | I99: https://montevidata.montevideo.gub.uy/objetivos-de-desarrollo-sostenible | J99: T49 · Estadística oficial y seguimiento ODS | K99: =LEFT(J99,3) -> T49 | L99: T39 | M99: =IF(L99="",K99,K99&"; "&L99) -> T49; T39 | N99: =INDEX('Taxonomía temas'!$D$2:$D$54,MATCH(K99,'Taxonomía temas'!$A$2:$A$54,0)) -> Estado, gobierno y derechos | O99: =INDEX('Taxonomía temas'!$F$2:$F$54,MATCH(K99,'Taxonomía temas'!$A$2:$A$54,0)) -> 17 | P99: E09 · Territorial y subnacional | Q99: 3 · Visualización interactiva | R99: Por verificar | S99: Por verificar | T99: Sí | U99: Por verificar | W99: =IF(V99="","No","Sí") -> No | Y99: Montevidata | Z99: 2030 es horizonte de metas, no el último año observado. | AA99: https://montevidata.montevideo.gub.uy/objetivos-de-desarrollo-sostenible | AB99: 2026-10-02 | AC99: Territorial | AD99: montevideo; ods; sostenibilidad; indicadores | AE99: Relevamiento 02/10/2026
A100: UY-099 | B100: Observatorio Territorial de Montevideo | C100: Intendencia de Montevideo | D100: Departamental | E100: Gobierno departamental | F100: Módulo | G100: Montevideo | H100: Indicadores de vivienda, hogares, hábitat y dinámicas del territorio departamental. | I100: https://montevidata.montevideo.gub.uy/territorial | J100: T39 · Territorio, ordenamiento y desarrollo local | K100: =LEFT(J100,3) -> T39 | L100: T40 | M100: =IF(L100="",K100,K100&"; "&L100) -> T39; T40 | N100: =INDEX('Taxonomía temas'!$D$2:$D$54,MATCH(K100,'Taxonomía temas'!$A$2:$A$54,0)) -> Territorio, vivienda y movilidad | O100: =INDEX('Taxonomía temas'!$F$2:$F$54,MATCH(K100,'Taxonomía temas'!$A$2:$A$54,0)) -> 11 | P100: E09 · Territorial y subnacional | Q100: 3 · Visualización interactiva | R100: Por verificar | S100: Por verificar | T100: Sí | U100: Por verificar | V100: 2025: vivienda y hogares | W100: =IF(V100="","No","Sí") -> Sí | Y100: Montevidata | Z100: Período comprobado en el módulo de vivienda y hogares. | AA100: https://montevidata.montevideo.gub.uy/territorial https://montevidata.montevideo.gub.uy/territorial/vivienda-y-hogares | AB100: 2026-10-02 | AC100: Territorial | AD100: montevideo; territorio; vivienda; hogares | AE100: Relevamiento 02/10/2026
...

Sheet Cobertura temática
A1: Cobertura temática del ecosistema
A2: Recursos nacionales y departamentales; las referencias internacionales se cuentan aparte. Todas las cifras son fórmulas sobre el inventario.
A4: Código | B4: Área | C4: Tema | D4: ODS | E4: Recursos (tema principal) | F4: Recursos (cualquier mención) | G4: Con análisis e informes (nivel 4) | H4: Con visualización (nivel 3) | I4: Con vigencia comprobada | J4: Referencias internacionales | K4: Estado de cobertura | L4: Concentración | M4: Datasets en Catálogo AGESIC
A5: ='Taxonomía temas'!A2 -> T01 | B5: ='Taxonomía temas'!D2 -> Economía y producción | C5: ='Taxonomía temas'!E2 -> Macroeconomía y cuentas nacionales | D5: ='Taxonomía temas'!F2 -> 8 | E5: =COUNTIFS(Inventario!$K$2:$K$1000,A5,Inventario!$D$2:$D$1000,"<>Internacional") -> 3 | F5: =COUNTIFS(Inventario!$M$2:$M$1000,"*"&A5&"*",Inventario!$D$2:$D$1000,"<>Internacional") -> 7 | G5: =COUNTIFS(Inventario!$M$2:$M$1000,"*"&A5&"*",Inventario!$D$2:$D$1000,"<>Internacional",Inventario!$Q$2:$Q$1000,"4*") -> 3 | H5: =COUNTIFS(Inventario!$M$2:$M$1000,"*"&A5&"*",Inventario!$D$2:$D$1000,"<>Internacional",Inventario!$Q$2:$Q$1000,"3*") -> 1 | I5: =COUNTIFS(Inventario!$M$2:$M$1000,"*"&A5&"*",Inventario!$D$2:$D$1000,"<>Internacional",Inventario!$W$2:$W$1000,"Sí") -> 4 | J5: =COUNTIFS(Inventario!$M$2:$M$1000,"*"&A5&"*",Inventario!$D$2:$D$1000,"Internacional") -> 2 | K5: =IF(F5=0,IF(J5>0,"Sin cobertura nacional (solo internacional)","Sin cobertura"),IF(E5=0,"Cobertura indirecta",IF(G5=0,"Cobertura sin análisis","Cobertura con análisis"))) -> Cobertura con análisis | L5: =IF(E5>=5,"Alta concentración: revisar superposición","") | M5: =HYPERLINK("https://catalogodatos.gub.uy/dataset?q="&SUBSTITUTE('Taxonomía temas'!J2," ","+"),"Buscar datasets") -> Buscar datasets
A6: ='Taxonomía temas'!A3 -> T02 | B6: ='Taxonomía temas'!D3 -> Economía y producción | C6: ='Taxonomía temas'!E3 -> Finanzas públicas, tributación y presupuesto | D6: ='Taxonomía temas'!F3 -> 17 | E6: =COUNTIFS(Inventario!$K$2:$K$1000,A6,Inventario!$D$2:$D$1000,"<>Internacional") -> 3 | F6: =COUNTIFS(Inventario!$M$2:$M$1000,"*"&A6&"*",Inventario!$D$2:$D$1000,"<>Internacional") -> 6 | G6: =COUNTIFS(Inventario!$M$2:$M$1000,"*"&A6&"*",Inventario!$D$2:$D$1000,"<>Internacional",Inventario!$Q$2:$Q$1000,"4*") -> 1 | H6: =COUNTIFS(Inventario!$M$2:$M$1000,"*"&A6&"*",Inventario!$D$2:$D$1000,"<>Internacional",Inventario!$Q$2:$Q$1000,"3*") -> 2 | I6: =COUNTIFS(Inventario!$M$2:$M$1000,"*"&A6&"*",Inventario!$D$2:$D$1000,"<>Internacional",Inventario!$W$2:$W$1000,"Sí") -> 2 | J6: =COUNTIFS(Inventario!$M$2:$M$1000,"*"&A6&"*",Inventario!$D$2:$D$1000,"Internacional") -> 0 | K6: =IF(F6=0,IF(J6>0,"Sin cobertura nacional (solo internacional)","Sin cobertura"),IF(E6=0,"Cobertura indirecta",IF(G6=0,"Cobertura sin análisis","Cobertura con análisis"))) -> Cobertura con análisis | L6: =IF(E6>=5,"Alta concentración: revisar superposición","") | M6: =HYPERLINK("https://catalogodatos.gub.uy/dataset?q="&SUBSTITUTE('Taxonomía temas'!J3," ","+"),"Buscar datasets") -> Buscar datasets
A7: ='Taxonomía temas'!A4 -> T03 | B7: ='Taxonomía temas'!D4 -> Economía y producción | C7: ='Taxonomía temas'!E4 -> Comercio exterior e inversión | D7: ='Taxonomía temas'!F4 -> 17 | E7: =COUNTIFS(Inventario!$K$2:$K$1000,A7,Inventario!$D$2:$D$1000,"<>Internacional") -> 4 | F7: =COUNTIFS(Inventario!$M$2:$M$1000,"*"&A7&"*",Inventario!$D$2:$D$1000,"<>Internacional") -> 13 | G7: =COUNTIFS(Inventario!$M$2:$M$1000,"*"&A7&"*",Inventario!$D$2:$D$1000,"<>Internacional",Inventario!$Q$2:$Q$1000,"4*") -> 3 | H7: =COUNTIFS(Inventario!$M$2:$M$1000,"*"&A7&"*",Inventario!$D$2:$D$1000,"<>Internacional",Inventario!$Q$2:$Q$1000,"3*") -> 3 | I7: =COUNTIFS(Inventario!$M$2:$M$1000,"*"&A7&"*",Inventario!$D$2:$D$1000,"<>Internacional",Inventario!$W$2:$W$1000,"Sí") -> 8 | J7: =COUNTIFS(Inventario!$M$2:$M$1000,"*"&A7&"*",Inventario!$D$2:$D$1000,"Internacional") -> 3 | K7: =IF(F7=0,IF(J7>0,"Sin cobertura nacional (solo internacional)","Sin cobertura"),IF(E7=0,"Cobertura indirecta",IF(G7=0,"Cobertura sin análisis","Cobertura con análisis"))) -> Cobertura con análisis | L7: =IF(E7>=5,"Alta concentración: revisar superposición","") | M7: =HYPERLINK("https://catalogodatos.gub.uy/dataset?q="&SUBSTITUTE('Taxonomía temas'!J4," ","+"),"Buscar datasets") -> Buscar datasets
A8: ='Taxonomía temas'!A5 -> T04 | B8: ='Taxonomía temas'!D5 -> Economía y producción | C8: ='Taxonomía temas'!E5 -> Agro y cadenas agroindustriales | D8: ='Taxonomía temas'!F5 -> 2 | E8: =COUNTIFS(Inventario!$K$2:$K$1000,A8,Inventario!$D$2:$D$1000,"<>Internacional") -> 11 | F8: =COUNTIFS(Inventario!$M$2:$M$1000,"*"&A8&"*",Inventario!$D$2:$D$1000,"<>Internacional") -> 15 | G8: =COUNTIFS(Inventario!$M$2:$M$1000,"*"&A8&"*",Inventario!$D$2:$D$1000,"<>Internacional",Inventario!$Q$2:$Q$1000,"4*") -> 3 | H8: =COUNTIFS(Inventario!$M$2:$M$1000,"*"&A8&"*",Inventario!$D$2:$D$1000,"<>Internacional",Inventario!$Q$2:$Q$1000,"3*") -> 6 | I8: =COUNTIFS(Inventario!$M$2:$M$1000,"*"&A8&"*",Inventario!$D$2:$D$1000,"<>Internacional",Inventario!$W$2:$W$1000,"Sí") -> 7 | J8: =COUNTIFS(Inventario!$M$2:$M$1000,"*"&A8&"*",Inventario!$D$2:$D$1000,"Internacional") -> 1 | K8: =IF(F8=0,IF(J8>0,"Sin cobertura nacional (solo internacional)","Sin cobertura"),IF(E8=0,"Cobertura indirecta",IF(G8=0,"Cobertura sin análisis","Cobertura con análisis"))) -> Cobertura con análisis | L8: =IF(E8>=5,"Alta concentración: revisar superposición","") -> Alta concentración: revisar superposición | M8: =HYPERLINK("https://catalogodatos.gub.uy/dataset?q="&SUBSTITUTE('Taxonomía temas'!J5," ","+"),"Buscar datasets") -> Buscar datasets
A9: ='Taxonomía temas'!A6 -> T05 | B9: ='Taxonomía temas'!D6 -> Economía y producción | C9: ='Taxonomía temas'!E6 -> Industria y manufactura | D9: ='Taxonomía temas'!F6 -> 9 | E9: =COUNTIFS(Inventario!$K$2:$K$1000,A9,Inventario!$D$2:$D$1000,"<>Internacional") -> 2 | F9: =COUNTIFS(Inventario!$M$2:$M$1000,"*"&A9&"*",Inventario!$D$2:$D$1000,"<>Internacional") -> 2 | G9: =COUNTIFS(Inventario!$M$2:$M$1000,"*"&A9&"*",Inventario!$D$2:$D$1000,"<>Internacional",Inventario!$Q$2:$Q$1000,"4*") -> 1 | H9: =COUNTIFS(Inventario!$M$2:$M$1000,"*"&A9&"*",Inventario!$D$2:$D$1000,"<>Internacional",Inventario!$Q$2:$Q$1000,"3*") -> 1 | I9: =COUNTIFS(Inventario!$M$2:$M$1000,"*"&A9&"*",Inventario!$D$2:$D$1000,"<>Internacional",Inventario!$W$2:$W$1000,"Sí") -> 2 | J9: =COUNTIFS(Inventario!$M$2:$M$1000,"*"&A9&"*",Inventario!$D$2:$D$1000,"Internacional") -> 1 | K9: =IF(F9=0,IF(J9>0,"Sin cobertura nacional (solo internacional)","Sin cobertura"),IF(E9=0,"Cobertura indirecta",IF(G9=0,"Cobertura sin análisis","Cobertura con análisis"))) -> Cobertura con análisis | L9: =IF(E9>=5,"Alta concentración: revisar superposición","") | M9: =HYPERLINK("https://catalogodatos.gub.uy/dataset?q="&SUBSTITUTE('Taxonomía temas'!J6," ","+"),"Buscar datasets") -> Buscar datasets
A10: ='Taxonomía temas'!A7 -> T06 | B10: ='Taxonomía temas'!D7 -> Economía y producción | C10: ='Taxonomía temas'!E7 -> Turismo | D10: ='Taxonomía temas'!F7 -> 8 | E10: =COUNTIFS(Inventario!$K$2:$K$1000,A10,Inventario!$D$2:$D$1000,"<>Internacional") -> 2 | F10: =COUNTIFS(Inventario!$M$2:$M$1000,"*"&A10&"*",Inventario!$D$2:$D$1000,"<>Internacional") -> 2 | G10: =COUNTIFS(Inventario!$M$2:$M$1000,"*"&A10&"*",Inventario!$D$2:$D$1000,"<>Internacional",Inventario!$Q$2:$Q$1000,"4*") -> 1 | H10: =COUNTIFS(Inventario!$M$2:$M$1000,"*"&A10&"*",Inventario!$D$2:$D$1000,"<>Internacional",Inventario!$Q$2:$Q$1000,"3*") -> 1 | I10: =COUNTIFS(Inventario!$M$2:$M$1000,"*"&A10&"*",Inventario!$D$2:$D$1000,"<>Internacional",Inventario!$W$2:$W$1000,"Sí") -> 1 | J10: =COUNTIFS(Inventario!$M$2:$M$1000,"*"&A10&"*",Inventario!$D$2:$D$1000,"Internacional") -> 0 | K10: =IF(F10=0,IF(J10>0,"Sin cobertura nacional (solo internacional)","Sin cobertura"),IF(E10=0,"Cobertura indirecta",IF(G10=0,"Cobertura sin análisis","Cobertura con análisis"))) -> Cobertura con análisis | L10: =IF(E10>=5,"Alta concentración: revisar superposición","") | M10: =HYPERLINK("https://catalogodatos.gub.uy/dataset?q="&SUBSTITUTE('Taxonomía temas'!J7," ","+"),"Buscar datasets") -> Buscar datasets
A11: ='Taxonomía temas'!A8 -> T07 | B11: ='Taxonomía temas'!D8 -> Economía y producción | C11: ='Taxonomía temas'!E8 -> Empresas, mipymes y emprendimiento | D11: ='Taxonomía temas'!F8 -> 8 | E11: =COUNTIFS(Inventario!$K$2:$K$1000,A11,Inventario!$D$2:$D$1000,"<>Internacional") -> 1 | F11: =COUNTIFS(Inventario!$M$2:$M$1000,"*"&A11&"*",Inventario!$D$2:$D$1000,"<>Internacional") -> 4 | G11: =COUNTIFS(Inventario!$M$2:$M$1000,"*"&A11&"*",Inventario!$D$2:$D$1000,"<>Internacional",Inventario!$Q$2:$Q$1000,"4*") -> 2 | H11: =COUNTIFS(Inventario!$M$2:$M$1000,"*"&A11&"*",Inventario!$D$2:$D$1000,"<>Internacional",Inventario!$Q$2:$Q$1000,"3*") -> 2 | I11: =COUNTIFS(Inventario!$M$2:$M$1000,"*"&A11&"*",Inventario!$D$2:$D$1000,"<>Internacional",Inventario!$W$2:$W$1000,"Sí") -> 2 | J11: =COUNTIFS(Inventario!$M$2:$M$1000,"*"&A11&"*",Inventario!$D$2:$D$1000,"Internacional") -> 1 | K11: =IF(F11=0,IF(J11>0,"Sin cobertura nacional (solo internacional)","Sin cobertura"),IF(E11=0,"Cobertura indirecta",IF(G11=0,"Cobertura sin análisis","Cobertura con análisis"))) -> Cobertura con análisis | L11: =IF(E11>=5,"Alta concentración: revisar superposición","") | M11: =HYPERLINK("https://catalogodatos.gub.uy/dataset?q="&SUBSTITUTE('Taxonomía temas'!J8," ","+"),"Buscar datasets") -> Buscar datasets
A12: ='Taxonomía temas'!A9 -> T08 | B12: ='Taxonomía temas'!D9 -> Economía y producción | C12: ='Taxonomía temas'!E9 -> Logística, transporte de cargas e infraestructura | D12: ='Taxonomía temas'!F9 -> 9 | E12: =COUNTIFS(Inventario!$K$2:$K$1000,A12,Inventario!$D$2:$D$1000,"<>Internacional") -> 3 | F12: =COUNTIFS(Inventario!$M$2:$M$1000,"*"&A12&"*",Inventario!$D$2:$D$1000,"<>Internacional") -> 3 | G12: =COUNTIFS(Inventario!$M$2:$M$1000,"*"&A12&"*",Inventario!$D$2:$D$1000,"<>Internacional",Inventario!$Q$2:$Q$1000,"4*") -> 0 | H12: =COUNTIFS(Inventario!$M$2:$M$1000,"*"&A12&"*",Inventario!$D$2:$D$1000,"<>Internacional",Inventario!$Q$2:$Q$1000,"3*") -> 1 | I12: =COUNTIFS(Inventario!$M$2:$M$1000,"*"&A12&"*",Inventario!$D$2:$D$1000,"<>Internacional",Inventario!$W$2:$W$1000,"Sí") -> 1 | J12: =COUNTIFS(Inventario!$M$2:$M$1000,"*"&A12&"*",Inventario!$D$2:$D$1000,"Internacional") -> 0 | K12: =IF(F12=0,IF(J12>0,"Sin cobertura nacional (solo internacional)","Sin cobertura"),IF(E12=0,"Cobertura indirecta",IF(G12=0,"Cobertura sin análisis","Cobertura con análisis"))) -> Cobertura sin análisis | L12: =IF(E12>=5,"Alta concentración: revisar superposición","") | M12: =HYPERLINK("https://catalogodatos.gub.uy/dataset?q="&SUBSTITUTE('Taxonomía temas'!J9," ","+"),"Buscar datasets") -> Buscar datasets
A13: ='Taxonomía temas'!A10 -> T09 | B13: ='Taxonomía temas'!D10 -> Economía y producción | C13: ='Taxonomía temas'!E10 -> Precios, consumo y construcción | D13: ='Taxonomía temas'!F10 -> 12 | E13: =COUNTIFS(Inventario!$K$2:$K$1000,A13,Inventario!$D$2:$D$1000,"<>Internacional") -> 3 | F13: =COUNTIFS(Inventario!$M$2:$M$1000,"*"&A13&"*",Inventario!$D$2:$D$1000,"<>Internacional") -> 9 | G13: =COUNTIFS(Inventario!$M$2:$M$1000,"*"&A13&"*",Inventario!$D$2:$D$1000,"<>Internacional",Inventario!$Q$2:$Q$1000,"4*") -> 4 | H13: =COUNTIFS(Inventario!$M$2:$M$1000,"*"&A13&"*",Inventario!$D$2:$D$1000,"<>Internacional",Inventario!$Q$2:$Q$1000,"3*") -> 4 | I13: =COUNTIFS(Inventario!$M$2:$M$1000,"*"&A13&"*",Inventario!$D$2:$D$1000,"<>Internacional",Inventario!$W$2:$W$1000,"Sí") -> 2 | J13: =COUNTIFS(Inventario!$M$2:$M$1000,"*"&A13&"*",Inventario!$D$2:$D$1000,"Internacional") -> 0 | K13: =IF(F13=0,IF(J13>0,"Sin cobertura nacional (solo internacional)","Sin cobertura"),IF(E13=0,"Cobertura indirecta",IF(G13=0,"Cobertura sin análisis","Cobertura con análisis"))) -> Cobertura con análisis | L13: =IF(E13>=5,"Alta concentración: revisar superposición","") | M13: =HYPERLINK("https://catalogodatos.gub.uy/dataset?q="&SUBSTITUTE('Taxonomía temas'!J10," ","+"),"Buscar datasets") -> Buscar datasets
A14: ='Taxonomía temas'!A11 -> T10 | B14: ='Taxonomía temas'!D11 -> Ciencia, tecnología e innovación | C14: ='Taxonomía temas'!E11 -> Telecomunicaciones y sociedad digital | D14: ='Taxonomía temas'!F11 -> 9 | E14: =COUNTIFS(Inventario!$K$2:$K$1000,A14,Inventario!$D$2:$D$1000,"<>Internacional") -> 2 | F14: =COUNTIFS(Inventario!$M$2:$M$1000,"*"&A14&"*",Inventario!$D$2:$D$1000,"<>Internacional") -> 2 | G14: =COUNTIFS(Inventario!$M$2:$M$1000,"*"&A14&"*",Inventario!$D$2:$D$1000,"<>Internacional",Inventario!$Q$2:$Q$1000,"4*") -> 1 | H14: =COUNTIFS(Inventario!$M$2:$M$1000,"*"&A14&"*",Inventario!$D$2:$D$1000,"<>Internacional",Inventario!$Q$2:$Q$1000,"3*") -> 0 | I14: =COUNTIFS(Inventario!$M$2:$M$1000,"*"&A14&"*",Inventario!$D$2:$D$1000,"<>Internacional",Inventario!$W$2:$W$1000,"Sí") -> 2 | J14: =COUNTIFS(Inventario!$M$2:$M$1000,"*"&A14&"*",Inventario!$D$2:$D$1000,"Internacional") -> 3 | K14: =IF(F14=0,IF(J14>0,"Sin cobertura nacional (solo internacional)","Sin cobertura"),IF(E14=0,"Cobertura indirecta",IF(G14=0,"Cobertura sin análisis","Cobertura con análisis"))) -> Cobertura con análisis | L14: =IF(E14>=5,"Alta concentración: revisar superposición","") | M14: =HYPERLINK("https://catalogodatos.gub.uy/dataset?q="&SUBSTITUTE('Taxonomía temas'!J11," ","+"),"Buscar datasets") -> Buscar datasets
A15: ='Taxonomía temas'!A12 -> T11 | B15: ='Taxonomía temas'!D12 -> Ciencia, tecnología e innovación | C15: ='Taxonomía temas'!E12 -> Investigación, ciencia e innovación | D15: ='Taxonomía temas'!F12 -> 9 | E15: =COUNTIFS(Inventario!$K$2:$K$1000,A15,Inventario!$D$2:$D$1000,"<>Internacional") -> 2 | F15: =COUNTIFS(Inventario!$M$2:$M$1000,"*"&A15&"*",Inventario!$D$2:$D$1000,"<>Internacional") -> 4 | G15: =COUNTIFS(Inventario!$M$2:$M$1000,"*"&A15&"*",Inventario!$D$2:$D$1000,"<>Internacional",Inventario!$Q$2:$Q$1000,"4*") -> 1 | H15: =COUNTIFS(Inventario!$M$2:$M$1000,"*"&A15&"*",Inventario!$D$2:$D$1000,"<>Internacional",Inventario!$Q$2:$Q$1000,"3*") -> 0 | I15: =COUNTIFS(Inventario!$M$2:$M$1000,"*"&A15&"*",Inventario!$D$2:$D$1000,"<>Internacional",Inventario!$W$2:$W$1000,"Sí") -> 1 | J15: =COUNTIFS(Inventario!$M$2:$M$1000,"*"&A15&"*",Inventario!$D$2:$D$1000,"Internacional") -> 10 | K15: =IF(F15=0,IF(J15>0,"Sin cobertura nacional (solo internacional)","Sin cobertura"),IF(E15=0,"Cobertura indirecta",IF(G15=0,"Cobertura sin análisis","Cobertura con análisis"))) -> Cobertura con análisis | L15: =IF(E15>=5,"Alta concentración: revisar superposición","") | M15: =HYPERLINK("https://catalogodatos.gub.uy/dataset?q="&SUBSTITUTE('Taxonomía temas'!J12," ","+"),"Buscar datasets") -> Buscar datasets
A16: ='Taxonomía temas'!A13 -> T12 | B16: ='Taxonomía temas'!D13 -> Ciencia, tecnología e innovación | C16: ='Taxonomía temas'!E13 -> Propiedad intelectual | D16: ='Taxonomía temas'!F13 -> 9 | E16: =COUNTIFS(Inventario!$K$2:$K$1000,A16,Inventario!$D$2:$D$1000,"<>Internacional") -> 1 | F16: =COUNTIFS(Inventario!$M$2:$M$1000,"*"&A16&"*",Inventario!$D$2:$D$1000,"<>Internacional") -> 1 | G16: =COUNTIFS(Inventario!$M$2:$M$1000,"*"&A16&"*",Inventario!$D$2:$D$1000,"<>Internacional",Inventario!$Q$2:$Q$1000,"4*") -> 0 | H16: =COUNTIFS(Inventario!$M$2:$M$1000,"*"&A16&"*",Inventario!$D$2:$D$1000,"<>Internacional",Inventario!$Q$2:$Q$1000,"3*") -> 0 | I16: =COUNTIFS(Inventario!$M$2:$M$1000,"*"&A16&"*",Inventario!$D$2:$D$1000,"<>Internacional",Inventario!$W$2:$W$1000,"Sí") -> 0 | J16: =COUNTIFS(Inventario!$M$2:$M$1000,"*"&A16&"*",Inventario!$D$2:$D$1000,"Internacional") -> 4 | K16: =IF(F16=0,IF(J16>0,"Sin cobertura nacional (solo internacional)","Sin cobertura"),IF(E16=0,"Cobertura indirecta",IF(G16=0,"Cobertura sin análisis","Cobertura con análisis"))) -> Cobertura sin análisis | L16: =IF(E16>=5,"Alta concentración: revisar superposición","") | M16: =HYPERLINK("https://catalogodatos.gub.uy/dataset?q="&SUBSTITUTE('Taxonomía temas'!J13," ","+"),"Buscar datasets") -> Buscar datasets
... A57: ='Taxonomía temas'!A54 -> T53 | B57: ='Taxonomía temas'!D54 -> Estado, gobierno y derechos | C57: ='Taxonomía temas'!E54 -> Integridad y prevención de la corrupción | D57: ='Taxonomía temas'!F54 -> 16 | E57: =COUNTIFS(Inventario!$K$2:$K$1000,A57,Inventario!$D$2:$D$1000,"<>Internacional") -> 0 | F57: =COUNTIFS(Inventario!$M$2:$M$1000,"*"&A57&"*",Inventario!$D$2:$D$1000,"<>Internacional") -> 0 | G57: =COUNTIFS(Inventario!$M$2:$M$1000,"*"&A57&"*",Inventario!$D$2:$D$1000,"<>Internacional",Inventario!$Q$2:$Q$1000,"4*") -> 0 | H57: =COUNTIFS(Inventario!$M$2:$M$1000,"*"&A57&"*",Inventario!$D$2:$D$1000,"<>Internacional",Inventario!$Q$2:$Q$1000,"3*") -> 0 | I57: =COUNTIFS(Inventario!$M$2:$M$1000,"*"&A57&"*",Inventario!$D$2:$D$1000,"<>Internacional",Inventario!$W$2:$W$1000,"Sí") -> 0 | J57: =COUNTIFS(Inventario!$M$2:$M$1000,"*"&A57&"*",Inventario!$D$2:$D$1000,"Internacional") -> 0 | K57: =IF(F57=0,IF(J57>0,"Sin cobertura nacional (solo internacional)","Sin cobertura"),IF(E57=0,"Cobertura indirecta",IF(G57=0,"Cobertura sin análisis","Cobertura con análisis"))) -> Sin cobertura | L57: =IF(E57>=5,"Alta concentración: revisar superposición","") | M57: =HYPERLINK("https://catalogodatos.gub.uy/dataset?q="&SUBSTITUTE('Taxonomía temas'!J54," ","+"),"Buscar datasets") -> Buscar datasets
C59: Estado | E59: Temas
C60: Cobertura con análisis | E60: =COUNTIF($K$5:$K$57,C60) -> 37
C61: Cobertura sin análisis | E61: =COUNTIF($K$5:$K$57,C61) -> 12
C62: Cobertura indirecta | E62: =COUNTIF($K$5:$K$57,C62) -> 0
C63: Sin cobertura nacional (solo internacional) | E63: =COUNTIF($K$5:$K$57,C63) -> 0
C64: Sin cobertura | E64: =COUNTIF($K$5:$K$57,C64) -> 4
C65: Temas con alta concentración | E65: =COUNTIF($L$5:$L$57,"Alta*") -> 11
C67: Estados: con análisis = al menos un recurso nacional de nivel 4; sin análisis = recursos con el tema como principal pero ninguno de nivel 4; indirecta = el tema solo aparece como secundario; sin cobertura = ningún recurso nacional. Concentración = 5 o más recursos con el tema como principal.

Sheet Cobertura ODS
A1: Cobertura por Objetivo de Desarrollo Sostenible
A2: Agregación de la cobertura temática según el ODS principal de cada tema.
A4: ODS | B4: Objetivo | C4: Temas de la taxonomía | D4: Recursos nacionales (ODS principal) | E4: Temas con análisis | F4: Temas sin análisis o indirectos | G4: Temas sin cobertura nacional | H4: Referencias internacionales | I4: Lectura
A5: 1 | B5: Fin de la pobreza | C5: =COUNTIF('Taxonomía temas'!$F$2:$F$54,A5) -> 3 | D5: =COUNTIFS(Inventario!$O$2:$O$1000,A5,Inventario!$D$2:$D$1000,"<>Internacional") -> 9 | E5: =COUNTIFS('Cobertura temática'!$D$5:$D$57,A5,'Cobertura temática'!$K$5:$K$57,"Cobertura con análisis") -> 3 | F5: =COUNTIFS('Cobertura temática'!$D$5:$D$57,A5,'Cobertura temática'!$K$5:$K$57,"Cobertura sin análisis")+COUNTIFS('Cobertura temática'!$D$5:$D$57,A5,'Cobertura temática'!$K$5:$K$57,"Cobertura indirecta") -> 0 | G5: =COUNTIFS('Cobertura temática'!$D$5:$D$57,A5,'Cobertura temática'!$K$5:$K$57,"Sin cobertura*") -> 0 | H5: =COUNTIFS(Inventario!$O$2:$O$1000,A5,Inventario!$D$2:$D$1000,"Internacional") -> 1 | I5: =IF(G5>0,"Hay temas sin cobertura nacional",IF(F5>0,"Cobertura sin análisis en algún tema",IF(D5=0,"Sin recursos nacionales","Cubierto"))) -> Cubierto
A6: 2 | B6: Hambre cero | C6: =COUNTIF('Taxonomía temas'!$F$2:$F$54,A6) -> 2 | D6: =COUNTIFS(Inventario!$O$2:$O$1000,A6,Inventario!$D$2:$D$1000,"<>Internacional") -> 14 | E6: =COUNTIFS('Cobertura temática'!$D$5:$D$57,A6,'Cobertura temática'!$K$5:$K$57,"Cobertura con análisis") -> 2 | F6: =COUNTIFS('Cobertura temática'!$D$5:$D$57,A6,'Cobertura temática'!$K$5:$K$57,"Cobertura sin análisis")+COUNTIFS('Cobertura temática'!$D$5:$D$57,A6,'Cobertura temática'!$K$5:$K$57,"Cobertura indirecta") -> 0 | G6: =COUNTIFS('Cobertura temática'!$D$5:$D$57,A6,'Cobertura temática'!$K$5:$K$57,"Sin cobertura*") -> 0 | H6: =COUNTIFS(Inventario!$O$2:$O$1000,A6,Inventario!$D$2:$D$1000,"Internacional") -> 1 | I6: =IF(G6>0,"Hay temas sin cobertura nacional",IF(F6>0,"Cobertura sin análisis en algún tema",IF(D6=0,"Sin recursos nacionales","Cubierto"))) -> Cubierto
A7: 3 | B7: Salud y bienestar | C7: =COUNTIF('Taxonomía temas'!$F$2:$F$54,A7) -> 5 | D7: =COUNTIFS(Inventario!$O$2:$O$1000,A7,Inventario!$D$2:$D$1000,"<>Internacional") -> 9 | E7: =COUNTIFS('Cobertura temática'!$D$5:$D$57,A7,'Cobertura temática'!$K$5:$K$57,"Cobertura con análisis") -> 3 | F7: =COUNTIFS('Cobertura temática'!$D$5:$D$57,A7,'Cobertura temática'!$K$5:$K$57,"Cobertura sin análisis")+COUNTIFS('Cobertura temática'!$D$5:$D$57,A7,'Cobertura temática'!$K$5:$K$57,"Cobertura indirecta") -> 1 | G7: =COUNTIFS('Cobertura temática'!$D$5:$D$57,A7,'Cobertura temática'!$K$5:$K$57,"Sin cobertura*") -> 1 | H7: =COUNTIFS(Inventario!$O$2:$O$1000,A7,Inventario!$D$2:$D$1000,"Internacional") -> 1 | I7: =IF(G7>0,"Hay temas sin cobertura nacional",IF(F7>0,"Cobertura sin análisis en algún tema",IF(D7=0,"Sin recursos nacionales","Cubierto"))) -> Hay temas sin cobertura nacional
A8: 4 | B8: Educación de calidad | C8: =COUNTIF('Taxonomía temas'!$F$2:$F$54,A8) -> 4 | D8: =COUNTIFS(Inventario!$O$2:$O$1000,A8,Inventario!$D$2:$D$1000,"<>Internacional") -> 13 | E8: =COUNTIFS('Cobertura temática'!$D$5:$D$57,A8,'Cobertura temática'!$K$5:$K$57,"Cobertura con análisis") -> 3 | F8: =COUNTIFS('Cobertura temática'!$D$5:$D$57,A8,'Cobertura temática'!$K$5:$K$57,"Cobertura sin análisis")+COUNTIFS('Cobertura temática'!$D$5:$D$57,A8,'Cobertura temática'!$K$5:$K$57,"Cobertura indirecta") -> 1 | G8: =COUNTIFS('Cobertura temática'!$D$5:$D$57,A8,'Cobertura temática'!$K$5:$K$57,"Sin cobertura*") -> 0 | H8: =COUNTIFS(Inventario!$O$2:$O$1000,A8,Inventario!$D$2:$D$1000,"Internacional") -> 0 | I8: =IF(G8>0,"Hay temas sin cobertura nacional",IF(F8>0,"Cobertura sin análisis en algún tema",IF(D8=0,"Sin recursos nacionales","Cubierto"))) -> Cobertura sin análisis en algún tema
A9: 5 | B9: Igualdad de género | C9: =COUNTIF('Taxonomía temas'!$F$2:$F$54,A9) -> 1 | D9: =COUNTIFS(Inventario!$O$2:$O$1000,A9,Inventario!$D$2:$D$1000,"<>Internacional") -> 1 | E9: =COUNTIFS('Cobertura temática'!$D$5:$D$57,A9,'Cobertura temática'!$K$5:$K$57,"Cobertura con análisis") -> 0 | F9: =COUNTIFS('Cobertura temática'!$D$5:$D$57,A9,'Cobertura temática'!$K$5:$K$57,"Cobertura sin análisis")+COUNTIFS('Cobertura temática'!$D$5:$D$57,A9,'Cobertura temática'!$K$5:$K$57,"Cobertura indirecta") -> 1 | G9: =COUNTIFS('Cobertura temática'!$D$5:$D$57,A9,'Cobertura temática'!$K$5:$K$57,"Sin cobertura*") -> 0 | H9: =COUNTIFS(Inventario!$O$2:$O$1000,A9,Inventario!$D$2:$D$1000,"Internacional") -> 0 | I9: =IF(G9>0,"Hay temas sin cobertura nacional",IF(F9>0,"Cobertura sin análisis en algún tema",IF(D9=0,"Sin recursos nacionales","Cubierto"))) -> Cobertura sin análisis en algún tema
A10: 6 | B10: Agua limpia y saneamiento | C10: =COUNTIF('Taxonomía temas'!$F$2:$F$54,A10) -> 1 | D10: =COUNTIFS(Inventario!$O$2:$O$1000,A10,Inventario!$D$2:$D$1000,"<>Internacional") -> 3 | E10: =COUNTIFS('Cobertura temática'!$D$5:$D$57,A10,'Cobertura temática'!$K$5:$K$57,"Cobertura con análisis") -> 1 | F10: =COUNTIFS('Cobertura temática'!$D$5:$D$57,A10,'Cobertura temática'!$K$5:$K$57,"Cobertura sin análisis")+COUNTIFS('Cobertura temática'!$D$5:$D$57,A10,'Cobertura temática'!$K$5:$K$57,"Cobertura indirecta") -> 0 | G10: =COUNTIFS('Cobertura temática'!$D$5:$D$57,A10,'Cobertura temática'!$K$5:$K$57,"Sin cobertura*") -> 0 | H10: =COUNTIFS(Inventario!$O$2:$O$1000,A10,Inventario!$D$2:$D$1000,"Internacional") -> 0 | I10: =IF(G10>0,"Hay temas sin cobertura nacional",IF(F10>0,"Cobertura sin análisis en algún tema",IF(D10=0,"Sin recursos nacionales","Cubierto"))) -> Cubierto
A11: 7 | B11: Energía asequible y no contaminante | C11: =COUNTIF('Taxonomía temas'!$F$2:$F$54,A11) -> 1 | D11: =COUNTIFS(Inventario!$O$2:$O$1000,A11,Inventario!$D$2:$D$1000,"<>Internacional") -> 6 | E11: =COUNTIFS('Cobertura temática'!$D$5:$D$57,A11,'Cobertura temática'!$K$5:$K$57,"Cobertura con análisis") -> 1 | F11: =COUNTIFS('Cobertura temática'!$D$5:$D$57,A11,'Cobertura temática'!$K$5:$K$57,"Cobertura sin análisis")+COUNTIFS('Cobertura temática'!$D$5:$D$57,A11,'Cobertura temática'!$K$5:$K$57,"Cobertura indirecta") -> 0 | G11: =COUNTIFS('Cobertura temática'!$D$5:$D$57,A11,'Cobertura temática'!$K$5:$K$57,"Sin cobertura*") -> 0 | H11: =COUNTIFS(Inventario!$O$2:$O$1000,A11,Inventario!$D$2:$D$1000,"Internacional") -> 0 | I11: =IF(G11>0,"Hay temas sin cobertura nacional",IF(F11>0,"Cobertura sin análisis en algún tema",IF(D11=0,"Sin recursos nacionales","Cubierto"))) -> Cubierto
A12: 8 | B12: Trabajo decente y crecimiento económico | C12: =COUNTIF('Taxonomía temas'!$F$2:$F$54,A12) -> 6 | D12: =COUNTIFS(Inventario!$O$2:$O$1000,A12,Inventario!$D$2:$D$1000,"<>Internacional") -> 10 | E12: =COUNTIFS('Cobertura temática'!$D$5:$D$57,A12,'Cobertura temática'!$K$5:$K$57,"Cobertura con análisis") -> 4 | F12: =COUNTIFS('Cobertura temática'!$D$5:$D$57,A12,'Cobertura temática'!$K$5:$K$57,"Cobertura sin análisis")+COUNTIFS('Cobertura temática'!$D$5:$D$57,A12,'Cobertura temática'!$K$5:$K$57,"Cobertura indirecta") -> 1 | G12: =COUNTIFS('Cobertura temática'!$D$5:$D$57,A12,'Cobertura temática'!$K$5:$K$57,"Sin cobertura*") -> 1 | H12: =COUNTIFS(Inventario!$O$2:$O$1000,A12,Inventario!$D$2:$D$1000,"Internacional") -> 2 | I12: =IF(G12>0,"Hay temas sin cobertura nacional",IF(F12>0,"Cobertura sin análisis en algún tema",IF(D12=0,"Sin recursos nacionales","Cubierto"))) -> Hay temas sin cobertura nacional
A13: 9 | B13: Industria, innovación e infraestructura | C13: =COUNTIF('Taxonomía temas'!$F$2:$F$54,A13) -> 6 | D13: =COUNTIFS(Inventario!$O$2:$O$1000,A13,Inventario!$D$2:$D$1000,"<>Internacional") -> 11 | E13: =COUNTIFS('Cobertura temática'!$D$5:$D$57,A13,'Cobertura temática'!$K$5:$K$57,"Cobertura con análisis") -> 4 | F13: =COUNTIFS('Cobertura temática'!$D$5:$D$57,A13,'Cobertura temática'!$K$5:$K$57,"Cobertura sin análisis")+COUNTIFS('Cobertura temática'!$D$5:$D$57,A13,'Cobertura temática'!$K$5:$K$57,"Cobertura indirecta") -> 2 | G13: =COUNTIFS('Cobertura temática'!$D$5:$D$57,A13,'Cobertura temática'!$K$5:$K$57,"Sin cobertura*") -> 0 | H13: =COUNTIFS(Inventario!$O$2:$O$1000,A13,Inventario!$D$2:$D$1000,"Internacional") -> 9 | I13: =IF(G13>0,"Hay temas sin cobertura nacional",IF(F13>0,"Cobertura sin análisis en algún tema",IF(D13=0,"Sin recursos nacionales","Cubierto"))) -> Cobertura sin análisis en algún tema
A14: 10 | B14: Reducción de las desigualdades | C14: =COUNTIF('Taxonomía temas'!$F$2:$F$54,A14) -> 1 | D14: =COUNTIFS(Inventario!$O$2:$O$1000,A14,Inventario!$D$2:$D$1000,"<>Internacional") -> 2 | E14: =COUNTIFS('Cobertura temática'!$D$5:$D$57,A14,'Cobertura temática'!$K$5:$K$57,"Cobertura con análisis") -> 1 | F14: =COUNTIFS('Cobertura temática'!$D$5:$D$57,A14,'Cobertura temática'!$K$5:$K$57,"Cobertura sin análisis")+COUNTIFS('Cobertura temática'!$D$5:$D$57,A14,'Cobertura temática'!$K$5:$K$57,"Cobertura indirecta") -> 0 | G14: =COUNTIFS('Cobertura temática'!$D$5:$D$57,A14,'Cobertura temática'!$K$5:$K$57,"Sin cobertura*") -> 0 | H14: =COUNTIFS(Inventario!$O$2:$O$1000,A14,Inventario!$D$2:$D$1000,"Internacional") -> 0 | I14: =IF(G14>0,"Hay temas sin cobertura nacional",IF(F14>0,"Cobertura sin análisis en algún tema",IF(D14=0,"Sin recursos nacionales","Cubierto"))) -> Cubierto
A15: 11 | B15: Ciudades y comunidades sostenibles | C15: =COUNTIF('Taxonomía temas'!$F$2:$F$54,A15) -> 5 | D15: =COUNTIFS(Inventario!$O$2:$O$1000,A15,Inventario!$D$2:$D$1000,"<>Internacional") -> 12 | E15: =COUNTIFS('Cobertura temática'!$D$5:$D$57,A15,'Cobertura temática'!$K$5:$K$57,"Cobertura con análisis") -> 3 | F15: =COUNTIFS('Cobertura temática'!$D$5:$D$57,A15,'Cobertura temática'!$K$5:$K$57,"Cobertura sin análisis")+COUNTIFS('Cobertura temática'!$D$5:$D$57,A15,'Cobertura temática'!$K$5:$K$57,"Cobertura indirecta") -> 2 | G15: =COUNTIFS('Cobertura temática'!$D$5:$D$57,A15,'Cobertura temática'!$K$5:$K$57,"Sin cobertura*") -> 0 | H15: =COUNTIFS(Inventario!$O$2:$O$1000,A15,Inventario!$D$2:$D$1000,"Internacional") -> 0 | I15: =IF(G15>0,"Hay temas sin cobertura nacional",IF(F15>0,"Cobertura sin análisis en algún tema",IF(D15=0,"Sin recursos nacionales","Cubierto"))) -> Cobertura sin análisis en algún tema
A16: 12 | B16: Producción y consumo responsables | C16: =COUNTIF('Taxonomía temas'!$F$2:$F$54,A16) -> 2 | D16: =COUNTIFS(Inventario!$O$2:$O$1000,A16,Inventario!$D$2:$D$1000,"<>Internacional") -> 5 | E16: =COUNTIFS('Cobertura temática'!$D$5:$D$57,A16,'Cobertura temática'!$K$5:$K$57,"Cobertura con análisis") -> 2 | F16: =COUNTIFS('Cobertura temática'!$D$5:$D$57,A16,'Cobertura temática'!$K$5:$K$57,"Cobertura sin análisis")+COUNTIFS('Cobertura temática'!$D$5:$D$57,A16,'Cobertura temática'!$K$5:$K$57,"Cobertura indirecta") -> 0 | G16: =COUNTIFS('Cobertura temática'!$D$5:$D$57,A16,'Cobertura temática'!$K$5:$K$57,"Sin cobertura*") -> 0 | H16: =COUNTIFS(Inventario!$O$2:$O$1000,A16,Inventario!$D$2:$D$1000,"Internacional") -> 0 | I16: =IF(G16>0,"Hay temas sin cobertura nacional",IF(F16>0,"Cobertura sin análisis en algún tema",IF(D16=0,"Sin recursos nacionales","Cubierto"))) -> Cubierto
... A21: 17 | B21: Alianzas para lograr los objetivos | C21: =COUNTIF('Taxonomía temas'!$F$2:$F$54,A21) -> 5 | D21: =COUNTIFS(Inventario!$O$2:$O$1000,A21,Inventario!$D$2:$D$1000,"<>Internacional") -> 22 | E21: =COUNTIFS('Cobertura temática'!$D$5:$D$57,A21,'Cobertura temática'!$K$5:$K$57,"Cobertura con análisis") -> 3 | F21: =COUNTIFS('Cobertura temática'!$D$5:$D$57,A21,'Cobertura temática'!$K$5:$K$57,"Cobertura sin análisis")+COUNTIFS('Cobertura temática'!$D$5:$D$57,A21,'Cobertura temática'!$K$5:$K$57,"Cobertura indirecta") -> 2 | G21: =COUNTIFS('Cobertura temática'!$D$5:$D$57,A21,'Cobertura temática'!$K$5:$K$57,"Sin cobertura*") -> 0 | H21: =COUNTIFS(Inventario!$O$2:$O$1000,A21,Inventario!$D$2:$D$1000,"Internacional") -> 6 | I21: =IF(G21>0,"Hay temas sin cobertura nacional",IF(F21>0,"Cobertura sin análisis en algún tema",IF(D21=0,"Sin recursos nacionales","Cubierto"))) -> Cobertura sin análisis en algún tema
B23: Total | C23: =SUM(C5:C21) -> 53 | D23: =SUM(D5:D21) -> 148 | E23: =SUM(E5:E21) -> 37 | F23: =SUM(F5:F21) -> 12 | G23: =SUM(G5:G21) -> 4 | H23: =SUM(H5:H21) -> 22

Sheet Cobertura enfoques
A1: Cobertura de enfoques transversales
A2: Solo cuentan recursos que incorporan el enfoque de forma explícita (ver regla en la hoja Enfoques).
A4: Código | B4: Enfoque | C4: Recursos nacionales | D4: Con análisis (nivel 4) | E4: Referencias internacionales | F4: Estado
A5: =Enfoques!A2 -> E01 | B5: =Enfoques!C2 -> Género | C5: =COUNTIFS(Inventario!$P$2:$P$1000,"*"&A5&"*",Inventario!$D$2:$D$1000,"<>Internacional") -> 8 | D5: =COUNTIFS(Inventario!$P$2:$P$1000,"*"&A5&"*",Inventario!$D$2:$D$1000,"<>Internacional",Inventario!$Q$2:$Q$1000,"4*") -> 4 | E5: =COUNTIFS(Inventario!$P$2:$P$1000,"*"&A5&"*",Inventario!$D$2:$D$1000,"Internacional") -> 1 | F5: =IF(C5=0,"Sin cobertura",IF(D5=0,"Cobertura sin análisis","Cobertura con análisis")) -> Cobertura con análisis
A6: =Enfoques!A3 -> E02 | B6: =Enfoques!C3 -> Infancia y adolescencia | C6: =COUNTIFS(Inventario!$P$2:$P$1000,"*"&A6&"*",Inventario!$D$2:$D$1000,"<>Internacional") -> 5 | D6: =COUNTIFS(Inventario!$P$2:$P$1000,"*"&A6&"*",Inventario!$D$2:$D$1000,"<>Internacional",Inventario!$Q$2:$Q$1000,"4*") -> 3 | E6: =COUNTIFS(Inventario!$P$2:$P$1000,"*"&A6&"*",Inventario!$D$2:$D$1000,"Internacional") -> 0 | F6: =IF(C6=0,"Sin cobertura",IF(D6=0,"Cobertura sin análisis","Cobertura con análisis")) -> Cobertura con análisis
A7: =Enfoques!A4 -> E03 | B7: =Enfoques!C4 -> Juventud | C7: =COUNTIFS(Inventario!$P$2:$P$1000,"*"&A7&"*",Inventario!$D$2:$D$1000,"<>Internacional") -> 0 | D7: =COUNTIFS(Inventario!$P$2:$P$1000,"*"&A7&"*",Inventario!$D$2:$D$1000,"<>Internacional",Inventario!$Q$2:$Q$1000,"4*") -> 0 | E7: =COUNTIFS(Inventario!$P$2:$P$1000,"*"&A7&"*",Inventario!$D$2:$D$1000,"Internacional") -> 0 | F7: =IF(C7=0,"Sin cobertura",IF(D7=0,"Cobertura sin análisis","Cobertura con análisis")) -> Sin cobertura
A8: =Enfoques!A5 -> E04 | B8: =Enfoques!C5 -> Personas mayores y envejecimiento | C8: =COUNTIFS(Inventario!$P$2:$P$1000,"*"&A8&"*",Inventario!$D$2:$D$1000,"<>Internacional") -> 3 | D8: =COUNTIFS(Inventario!$P$2:$P$1000,"*"&A8&"*",Inventario!$D$2:$D$1000,"<>Internacional",Inventario!$Q$2:$Q$1000,"4*") -> 2 | E8: =COUNTIFS(Inventario!$P$2:$P$1000,"*"&A8&"*",Inventario!$D$2:$D$1000,"Internacional") -> 0 | F8: =IF(C8=0,"Sin cobertura",IF(D8=0,"Cobertura sin análisis","Cobertura con análisis")) -> Cobertura con análisis
A9: =Enfoques!A6 -> E05 | B9: =Enfoques!C6 -> Discapacidad | C9: =COUNTIFS(Inventario!$P$2:$P$1000,"*"&A9&"*",Inventario!$D$2:$D$1000,"<>Internacional") -> 2 | D9: =COUNTIFS(Inventario!$P$2:$P$1000,"*"&A9&"*",Inventario!$D$2:$D$1000,"<>Internacional",Inventario!$Q$2:$Q$1000,"4*") -> 1 | E9: =COUNTIFS(Inventario!$P$2:$P$1000,"*"&A9&"*",Inventario!$D$2:$D$1000,"Internacional") -> 0 | F9: =IF(C9=0,"Sin cobertura",IF(D9=0,"Cobertura sin análisis","Cobertura con análisis")) -> Cobertura con análisis
A10: =Enfoques!A7 -> E06 | B10: =Enfoques!C7 -> Migración | C10: =COUNTIFS(Inventario!$P$2:$P$1000,"*"&A10&"*",Inventario!$D$2:$D$1000,"<>Internacional") -> 2 | D10: =COUNTIFS(Inventario!$P$2:$P$1000,"*"&A10&"*",Inventario!$D$2:$D$1000,"<>Internacional",Inventario!$Q$2:$Q$1000,"4*") -> 2 | E10: =COUNTIFS(Inventario!$P$2:$P$1000,"*"&A10&"*",Inventario!$D$2:$D$1000,"Internacional") -> 0 | F10: =IF(C10=0,"Sin cobertura",IF(D10=0,"Cobertura sin análisis","Cobertura con análisis")) -> Cobertura con análisis
A11: =Enfoques!A8 -> E07 | B11: =Enfoques!C8 -> Afrodescendencia y etnia-raza | C11: =COUNTIFS(Inventario!$P$2:$P$1000,"*"&A11&"*",Inventario!$D$2:$D$1000,"<>Internacional") -> 0 | D11: =COUNTIFS(Inventario!$P$2:$P$1000,"*"&A11&"*",Inventario!$D$2:$D$1000,"<>Internacional",Inventario!$Q$2:$Q$1000,"4*") -> 0 | E11: =COUNTIFS(Inventario!$P$2:$P$1000,"*"&A11&"*",Inventario!$D$2:$D$1000,"Internacional") -> 0 | F11: =IF(C11=0,"Sin cobertura",IF(D11=0,"Cobertura sin análisis","Cobertura con análisis")) -> Sin cobertura
A12: =Enfoques!A9 -> E08 | B12: =Enfoques!C9 -> Enfoque de derechos | C12: =COUNTIFS(Inventario!$P$2:$P$1000,"*"&A12&"*",Inventario!$D$2:$D$1000,"<>Internacional") -> 9 | D12: =COUNTIFS(Inventario!$P$2:$P$1000,"*"&A12&"*",Inventario!$D$2:$D$1000,"<>Internacional",Inventario!$Q$2:$Q$1000,"4*") -> 8 | E12: =COUNTIFS(Inventario!$P$2:$P$1000,"*"&A12&"*",Inventario!$D$2:$D$1000,"Internacional") -> 0 | F12: =IF(C12=0,"Sin cobertura",IF(D12=0,"Cobertura sin análisis","Cobertura con análisis")) -> Cobertura con análisis
A13: =Enfoques!A10 -> E09 | B13: =Enfoques!C10 -> Territorial y subnacional | C13: =COUNTIFS(Inventario!$P$2:$P$1000,"*"&A13&"*",Inventario!$D$2:$D$1000,"<>Internacional") -> 24 | D13: =COUNTIFS(Inventario!$P$2:$P$1000,"*"&A13&"*",Inventario!$D$2:$D$1000,"<>Internacional",Inventario!$Q$2:$Q$1000,"4*") -> 3 | E13: =COUNTIFS(Inventario!$P$2:$P$1000,"*"&A13&"*",Inventario!$D$2:$D$1000,"Internacional") -> 0 | F13: =IF(C13=0,"Sin cobertura",IF(D13=0,"Cobertura sin análisis","Cobertura con análisis")) -> Cobertura con análisis

Sheet Resumen
A1: Resumen del inventario
A2: Tablas cruzadas con fórmulas sobre el inventario.
A4: Área (tema principal) por nivel de análisis
A5: Área | B5: 1 · Datos | C5: 2 · Indicadores y series | D5: 3 · Visualización interactiva | E5: 4 · Análisis e informes | F5: Total | G5: Internacional
A6: Economía y producción | B6: =COUNTIFS(Inventario!$N$2:$N$1000,$A6,Inventario!$Q$2:$Q$1000,"1*",Inventario!$D$2:$D$1000,"<>Internacional") -> 2 | C6: =COUNTIFS(Inventario!$N$2:$N$1000,$A6,Inventario!$Q$2:$Q$1000,"2*",Inventario!$D$2:$D$1000,"<>Internacional") -> 10 | D6: =COUNTIFS(Inventario!$N$2:$N$1000,$A6,Inventario!$Q$2:$Q$1000,"3*",Inventario!$D$2:$D$1000,"<>Internacional") -> 10 | E6: =COUNTIFS(Inventario!$N$2:$N$1000,$A6,Inventario!$Q$2:$Q$1000,"4*",Inventario!$D$2:$D$1000,"<>Internacional") -> 10 | F6: =SUM(B6:E6) -> 32 | G6: =COUNTIFS(Inventario!$N$2:$N$1000,$A6,Inventario!$D$2:$D$1000,"Internacional") -> 4
A7: Trabajo y protección social | B7: =COUNTIFS(Inventario!$N$2:$N$1000,$A7,Inventario!$Q$2:$Q$1000,"1*",Inventario!$D$2:$D$1000,"<>Internacional") -> 1 | C7: =COUNTIFS(Inventario!$N$2:$N$1000,$A7,Inventario!$Q$2:$Q$1000,"2*",Inventario!$D$2:$D$1000,"<>Internacional") -> 4 | D7: =COUNTIFS(Inventario!$N$2:$N$1000,$A7,Inventario!$Q$2:$Q$1000,"3*",Inventario!$D$2:$D$1000,"<>Internacional") -> 3 | E7: =COUNTIFS(Inventario!$N$2:$N$1000,$A7,Inventario!$Q$2:$Q$1000,"4*",Inventario!$D$2:$D$1000,"<>Internacional") -> 10 | F7: =SUM(B7:E7) -> 18 | G7: =COUNTIFS(Inventario!$N$2:$N$1000,$A7,Inventario!$D$2:$D$1000,"Internacional") -> 2
A8: Salud y población | B8: =COUNTIFS(Inventario!$N$2:$N$1000,$A8,Inventario!$Q$2:$Q$1000,"1*",Inventario!$D$2:$D$1000,"<>Internacional") -> 1 | C8: =COUNTIFS(Inventario!$N$2:$N$1000,$A8,Inventario!$Q$2:$Q$1000,"2*",Inventario!$D$2:$D$1000,"<>Internacional") -> 5 | D8: =COUNTIFS(Inventario!$N$2:$N$1000,$A8,Inventario!$Q$2:$Q$1000,"3*",Inventario!$D$2:$D$1000,"<>Internacional") -> 2 | E8: =COUNTIFS(Inventario!$N$2:$N$1000,$A8,Inventario!$Q$2:$Q$1000,"4*",Inventario!$D$2:$D$1000,"<>Internacional") -> 6 | F8: =SUM(B8:E8) -> 14 | G8: =COUNTIFS(Inventario!$N$2:$N$1000,$A8,Inventario!$D$2:$D$1000,"Internacional") -> 1
A9: Educación, cultura y deporte | B9: =COUNTIFS(Inventario!$N$2:$N$1000,$A9,Inventario!$Q$2:$Q$1000,"1*",Inventario!$D$2:$D$1000,"<>Internacional") -> 0 | C9: =COUNTIFS(Inventario!$N$2:$N$1000,$A9,Inventario!$Q$2:$Q$1000,"2*",Inventario!$D$2:$D$1000,"<>Internacional") -> 3 | D9: =COUNTIFS(Inventario!$N$2:$N$1000,$A9,Inventario!$Q$2:$Q$1000,"3*",Inventario!$D$2:$D$1000,"<>Internacional") -> 7 | E9: =COUNTIFS(Inventario!$N$2:$N$1000,$A9,Inventario!$Q$2:$Q$1000,"4*",Inventario!$D$2:$D$1000,"<>Internacional") -> 4 | F9: =SUM(B9:E9) -> 14 | G9: =COUNTIFS(Inventario!$N$2:$N$1000,$A9,Inventario!$D$2:$D$1000,"Internacional") -> 0
A10: Ciencia, tecnología e innovación | B10: =COUNTIFS(Inventario!$N$2:$N$1000,$A10,Inventario!$Q$2:$Q$1000,"1*",Inventario!$D$2:$D$1000,"<>Internacional") -> 2 | C10: =COUNTIFS(Inventario!$N$2:$N$1000,$A10,Inventario!$Q$2:$Q$1000,"2*",Inventario!$D$2:$D$1000,"<>Internacional") -> 2 | D10: =COUNTIFS(Inventario!$N$2:$N$1000,$A10,Inventario!$Q$2:$Q$1000,"3*",Inventario!$D$2:$D$1000,"<>Internacional") -> 0 | E10: =COUNTIFS(Inventario!$N$2:$N$1000,$A10,Inventario!$Q$2:$Q$1000,"4*",Inventario!$D$2:$D$1000,"<>Internacional") -> 2 | F10: =SUM(B10:E10) -> 6 | G10: =COUNTIFS(Inventario!$N$2:$N$1000,$A10,Inventario!$D$2:$D$1000,"Internacional") -> 9
A11: Ambiente, energía y clima | B11: =COUNTIFS(Inventario!$N$2:$N$1000,$A11,Inventario!$Q$2:$Q$1000,"1*",Inventario!$D$2:$D$1000,"<>Internacional") -> 4 | C11: =COUNTIFS(Inventario!$N$2:$N$1000,$A11,Inventario!$Q$2:$Q$1000,"2*",Inventario!$D$2:$D$1000,"<>Internacional") -> 1 | D11: =COUNTIFS(Inventario!$N$2:$N$1000,$A11,Inventario!$Q$2:$Q$1000,"3*",Inventario!$D$2:$D$1000,"<>Internacional") -> 15 | E11: =COUNTIFS(Inventario!$N$2:$N$1000,$A11,Inventario!$Q$2:$Q$1000,"4*",Inventario!$D$2:$D$1000,"<>Internacional") -> 4 | F11: =SUM(B11:E11) -> 24 | G11: =COUNTIFS(Inventario!$N$2:$N$1000,$A11,Inventario!$D$2:$D$1000,"Internacional") -> 1
A12: Territorio, vivienda y movilidad | B12: =COUNTIFS(Inventario!$N$2:$N$1000,$A12,Inventario!$Q$2:$Q$1000,"1*",Inventario!$D$2:$D$1000,"<>Internacional") -> 0 | C12: =COUNTIFS(Inventario!$N$2:$N$1000,$A12,Inventario!$Q$2:$Q$1000,"2*",Inventario!$D$2:$D$1000,"<>Internacional") -> 0 | D12: =COUNTIFS(Inventario!$N$2:$N$1000,$A12,Inventario!$Q$2:$Q$1000,"3*",Inventario!$D$2:$D$1000,"<>Internacional") -> 15 | E12: =COUNTIFS(Inventario!$N$2:$N$1000,$A12,Inventario!$Q$2:$Q$1000,"4*",Inventario!$D$2:$D$1000,"<>Internacional") -> 2 | F12: =SUM(B12:E12) -> 17 | G12: =COUNTIFS(Inventario!$N$2:$N$1000,$A12,Inventario!$D$2:$D$1000,"Internacional") -> 0
A13: Estado, gobierno y derechos | B13: =COUNTIFS(Inventario!$N$2:$N$1000,$A13,Inventario!$Q$2:$Q$1000,"1*",Inventario!$D$2:$D$1000,"<>Internacional") -> 5 | C13: =COUNTIFS(Inventario!$N$2:$N$1000,$A13,Inventario!$Q$2:$Q$1000,"2*",Inventario!$D$2:$D$1000,"<>Internacional") -> 4 | D13: =COUNTIFS(Inventario!$N$2:$N$1000,$A13,Inventario!$Q$2:$Q$1000,"3*",Inventario!$D$2:$D$1000,"<>Internacional") -> 8 | E13: =COUNTIFS(Inventario!$N$2:$N$1000,$A13,Inventario!$Q$2:$Q$1000,"4*",Inventario!$D$2:$D$1000,"<>Internacional") -> 6 | F13: =SUM(B13:E13) -> 23 | G13: =COUNTIFS(Inventario!$N$2:$N$1000,$A13,Inventario!$D$2:$D$1000,"Internacional") -> 5
A14: Total | B14: =SUM(B6:B13) -> 15 | C14: =SUM(C6:C13) -> 29 | D14: =SUM(D6:D13) -> 60 | E14: =SUM(E6:E13) -> 44 | F14: =SUM(F6:F13) -> 148 | G14: =SUM(G6:G13) -> 22
A17: Ámbito
A18: Ámbito | B18: Recursos | C18: Con vigencia comprobada | D18: % vigencia
A19: Nacional | B19: =COUNTIF(Inventario!$D$2:$D$1000,A19) -> 129 | C19: =COUNTIFS(Inventario!$D$2:$D$1000,A19,Inventario!$W$2:$W$1000,"Sí") -> 45 | D19: =IF(B19=0,0,C19/B19) -> 0.34883721
A20: Departamental | B20: =COUNTIF(Inventario!$D$2:$D$1000,A20) -> 19 | C20: =COUNTIFS(Inventario!$D$2:$D$1000,A20,Inventario!$W$2:$W$1000,"Sí") -> 1 | D20: =IF(B20=0,0,C20/B20) -> 0.052631579
A21: Internacional | B21: =COUNTIF(Inventario!$D$2:$D$1000,A21) -> 22 | C21: =COUNTIFS(Inventario!$D$2:$D$1000,A21,Inventario!$W$2:$W$1000,"Sí") -> 3 | D21: =IF(B21=0,0,C21/B21) -> 0.13636364
A22: Total | B22: =SUM(B19:B21) -> 170 | C22: =SUM(C19:C21) -> 49 | D22: =IF(B22=0,0,C22/B22) -> 0.28823529
A25: Tipo de recurso | D25: Instituciones con más recursos
A26: Tipo | B26: Recursos | D26: Institución | E26: Recursos
A27: Observatorio | B27: =COUNTIF(Inventario!$F$2:$F$1000,A27) -> 35 | D27: Intendencia de Montevideo | E27: =COUNTIF(Inventario!$C$2:$C$1000,D27) -> 15
A28: Portal estadístico | B28: =COUNTIF(Inventario!$F$2:$F$1000,A28) -> 22 | D28: OPP | E28: =COUNTIF(Inventario!$C$2:$C$1000,D28) -> 5
A29: Módulo | B29: =COUNTIF(Inventario!$F$2:$F$1000,A29) -> 20 | D29: Uruguay XXI | E29: =COUNTIF(Inventario!$C$2:$C$1000,D29) -> 4
A30: Geoportal | B30: =COUNTIF(Inventario!$F$2:$F$1000,A30) -> 19 | D30: Ministerio de Ambiente | E30: =COUNTIF(Inventario!$C$2:$C$1000,D30) -> 4
A31: Monitor | B31: =COUNTIF(Inventario!$F$2:$F$1000,A31) -> 14 | D31: Instituto Nacional de Estadística | E31: =COUNTIF(Inventario!$C$2:$C$1000,D31) -> 4
A32: Repositorio estadístico | B32: =COUNTIF(Inventario!$F$2:$F$1000,A32) -> 12 | D32: Universidad Católica del Uruguay | E32: =COUNTIF(Inventario!$C$2:$C$1000,D32) -> 3
A33: Base de datos | B33: =COUNTIF(Inventario!$F$2:$F$1000,A33) -> 10 | D33: Ministerio de Salud Pública | E33: =COUNTIF(Inventario!$C$2:$C$1000,D33) -> 3
A34: Visualizador | B34: =COUNTIF(Inventario!$F$2:$F$1000,A34) -> 6 | D34: Ministerio de Ambiente / DINAGUA | E34: =COUNTIF(Inventario!$C$2:$C$1000,D34) -> 3
A35: Portal de datos | B35: =COUNTIF(Inventario!$F$2:$F$1000,A35) -> 6 | D35: INIA | E35: =COUNTIF(Inventario!$C$2:$C$1000,D35) -> 3
A36: Plataforma de comparación internacional | B36: =COUNTIF(Inventario!$F$2:$F$1000,A36) -> 5 | D36: MVOT / DINOT | E36: =COUNTIF(Inventario!$C$2:$C$1000,D36) -> 3
A37: Portal de indicadores | B37: =COUNTIF(Inventario!$F$2:$F$1000,A37) -> 4 | D37: ANEP | E37: =COUNTIF(Inventario!$C$2:$C$1000,D37) -> 3
A38: Índice compuesto | B38: =COUNTIF(Inventario!$F$2:$F$1000,A38) -> 4 | D38: MGAP | E38: =COUNTIF(Inventario!$C$2:$C$1000,D38) -> 2
... A41: Catálogo de datos | B41: =COUNTIF(Inventario!$F$2:$F$1000,A41) -> 3 | D41: Intendencia de Rivera | E41: =COUNTIF(Inventario!$C$2:$C$1000,D41) -> 2
A42: Directorio de herramientas | B42: =COUNTIF(Inventario!$F$2:$F$1000,A42) -> 2
A43: Catálogo institucional | B43: =COUNTIF(Inventario!$F$2:$F$1000,A43) -> 1
A44: Portal temático | B44: =COUNTIF(Inventario!$F$2:$F$1000,A44) -> 1

Sheet Taxonomía temas
A1: Código | B1: Etiqueta (lista) | C1: Área (código) | D1: Área | E1: Tema | F1: ODS principal | G1: Nombre ODS | H1: Metas ODS de referencia | I1: Sinónimos de búsqueda | J1: Término Catálogo AGESIC | L1: Código área | M1: Área
A2: T01 | B2: T01 · Macroeconomía y cuentas nacionales | C2: A1 | D2: Economía y producción | E2: Macroeconomía y cuentas nacionales | F2: 8 | G2: Trabajo decente y crecimiento económico | H2: 8.1; 17.13 | I2: pbi; producto interno bruto; pib; cuentas nacionales; actividad económica; crecimiento; coyuntura; macroeconomía; inflación; tipo de cambio; monetario; financiero; bcu | J2: pbi | L2: A1 | M2: Economía y producción
A3: T02 | B3: T02 · Finanzas públicas, tributación y presupuesto | C3: A1 | D3: Economía y producción | E3: Finanzas públicas, tributación y presupuesto | F3: 17 | G3: Alianzas para lograr los objetivos | H3: 17.1; 16.6 | I3: finanzas públicas; fiscal; déficit; deuda pública; impuestos; recaudación; tributación; presupuesto; gasto público; dgi | J3: finanzas públicas | L3: A2 | M3: Trabajo y protección social
A4: T03 | B4: T03 · Comercio exterior e inversión | C4: A1 | D4: Economía y producción | E4: Comercio exterior e inversión | F4: 17 | G4: Alianzas para lograr los objetivos | H4: 17.11; 8.2 | I4: exportaciones; importaciones; comercio exterior; aduanas; inversión extranjera; ied; mercados; destinos; balanza comercial | J4: exportaciones | L4: A3 | M4: Salud y población
A5: T04 | B5: T04 · Agro y cadenas agroindustriales | C5: A1 | D5: Economía y producción | E5: Agro y cadenas agroindustriales | F5: 2 | G5: Hambre cero | H5: 2.3; 2.4 | I5: agro; agropecuario; ganadería; carne; lechería; agricultura; soja; granos; forestación; vitivinicultura; horticultura; frutas; tierras; censo agropecuario | J5: agro | L5: A4 | M5: Educación, cultura y deporte
A6: T05 | B6: T05 · Industria y manufactura | C6: A1 | D6: Economía y producción | E6: Industria y manufactura | F6: 9 | G6: Industria, innovación e infraestructura | H6: 9.2 | I6: industria; manufactura; producción industrial; industrial; fábricas | J6: industria | L6: A5 | M6: Ciencia, tecnología e innovación
A7: T06 | B7: T06 · Turismo | C7: A1 | D7: Economía y producción | E7: Turismo | F7: 8 | G7: Trabajo decente y crecimiento económico | H7: 8.9 | I7: turismo; turistas; visitantes; cruceros; gasto turístico; hotelería | J7: turismo | L7: A6 | M7: Ambiente, energía y clima
A8: T07 | B8: T07 · Empresas, mipymes y emprendimiento | C8: A1 | D8: Economía y producción | E8: Empresas, mipymes y emprendimiento | F8: 8 | G8: Trabajo decente y crecimiento económico | H8: 8.3; 9.3 | I8: empresas; mipymes; pymes; pequeñas empresas; emprendimiento; emprendedores; startups; financiamiento empresarial; microfinanzas; registro de empresas | J8: empresas | L8: A7 | M8: Territorio, vivienda y movilidad
A9: T08 | B9: T08 · Logística, transporte de cargas e infraestructura | C9: A1 | D9: Economía y producción | E9: Logística, transporte de cargas e infraestructura | F9: 9 | G9: Industria, innovación e infraestructura | H9: 9.1 | I9: logística; puertos; cargas; infraestructura; rutas; carreteras; obras públicas; transporte de carga | J9: logística | L9: A8 | M9: Estado, gobierno y derechos
A10: T09 | B10: T09 · Precios, consumo y construcción | C10: A1 | D10: Economía y producción | E10: Precios, consumo y construcción | F10: 12 | G10: Producción y consumo responsables | H10: 12.8; 8.1 | I10: precios; ipc; consumo; consumidores; construcción; mercado inmobiliario; alquileres; compraventas; inmuebles | J10: precios
A11: T10 | B11: T10 · Telecomunicaciones y sociedad digital | C11: A5 | D11: Ciencia, tecnología e innovación | E11: Telecomunicaciones y sociedad digital | F11: 9 | G11: Industria, innovación e infraestructura | H11: 9.c; 17.6; 17.8 | I11: telecomunicaciones; internet; conectividad; banda ancha; tic; digital; uso de tecnologías; brecha digital; gobierno digital | J11: telecomunicaciones
A12: T11 | B12: T11 · Investigación, ciencia e innovación | C12: A5 | D12: Ciencia, tecnología e innovación | E12: Investigación, ciencia e innovación | F12: 9 | G12: Industria, innovación e infraestructura | H12: 9.5; 9.b | I12: cti; ciencia; tecnología; innovación; i+d; investigación; investigadores; gasto en i+d; publicaciones científicas; bibliometría; capacidades de innovación; complejidad económica; inteligencia artificial; ia | J12: cti
A13: T12 | B13: T12 · Propiedad intelectual | C13: A5 | D13: Ciencia, tecnología e innovación | E13: Propiedad intelectual | F13: 9 | G13: Industria, innovación e infraestructura | H13: 9.5; 9.b | I13: patentes; marcas; propiedad intelectual; propiedad industrial; dnpi; diseños industriales | J13: patentes
A14: T13 | B14: T13 · Sector tecnológico y software | C14: A5 | D14: Ciencia, tecnología e innovación | E14: Sector tecnológico y software | F14: 9 | G14: Industria, innovación e infraestructura | H14: 9.c; 8.2 | I14: software; empresas tecnológicas; sector ti; tecnologías de la información; servicios tecnológicos; talento digital | J14: software
A15: T14 | B15: T14 · Empleo y mercado de trabajo | C15: A2 | D15: Trabajo y protección social | E15: Empleo y mercado de trabajo | F15: 8 | G15: Trabajo decente y crecimiento económico | H15: 8.5; 8.6 | I15: empleo; desempleo; trabajo; mercado laboral; mercado de trabajo; ocupación; salarios; informalidad; desocupación; ech; encuesta continua de hogares | J15: empleo
A16: T15 | B16: T15 · Salud y seguridad laboral | C16: A2 | D16: Trabajo y protección social | E16: Salud y seguridad laboral | F16: 8 | G16: Trabajo decente y crecimiento económico | H16: 8.8 | I16: accidentes de trabajo; salud laboral; seguridad laboral; siniestralidad laboral; enfermedades profesionales | J16: accidentes de trabajo
A17: T16 | B17: T16 · Seguridad social y pensiones | C17: A2 | D17: Trabajo y protección social | E17: Seguridad social y pensiones | F17: 1 | G17: Fin de la pobreza | H17: 1.3 | I17: seguridad social; jubilaciones; pensiones; prestaciones; cotizantes; bps; previsión social | J17: seguridad social
A18: T17 | B18: T17 · Pobreza, desigualdad y condiciones de vida | C18: A2 | D18: Trabajo y protección social | E18: Pobreza, desigualdad y condiciones de vida | F18: 1 | G18: Fin de la pobreza | H18: 1.2; 10.1; 10.2 | I18: pobreza; indigencia; desigualdad; ingresos de los hogares; condiciones de vida; vulnerabilidad; políticas sociales | J18: pobreza
A19: T18 | B19: T18 · Protección social y servicios sociales | C19: A2 | D19: Trabajo y protección social | E19: Protección social y servicios sociales | F19: 1 | G19: Fin de la pobreza | H19: 1.3; 10.4 | I19: protección social; programas sociales; servicios sociales; inau; transferencias; asistencia social | J19: protección social
A20: T19 | B20: T19 · Cuidados | C20: A2 | D20: Trabajo y protección social | E20: Cuidados | F20: 5 | G20: Igualdad de género | H20: 5.4 | I20: cuidados; sistema de cuidados; cuidado infantil; dependencia; asistentes personales; trabajo no remunerado | J20: cuidados
A21: T20 | B21: T20 · Alimentación y nutrición | C21: A2 | D21: Trabajo y protección social | E21: Alimentación y nutrición | F21: 2 | G21: Hambre cero | H21: 2.1; 2.2 | I21: alimentación; nutrición; seguridad alimentaria; inseguridad alimentaria; hambre; malnutrición; obesidad; derecho a la alimentación | J21: alimentación
... A54: T53 | B54: T53 · Integridad y prevención de la corrupción | C54: A8 | D54: Estado, gobierno y derechos | E54: Integridad y prevención de la corrupción | F54: 16 | G54: Paz, justicia e instituciones sólidas | H54: 16.5 | I54: corrupción; integridad; ética pública; declaraciones juradas; jutep; lavado de activos | J54: corrupción

Sheet Enfoques
A1: Código | B1: Etiqueta | C1: Enfoque | D1: ODS asociado | E1: Sinónimos de búsqueda
A2: E01 | B2: E01 · Género | C2: Género | D2: 5 | E2: género; mujeres; igualdad de género; brecha de género; violencia de género; violencia basada en género; feminismo; paridad; varones
A3: E02 | B3: E02 · Infancia y adolescencia | C3: Infancia y adolescencia | D3: 4 | E3: infancia; niñez; niños; niñas; adolescencia; adolescentes; primera infancia
A4: E03 | B4: E03 · Juventud | C4: Juventud | D4: 8 | E4: juventud; jóvenes; ni-ni
A5: E04 | B5: E04 · Personas mayores y envejecimiento | C5: Personas mayores y envejecimiento | D5: 1 | E5: vejez; personas mayores; adultos mayores; envejecimiento; tercera edad
A6: E05 | B6: E05 · Discapacidad | C6: Discapacidad | D6: 10 | E6: discapacidad; personas con discapacidad; accesibilidad; inclusión
A7: E06 | B7: E06 · Migración | C7: Migración | D7: 10 | E7: migración; migrantes; población migrante
A8: E07 | B8: E07 · Afrodescendencia y etnia-raza | C8: Afrodescendencia y etnia-raza | D8: 10 | E8: afrodescendientes; afro; étnico-racial; racismo
A9: E08 | B9: E08 · Enfoque de derechos | C9: Enfoque de derechos | D9: 16 | E9: derechos; enfoque de derechos; derechos humanos
A10: E09 | B10: E09 · Territorial y subnacional | C10: Territorial y subnacional | D10: 11 | E10: departamental; municipal; local; frontera; subnacional; regional
A12: Regla de asignación | B12: Un enfoque transversal se asigna cuando el recurso tiene un módulo, conjunto de indicadores o línea de publicaciones dedicada al enfoque, o lo declara entre sus objetivos. La sola posibilidad de desagregar una variable (por ejemplo, por sexo) se registra en Desagregación y no habilita el enfoque.

Sheet Niveles
A1: Nivel | B1: Etiqueta (lista) | C1: Nombre | D1: Definición | E1: Tipos de recurso asignados por defecto
A2: 1 | B2: 1 · Datos | C2: Datos | D2: Bases, microdatos o conjuntos de datos para procesamiento propio. | E2: Catálogo de datos, Catálogo institucional, Repositorio de datos, Base de datos, Portal de datos
A3: 2 | B3: 2 · Indicadores y series | C3: Indicadores y series | D3: Indicadores, tabulados o series ya calculados. | E3: Portal estadístico, Repositorio estadístico, Portal de indicadores, Portal temático, Índice compuesto
A4: 3 | B4: 3 · Visualización interactiva | C4: Visualización interactiva | D4: Tableros, monitores, visores o mapas con consulta interactiva. | E4: Visualizador, Geoportal, Monitor, Módulo, Directorio de herramientas, Plataforma de comparación internacional
A5: 4 | B5: 4 · Análisis e informes | C5: Análisis e informes | D5: Producción interpretativa recurrente: informes, estudios, boletines con análisis. | E5: Observatorio, Observatorio de estudios

Sheet Por confirmar
A1: Iniciativa no sumada al inventario | B1: Responsable / ámbito | C1: Motivo y verificación pendiente | D1: Referencia | E1: Incorporación
A2: Observatorio de discapacidad — Uruguay sin barreras | B2: MIDES | C2: El plan y sus ejes prevén observatorio y visualizador. No se confirmó aquí un portal público operativo diferenciado. | D2: https://www.gub.uy/ministerio-desarrollo-social/uruguay-sin-barreras/ejes/datos-estadisticas | E2: Relevamiento 02/10/2026
A3: Observatorio de derechos de personas con discapacidad | B3: INDDHH | C3: Se localizaron referencias a diseño y desarrollo; acceso público a datos no confirmado. | D3: https://www.gub.uy/institucion-nacional-derechos-humanos-uruguay/node/3033 | E3: Relevamiento 02/10/2026
A4: Observatorio de cooperativismo | B4: INACOOP | C4: Referencia a una propuesta; no se confirmó un monitor público operativo. | D4: https://www.gub.uy/agencia-uruguaya-cooperacion-internacional/comunicacion/noticias/instituciones-sociedad-civil-valoraron-acciones-del-cooperativismo-factor | E4: Relevamiento 02/10/2026
A5: Visualizador de valorización de materiales | B5: CEMPRE | C5: Se encontró un sitio de pruebas; no se incorporó como portal de producción. | D5: https://cempre.stage.data.org.uy/comprador/2 | E5: Relevamiento 02/10/2026
A6: Observatorio social de la Región Este | B6: Ámbito regional / Udelar | C6: Referencia histórica a una iniciativa; continuidad y acceso actual no comprobados. | D6: https://www.gub.uy/presidencia/comunicacion/noticias/opp-apoya-observatorio-social-territorial-para-mejor-desarrollo-politicas | E6: Relevamiento 02/10/2026
A7: Sistema Nacional de Investigadores — estadísticas | B7: ANII | C7: Se localizaron informes de monitoreo del SNI (2008-2018); no se confirmó un tablero público actualizado con datos del sistema. | D7: https://anii.org.uy/upcms/files/listado-documentos/documentos/informe-de-monitoreo-sistema-nacional-de-investigadores-2008-2018.pdf | E7: Corte 08/10/2026
A8: SII-CTI — Sistema Integrado de Información de CTI | B8: UNE-CTI / Uruguay Innova | C8: Sistema en diseño e implementación; sin portal público al corte. | E8: Corte 08/10/2026
A9: Sistema de información cultural | B9: MEC | C9: Compromiso de gobierno abierto sobre datos culturales (UY0186); no se confirmó un portal público operativo. | D9: https://www.opengovpartnership.org/es/members/uruguay/commitments/UY0186/ | E9: Corte 08/10/2026
A10: Observatorio de vivienda | B10: MVOT | C10: No se localizó un observatorio o tablero propio de vivienda; parte de la información está en el Observatorio Territorial DINOT. | E10: Corte 08/10/2026

Sheet Metodología
A1: Metodología
A2: Criterios del relevamiento original (02/10/2026) y criterios de clasificación agregados (08/10/2026).
A4: Criterios del relevamiento
A5: Alcance | B5: Relevamiento web de observatorios, monitores, portales estadísticos, catálogos, geoportales y colecciones estadísticas institucionales sobre Uruguay. Corte: 02/10/2026.
A6: Unidad de registro | B6: Cada fila es un recurso. Un portal puede tener módulos o herramientas vinculadas, identificados en la columna Portal o sistema relacionado. El total no representa portales independientes.
A7: Cobertura institucional | B7: Organismos nacionales, gobiernos departamentales, entidades públicas no estatales, universidades, cámaras, sociedad civil y algunas secciones de organismos internacionales dedicadas a Uruguay.
A8: Criterio de inclusión | B8: Información organizada para consultar indicadores, mapas, bases, series, estudios recurrentes o seguimiento institucional. Los observatorios de estudios están identificados aunque no tengan una base numérica permanente.
A9: Exclusiones | B9: No se inventariaron cada dataset del catálogo nacional, cada gráfico de un tablero, bibliotecas generales, repositorios bibliográficos ni noticias o PDF aislados como recursos independientes.
A10: Período de datos | B10: Es el período más reciente que se pudo comprobar en las fuentes consultadas. Si corresponde solo a una serie o informe, se indica. No asegura que sea el último dato de todo el portal.
A11: Fecha de publicación | B11: Campo separado de la fecha de datos. Se conserva únicamente cuando fue posible identificar una fecha exacta; las celdas vacías significan no comprobada.
A12: No comprobado | B12: No se pudo establecer un último corte fiable. No significa que el portal esté desactualizado, vacío o inactivo. No se usaron fechas de rastreo del buscador, copyright ni horizontes de metas como fecha de datos.
A13: Enlaces y acceso | B13: Se priorizó la URL directa. Cuando fue necesario se utilizó una entrada o ficha institucional con acceso a la herramienta. Localizarla no implica haber probado todos los filtros, descargas, API o funciones autenticadas.
A14: Fuentes | B14: Cada fila incluye las páginas que sustentan su incorporación y, cuando procede, el período o fecha informado. Se consultaron páginas oficiales, directorios y resultados web indexados; la evidencia tiene distinto nivel de detalle.
A15: Categorías y etiquetas | B15: Una categoría principal por fila para evitar doble conteo. Las etiquetas permiten clasificación transversal. Energía se agrupa con ambiente; trabajo, cuidados y protección social con social y salud.
A16: Naturaleza institucional | B16: Clasificación descriptiva del responsable, no dictamen jurídico. Académico incluye universidades públicas y privadas. Dos observatorios con responsable no corroborado se marcan expresamente.
... A19: Cómo actualizar | B19: Abrir el recurso y sus fuentes; comprobar la última serie disponible; anotar por separado período y publicación; revisar institución, acceso y vínculo con otros portales antes de agregar una fila.
A21: Criterios de clasificación
A22: Modelo en facetas | B22: Cada recurso se describe con tres facetas independientes: tema sectorial (un tema principal y temas secundarios), enfoque transversal y desagregación disponible. Las facetas permiten que un mismo recurso aparezca en búsquedas de distinto tipo sin duplicar filas.
A23: Tema principal | B23: El dominio sustantivo dominante del recurso. Determina el área, el ODS principal y el conteo de concentración. Un recurso tiene un solo tema principal.
A24: Temas secundarios | B24: Otros dominios con información relevante y visible en el recurso. Amplían el alcance de la búsqueda y del conteo de cobertura indirecta.
A25: Enfoque transversal | B25: Un enfoque transversal se asigna cuando el recurso tiene un módulo, conjunto de indicadores o línea de publicaciones dedicada al enfoque, o lo declara entre sus objetivos. La sola posibilidad de desagregar una variable (por ejemplo, por sexo) se registra en Desagregación y no habilita el enfoque.
A26: Correspondencia ODS | B26: Cada tema se vincula con un ODS principal y metas de referencia. La cobertura se mide a nivel de tema y se agrega por ODS, lo que permite comparar con marcos internacionales sin perder detalle.
A27: Temas de referencia para vacíos | B27: La taxonomía incluye temas asociados a metas ODS con relevancia de política pública aunque no figuren en el inventario (pesca, inclusión financiera, salud mental, integridad). Sin esos temas de referencia el análisis no podría mostrar vacíos.
A28: Nivel de análisis | B28: Escala de 1 a 4 (datos, indicadores y series, visualización interactiva, análisis e informes). Se asigna por defecto según el tipo de recurso y se ajusta a 4 cuando el recurso produce informes interpretativos recurrentes. Es una clasificación provisoria a validar recurso por recurso.
A29: Acceso y desagregación | B29: Descarga, API y desagregaciones se marcan como Sí solo cuando la descripción o la fuente lo confirman. Por verificar indica ausencia de comprobación, no ausencia de la funcionalidad.
A30: Estados de cobertura | B30: Con análisis: al menos un recurso nacional de nivel 4. Sin análisis: hay recursos con el tema como principal y ninguno de nivel 4. Indirecta: el tema solo aparece como secundario. Sin cobertura: ningún recurso nacional, con o sin referencias internacionales. Alta concentración: cinco o más recursos con el tema como principal.
A31: Referencias internacionales | B31: Plataformas de organismos y redes internacionales con datos comparables de Uruguay. Se registran con ámbito Internacional y se cuentan aparte para no inflar la cobertura nacional.
A32: Capa AGESIC | B32: El Catálogo Nacional de Datos Abiertos se enlaza por tema mediante un término de búsqueda. El conteo automático de datasets por tema queda previsto para el sitio mediante la API pública del catálogo.
A33: Limitaciones del corte 08/10/2026 | B33: La clasificación fue hecha a partir de nombre, descripción y etiquetas del relevamiento, sin abrir cada recurso. Las URL de referencias internacionales marcadas como de referencia no fueron verificadas en este corte.

Sheet Listas
A1: Ámbito | B1: Sí/No
A2: Nacional | B2: Sí
A3: Departamental | B3: No
A4: Internacional | B4: Por verificar
